Workbook

Sheet 0_條件與假設
A1: 秀泰新辦公室（總部）選址分析 — 2026-09-24 新條件重跑
A2: 資料日期：2026-09-24。所有數字照來源原文；未揭露的欄位留空並以淺橘底標示，不估算。藍字＝輸入值，黑字＝公式。
A4: 項目 | B4: 數值 | C4: 說明
A5: 實坪門檻（坪，主建物＋附屬，不含公設） | B5: 220 | C5: 使用者條件：「實際」坪數約220坪起
A6: 理想月租上限（元，含稅） | B6: 450000 | C6: 使用者條件：45萬內
A7: 月租硬上限（元，含稅） | B7: 550000 | C7: 使用者條件：左右不要超過55萬
A8: 捷運步行門檻（分鐘） | B8: 10 | C8: 捷運以綠(松山新店)／紅(淡水信義)／藍(板南)為主；步行分＝直線距離×1.3÷80m
A9: 營業稅率 | B9: 0.05 | C9: 未稅價×1.05換算含稅
A11: 分級規則
A12: 第一優先 | B12: 實坪≥220（有謄本／物調表／房仲頁分項）＋ 月租≤45萬 ＋ 五區內 ＋ 綠紅藍線步行≤10分
A13: 第二優先 | B13: 實坪≥220 已確認 ＋ 月租≤55萬；捷運可為11～16分（標示）
A14: 待確認實坪 | B14: 權狀≥240坪、月租≤55萬、交通可，但實坪未揭露 → 需向仲介索取謄本／物調表
A15: 不符合 | B15: 實坪<220、權狀<240且無分項、月租>55萬、地下室／1樓、非五區、大直、附近無綠紅藍線
A17: 本輪結果
A18: 第一優先 | B18: =COUNTIF(A_總表!A:A,"第一優先") -> 1
A19: 第二優先 | B19: =COUNTIF(A_總表!A:A,"第二優先") -> 5
A20: 待確認實坪 | B20: =COUNTIF(A_總表!A:A,"待確認實坪") -> 13
A21: 不符合 | B21: =COUNTIF(A_總表!A:A,"不符合") -> 61
A22: 合計 | B22: =SUM(B18:B21) -> 80
A24: 分頁說明
A25: A_總表 | B25: 全部案件（新增＋上一版），依新條件分級排序；含公式驗算欄
A26: B_優先案詳情 | B26: 第一／第二優先與待確認案的完整資料、來源、聯絡人、缺漏
A27: C_待確認清單 | B27: 每一案還缺什麼、該問誰
A28: D_捷運距離 | B28: 每案最近綠／紅／藍線站、距離與計算依據
A29: E_591篩選紀錄 | B29: 591 商辦 116 筆逐筆對應到案號
A30: F_尚揚物調表 | B30: 尚揚國際提供 7 份物調表原文數字
A31: G_傑森愛華0923清單 | B31: 傑森愛華 2026/9/23 清單 13 筆原文＋對應
A32: H_搜尋範圍與來源 | B32: 各網站搜尋條件、筆數、被擋情形
A33: P_精選案件 | B33: Kevina 指定的精選案件（9/30、10/12 提供；10/12 重新查核刊登狀態）並排比較，含未達條件的案件與原因

Sheet P_精選案件
A1: Kevina 推薦的 18 案 — 並排比較
A2: 依使用者指定的連結整理（9/30 給 8 個、10/12 再給 12 個，其中 2 個與既有案同戶）；10/12 全部重新查核刊登狀態。分級仍依原條件，未達條件的案件排在後面，原因見最後一欄。藍字＝來源原文數字，黑字＝公式；淺橘底＝未揭露／有變動。月總成本只在管理費有數字時計算。
A4: 案號 | B4: 案名 | C4: 分級 | D4: 行政區 | E4: 地址 | F4: 樓層 | G4: 權狀坪 | H4: 實坪 (主+附) | I4: 月租(含稅) | J4: 租金原文／稅別 | K4: 管理費(月) | L4: 月總成本 (公式) | M4: 每權狀坪月租 (公式) | N4: 實坪≥門檻 (公式) | O4: 租金級距 (公式) | P4: 最近綠紅藍站 | Q4: 路線 | R4: 距離(m) | S4: 步行(分) | T4: 捷運判定 (公式) | U4: 屋況／廁所 | V4: 租期 | W4: 押金 | X4: 刊登查核 | Y4: 缺漏／待確認 | Z4: 聯絡人 | AA4: 您提供的連結 | AB4: Google 地圖 | AC4: 判定說明（未達條件原因）
A5: N04 | B5: 信義大樓 10F | C5: 第二優先 | D5: 信義 | E5: 松仁路（信義大樓） | F5: 10F/23F | G5: 330.22 | H5: 300.43 | I5: 480000 | J5: 480,000（591 21537848，稅別未寫）；同戶信義房屋刊登577,885；⚠ 9/30 591 21537848 已下架，信義 C904200 現刊 577,885 | K5: 49533 | L5: =IF(OR(I5="",K5=""),"管理費缺",I5+K5) -> 529533 | M5: =IF(OR(I5="",G5=""),"",I5/G5) -> 1453.5764 | N5: =IF(H5="","未揭露",IF(H5>=0_條件與假設!$B$5,"✓","✗")) -> ✓ | O5: =IF(I5="","未提供",IF(I5<=0_條件與假設!$B$6,"≤45萬",IF(I5<=0_條件與假設!$B$7,"45～55萬","超過55萬"))) -> 45～55萬 | P5: 象山 | Q5: 紅 | R5: 950 | S5: 16 | T5: =IF(S5="","未確認",IF(S5<=0_條件與假設!$B$8,"✓",IF(S5<=16,"△ 11～16分","✗"))) -> △ 11～16分 | U5: 廁所新：廁所為新裝修（信義房屋 C904200 照片 C：檯面式洗手台、木紋隔間）；辦公區天花為開放式未封板。 | V5: 591：兩年 | W5: — | X5: 9/30：信義 C904200 刊登中，577,885／權狀330.22坪（與前次相同）；⚠ 591 21537848（48萬）已下架；10/12 再查：信義 C904200 仍為 577,885；591 21537848 仍下架 | Y5: 591 48萬刊登已下架（9/30），現存刊登為信義 577,885（超過55萬）；租金稅別未寫；兩方報價不同 | Z5: 傑森愛華 張先生 0931-330-823 | AA5: 開啟 | AB5: 開啟地圖 | AC5: 坪數符合；實坪300.43 · 月租48.0萬（45～55萬） · 捷運象山(紅) 16分（>10分）
A6: N08 | B6: 松江路 3F（松江南京站） | C6: 待確認實坪 | D6: 中山 | E6: 松江路 | F6: 3F/12F | G6: 302 | I6: 540837 | J6: 515,083 未含營業稅（591 21635155）→ 含稅 540,837 | L6: =IF(OR(I6="",K6=""),"管理費缺",I6+K6) -> 管理費缺 | M6: =IF(OR(I6="",G6=""),"",I6/G6) -> 1790.851 | N6: =IF(H6="","未揭露",IF(H6>=0_條件與假設!$B$5,"✓","✗")) -> 未揭露 | O6: =IF(I6="","未提供",IF(I6<=0_條件與假設!$B$6,"≤45萬",IF(I6<=0_條件與假設!$B$7,"45～55萬","超過55萬"))) -> 45～55萬 | P6: 松江南京 | Q6: 綠 | R6: 156 | S6: 3 | T6: =IF(S6="","未確認",IF(S6<=0_條件與假設!$B$8,"✓",IF(S6<=16,"△ 11～16分","✗"))) -> ✓ | U6: 廁所無照片：591 只有 1 張照片（捷運出口），室內與廁所都沒有拍。需現勘。 | V6: 一年 | W6: 面議 | X6: 9/30：591 22017413 刊登中，515,083（未稅）／302.99坪；同戶 21635155 也仍刊登；10/12 再查：22017413、21635155 仍刊登，515,083 | Y6: 實坪未揭露；管理費未提供；廁所需現勘 | Z6: 東家國際 蔡泳翰 0912-816-677；兆淇 鄭先生 0960-539-161 | AA6: 開啟 | AB6: 開啟地圖 | AC6: 待確認：實坪未揭露（權狀302坪）；已符合：月租54.1萬（45～55萬） · 松江南京(綠) 3分
A7: S11 | B7: 八德大樓 5F（出租285.67坪） | C7: 待確認實坪 | D7: 中山 | E7: 八德路二段 | F7: 5F/12F | G7: 285.67 | I7: 428505 | J7: 428,505（信義刊登）；591 21804249 285坪 427,500（1,500/坪） | K7: 47136 | L7: =IF(OR(I7="",K7=""),"管理費缺",I7+K7) -> 475641 | M7: =IF(OR(I7="",G7=""),"",I7/G7) -> 1500 | N7: =IF(H7="","未揭露",IF(H7>=0_條件與假設!$B$5,"✓","✗")) -> 未揭露 | O7: =IF(I7="","未提供",IF(I7<=0_條件與假設!$B$6,"≤45萬",IF(I7<=0_條件與假設!$B$7,"45～55萬","超過55萬"))) -> ≤45萬 | P7: 忠孝復興 | Q7: 藍 | R7: 620 | S7: 11 | T7: =IF(S7="","未確認",IF(S7<=0_條件與假設!$B$8,"✓",IF(S7<=16,"△ 11～16分","✗"))) -> △ 11～16分 | U7: 廁所新：廁所新裝修（信義 CZ05585 照片 D、G：石材檯面、新式小便斗、木紋隔間）；茶水間新（照片 J）；電梯廳石材。 | V7: — | W7: — | X7: 9/30：信義 CZ05585 刊登中，428,505／出租285.67坪（與前次相同）；10/12 再查：CZ05585 仍為 428,505／285.67坪 | Y7: 出租部分實坪未揭露；稅別未寫 | Z7: 信義 林嘉君 0912-313-517 | AA7: 開啟 | AB7: 開啟地圖 | AC7: 待確認：實坪未揭露（權狀285.67坪） · 捷運忠孝復興(藍) 11分（>10分）；已符合：月租42.9萬
A8: N10 | B8: 光復北路11巷 2F（南京三民站） | C8: 待確認實坪 | D8: 松山 | E8: 光復北路11巷 | F8: 2F/14F | G8: 283 | I8: 534870 | J8: 509,400 未稅（591 22062249、傑森愛華清單第2頁）→ 含稅 534,870 | L8: =IF(OR(I8="",K8=""),"管理費缺",I8+K8) -> 管理費缺 | M8: =IF(OR(I8="",G8=""),"",I8/G8) -> 1890 | N8: =IF(H8="","未揭露",IF(H8>=0_條件與假設!$B$5,"✓","✗")) -> 未揭露 | O8: =IF(I8="","未提供",IF(I8<=0_條件與假設!$B$6,"≤45萬",IF(I8<=0_條件與假設!$B$7,"45～55萬","超過55萬"))) -> 45～55萬 | P8: 南京三民 | Q8: 綠 | R8: 88 | S8: 2 | T8: =IF(S8="","未確認",IF(S8<=0_條件與假設!$B$8,"✓",IF(S8<=16,"△ 11～16分","✗"))) -> ✓ | U8: 廁所無照片：591 只有 2 張（空室、捷運站），沒有拍廁所。需現勘。 | V8: 3年 | W8: 3個月 | X8: 9/30：591 22062249 刊登中，509,400（未稅）／283坪（與前次相同）；10/12 再查：22062249 仍為 509,400／283坪 | Y8: 實坪未揭露；大樓名稱為推定；管理費未提供；廁所需現勘 | Z8: 易信國際 王先生 0955-866-400；傑森愛華 張先生 0931-330823 | AA8: 開啟 | AB8: 開啟地圖 | AC8: 待確認：實坪未揭露（權狀283坪）；已符合：月租53.5萬（45～55萬） · 南京三民(綠) 2分
A9: N15 | B9: 民生東路二段 6F（仲介稱使用約226坪） | C9: 待確認實坪 | D9: 中山 | E9: 民生東路二段 | F9: 6F/12F | G9: 255.18 | I9: 507565 | J9: 483,395 未含稅（591 21595066）→ 含稅 507,565 | L9: =IF(OR(I9="",K9=""),"管理費缺",I9+K9) -> 管理費缺 | M9: =IF(OR(I9="",G9=""),"",I9/G9) -> 1989.0469 | N9: =IF(H9="","未揭露",IF(H9>=0_條件與假設!$B$5,"✓","✗")) -> 未揭露 | O9: =IF(I9="","未提供",IF(I9<=0_條件與假設!$B$6,"≤45萬",IF(I9<=0_條件與假設!$B$7,"45～55萬","超過55萬"))) -> 45～55萬 | P9: 行天宮(橘) 188m | T9: =IF(S9="","未確認",IF(S9<=0_條件與假設!$B$8,"✓",IF(S9<=16,"△ 11～16分","✗"))) -> 未確認 | U9: 廁所新：廁所為新裝修（591 21985150 照片 8、9：深色石材牆面、檯面式洗手台、新式小便斗）；辦公區天花有部分線材外露待整理；同戶 591 21812612 內文寫「廁所設於室內」。 | V9: 兩年～3年 | W9: 面議 | X9: 9/30：591 21985150 刊登中，483,395／使用約226坪（與前次相同）；同戶 21595066 也仍刊登；10/12 再查：21985150 仍為 483,395；使用者另給同戶 591 21812612（易信，483,395／255坪權狀）；⚠ 原「未含稅」依據 591 21595066 已下架，現存兩筆都沒寫稅別 | Y9: 實坪只有仲介口述；綠紅藍捷運距離未確認（概略座標推算松江南京約780m）；稅別依據（591 21595066「未含稅」）已下架，現存刊登未寫稅別 | Z9: 弘浥 張先生 0920-323-930；易信國際 王先生 0955-866-400 | AA9: 開啟 | AB9: 開啟地圖 | AC9: 待確認：實坪未揭露（權狀255.18坪） · 綠紅藍捷運距離未確認（最近 行天宮(橘) 188m）；已符合：月租50.8萬（45～55萬）
A10: S06 | B10: 八德大樓 7F（出租254.06坪） | C10: 待確認實坪 | D10: 中山 | E10: 八德路二段 | F10: 7F/12F | G10: 254.06 | I10: 381090 | J10: 381,090（信義刊登）；591 22053377 254坪 381,000 | K10: 41920 | L10: =IF(OR(I10="",K10=""),"管理費缺",I10+K10) -> 423010 | M10: =IF(OR(I10="",G10=""),"",I10/G10) -> 1500 | N10: =IF(H10="","未揭露",IF(H10>=0_條件與假設!$B$5,"✓","✗")) -> 未揭露 | O10: =IF(I10="","未提供",IF(I10<=0_條件與假設!$B$6,"≤45萬",IF(I10<=0_條件與假設!$B$7,"45～55萬","超過55萬"))) -> ≤45萬 | P10: 忠孝復興 | Q10: 藍 | R10: 620 | S10: 11 | T10: =IF(S10="","未確認",IF(S10<=0_條件與假設!$B$8,"✓",IF(S10<=16,"△ 11～16分","✗"))) -> △ 11～16分 | U10: 廁所新：與 S11 同棟同規格：廁所新裝修（信義 CZ05587 照片 H）、茶水間新（照片 G）。 | V10: 3年 | W10: 3個月 | X10: 9/30：信義 CZ05587 刊登中，381,090／出租254.06坪（與前次相同）；10/12 再查：CZ05587 仍為 381,090／254.06坪 | Y10: 出租部分實坪未揭露；稅別未寫 | Z10: 信義 林嘉君 0912-313-517 | AA10: 開啟 | AB10: 開啟地圖 | AC10: 待確認：實坪未揭露（權狀254.06坪） · 捷運忠孝復興(藍) 11分（>10分）；已符合：月租38.1萬
A11: N09 | B11: 長春路 8F（松江南京站） | C11: 待確認實坪 | D11: 中山 | E11: 長春路 | F11: 8F/12F | G11: 253 | I11: 480035 | J11: 480,035（591 22061922，稅別未寫） | L11: =IF(OR(I11="",K11=""),"管理費缺",I11+K11) -> 管理費缺 | M11: =IF(OR(I11="",G11=""),"",I11/G11) -> 1897.3715 | N11: =IF(H11="","未揭露",IF(H11>=0_條件與假設!$B$5,"✓","✗")) -> 未揭露 | O11: =IF(I11="","未提供",IF(I11<=0_條件與假設!$B$6,"≤45萬",IF(I11<=0_條件與假設!$B$7,"45～55萬","超過55萬"))) -> 45～55萬 | P11: 松江南京 | Q11: 綠 | R11: 310 | S11: 6 | T11: =IF(S11="","未確認",IF(S11<=0_條件與假設!$B$8,"✓",IF(S11<=16,"△ 11～16分","✗"))) -> ✓ | U11: 廁所無照片：591 共 4 張皆為辦公區（開放式天花、地毯），沒有拍廁所。需現勘。 | V11: 兩年 | W11: 面議 | X11: 9/30：591 22061922 刊登中，480,035／253坪（與前次相同）；10/12 再查：22061922 仍為 480,035／253坪 | Y11: 實坪未揭露；租金稅別未寫；管理費未提供；廁所需現勘 | Z11: 易信國際 王先生 0955-866-400 | AA11: 開啟 | AB11: 開啟地圖 | AC11: 待確認：實坪未揭露（權狀253坪）；已符合：月租48.0萬（45～55萬） · 松江南京(綠) 6分
A12: N27 | B12: 南京東路五段 3F（南京三民站） | C12: 待確認實坪 | D12: 松山 | E12: 南京東路五段 | F12: 3F/16F | G12: 243 | I12: 534754 | J12: 534,754（591 22061968，稅別未寫；若為未稅，含稅561,492將超過上限） | L12: =IF(OR(I12="",K12=""),"管理費缺",I12+K12) -> 管理費缺 | M12: =IF(OR(I12="",G12=""),"",I12/G12) -> 2200.6337 | N12: =IF(H12="","未揭露",IF(H12>=0_條件與假設!$B$5,"✓","✗")) -> 未揭露 | O12: =IF(I12="","未提供",IF(I12<=0_條件與假設!$B$6,"≤45萬",IF(I12<=0_條件與假設!$B$7,"45～55萬","超過55萬"))) -> 45～55萬 | P12: 南京三民 | Q12: 綠 | R12: 48 | S12: 1 | T12: =IF(S12="","未確認",IF(S12<=0_條件與假設!$B$8,"✓",IF(S12<=16,"△ 11～16分","✗"))) -> ✓ | U12: 廁所無照片：591 共 4 張（辦公區、外觀），沒有拍廁所。需現勘。 | V12: 兩年 | W12: 面議 | X12: 9/30：591 22061968 刊登中，534,754／243坪（與前次相同）；10/12 再查：22061968 仍為 534,754／243坪 | Y12: 實坪未揭露；稅別未寫（未稅則超過55萬）；廁所需現勘 | Z12: 易信國際 王先生 0955-866-400 | AA12: 開啟 | AB12: 開啟地圖 | AC12: 待確認：實坪未揭露（權狀243坪）；已符合：月租53.5萬（45～55萬） · 南京三民(綠) 1分
A13: D | B13: 敦化財經大樓 4F之1 | C13: 不符合 | D13: 松山 | E13: 敦化北路214號 | F13: 4F/11F(B2) | G13: 220.07 | H13: 207.21 | I13: 440140 | J13: 440,140 含稅（尚揚物調表）；591 同戶 386,839 稅別未寫 | K13: 48415 | L13: =IF(OR(I13="",K13=""),"管理費缺",I13+K13) -> 488555 | M13: =IF(OR(I13="",G13=""),"",I13/G13) -> 2000 | N13: =IF(H13="","未揭露",IF(H13>=0_條件與假設!$B$5,"✓","✗")) -> ✗ | O13: =IF(I13="","未提供",IF(I13<=0_條件與假設!$B$6,"≤45萬",IF(I13<=0_條件與假設!$B$7,"45～55萬","超過55萬"))) -> ≤45萬 | P13: 中山國中(棕) 404m（591寫明） | T13: =IF(S13="","未確認",IF(S13<=0_條件與假設!$B$8,"✓",IF(S13<=16,"△ 11～16分","✗"))) -> 未確認 | U13: 廁所在外：物調表註明「廁所在外」（公共廁所，非本戶專用）；尚揚照片大多為毛胚（天花拆除、管線外露），沒有拍廁所；591 21711753 共 11 張為大樓外觀、大廳（石材）與周邊，也沒有室內與廁所照片。 | V13: 2年 | W13: 3個月 | X13: 10/12：591 21711753 刊登中，446,480（含稅）／權狀220.07、主建＋附屬207.21 | Y13: 591 與物調表租金／管理費不同（446,480 vs 440,140；47,840 vs 48,415） | Z13: 尚揚國際 張正修 0937-519-365 | AA13: 開啟 | AB13: 開啟地圖 | AC13: 不符：實坪207.21（差12.8坪）
A14: N17 | B14: 松哖大樓 2F | C14: 不符合 | D14: 中山 | E14: 民生東路二段161號＋163號2樓 | F14: 2F/12F(B1) | G14: 227.15 | H14: 198.26 | I14: 500000 | J14: 500,000 含稅（尚揚物調表）；591 同樓層 439,450～500,000 多筆 | K14: 40000 | L14: =IF(OR(I14="",K14=""),"管理費缺",I14+K14) -> 540000 | M14: =IF(OR(I14="",G14=""),"",I14/G14) -> 2201.1886 | N14: =IF(H14="","未揭露",IF(H14>=0_條件與假設!$B$5,"✓","✗")) -> ✗ | O14: =IF(I14="","未提供",IF(I14<=0_條件與假設!$B$6,"≤45萬",IF(I14<=0_條件與假設!$B$7,"45～55萬","超過55萬"))) -> 45～55萬 | P14: 行天宮(橘) 約185～299m | T14: =IF(S14="","未確認",IF(S14<=0_條件與假設!$B$8,"✓",IF(S14<=16,"△ 11～16分","✗"))) -> 未確認 | U14: 廁所無照片：尚揚照片為辦公區（水泥地坪、部分天花拆），沒有拍廁所；591 20941554 共 10 張也都是空室（天花部分拆除），沒有廁所。 | V14: 2年 | W14: 3個月 | X14: 10/12：591 20941554 刊登中，439,450／235.73坪 | Z14: 尚揚 劉品汯 0901-407-026 | AA14: 開啟 | AB14: 開啟地圖 | AC14: 不符：實坪198.26（差21.7坪）
A15: N34 | B15: 民權西路 5F（民權西路站） | C15: 不符合 | D15: 大同 | E15: 民權西路 | F15: 5F/13F | G15: 303 | I15: 450000 | J15: 450,000（591 11580037，稅別未寫） | L15: =IF(OR(I15="",K15=""),"管理費缺",I15+K15) -> 管理費缺 | M15: =IF(OR(I15="",G15=""),"",I15/G15) -> 1485.1485 | N15: =IF(H15="","未揭露",IF(H15>=0_條件與假設!$B$5,"✓","✗")) -> 未揭露 | O15: =IF(I15="","未提供",IF(I15<=0_條件與假設!$B$6,"≤45萬",IF(I15<=0_條件與假設!$B$7,"45～55萬","超過55萬"))) -> ≤45萬 | P15: 民權西路 | Q15: 紅 | R15: 164 | S15: 3 | T15: =IF(S15="","未確認",IF(S15<=0_條件與假設!$B$8,"✓",IF(S15<=16,"△ 11～16分","✗"))) -> ✓ | U15: 廁所無照片：591 11580037 共 12 張為現有裝潢（木紋地板、玻璃隔間會議室、茶水區），沒有拍廁所；照片上傳於 2021/09，現況需現勘。 | V15: 兩年 | W15: 2個月 | X15: 10/12：591 11580037 刊登中，450,000／303坪（含公設） | Y15: 大同區（不在五區內）；實坪未揭露；租金稅別未寫；管理費未提供 | Z15: 住商 林玉蘋 0952-060-901 | AA15: 開啟 | AB15: 開啟地圖 | AC15: 不符：非指定行政區
A16: N30 | B16: 敦化南路二段 15F（信義安和站） | C16: 不符合 | D16: 大安 | E16: 敦化南路二段 | F16: 15F/27F | G16: 204 | I16: 469200 | J16: 469,200（591 22062144，稅別未寫） | L16: =IF(OR(I16="",K16=""),"管理費缺",I16+K16) -> 管理費缺 | M16: =IF(OR(I16="",G16=""),"",I16/G16) -> 2300 | N16: =IF(H16="","未揭露",IF(H16>=0_條件與假設!$B$5,"✓","✗")) -> 未揭露 | O16: =IF(I16="","未提供",IF(I16<=0_條件與假設!$B$6,"≤45萬",IF(I16<=0_條件與假設!$B$7,"45～55萬","超過55萬"))) -> 45～55萬 | P16: 信義安和 | Q16: 紅 | R16: 760 | S16: 13 | T16: =IF(S16="","未確認",IF(S16<=0_條件與假設!$B$8,"✓",IF(S16<=16,"△ 11～16分","✗"))) -> △ 11～16分 | U16: 廁所無照片：591 22062144 共 9 張為空室（木紋地板、開放式天花）＋茶水間（照片 9，新），沒有拍廁所。 | V16: 3年 | W16: 面議 | X16: 10/12：591 22062144 刊登中，469,200／204坪（權狀） | Y16: 權狀僅204坪；租金稅別未寫；管理費未提供 | Z16: 易信國際 王先生 0955-866-400 | AA16: 開啟 | AB16: 開啟地圖 | AC16: 不符：權狀僅204坪（實坪必低於220）
A17: N31 | B17: 健康路 8F（南京三民／小巨蛋站） | C17: 不符合 | D17: 松山 | E17: 健康路 | F17: 8F/12F | G17: 195 | I17: 470925 | J17: 448,500 未稅（591 17979949 內文「此租金為未稅金額」，2,300元/坪）→ 含稅 470,925 | L17: =IF(OR(I17="",K17=""),"管理費缺",I17+K17) -> 管理費缺 | M17: =IF(OR(I17="",G17=""),"",I17/G17) -> 2415 | N17: =IF(H17="","未揭露",IF(H17>=0_條件與假設!$B$5,"✓","✗")) -> 未揭露 | O17: =IF(I17="","未提供",IF(I17<=0_條件與假設!$B$6,"≤45萬",IF(I17<=0_條件與假設!$B$7,"45～55萬","超過55萬"))) -> 45～55萬 | P17: 台北小巨蛋 | Q17: 綠 | R17: 180 | S17: 3 | T17: =IF(S17="","未確認",IF(S17<=0_條件與假設!$B$8,"✓",IF(S17<=16,"△ 11～16分","✗"))) -> ✓ | U17: 廁所無照片：591 17979949 共 15 張為空室（高架地板、地毯已拆）＋茶水間（照片 15），沒有拍廁所；刊登設備寫「公共衛生間」；照片上傳於 2024/06。 | V17: 3年 | W17: 面議 | X17: 10/12：591 17979949 刊登中，448,500（未稅）／195坪 | Y17: 刊登195坪；坪數性質未說明；管理費未提供 | Z17: 尚揚 陳先生 0906-118-677 | AA17: 開啟 | AB17: 開啟地圖 | AC17: 不符：591 刊登195坪（未說明權狀或使用坪數，任一種都低於220）
A18: N32 | B18: 南京東路三段 9F（南京復興站） | C18: 不符合 | D18: 中山 | E18: 南京東路三段 | F18: 9F/14F | G18: 209.16 | I18: 501984 | J18: 501,984 含稅（591 21423260 內文「此租金為含稅金額」，2,400元/坪） | L18: =IF(OR(I18="",K18=""),"管理費缺",I18+K18) -> 管理費缺 | M18: =IF(OR(I18="",G18=""),"",I18/G18) -> 2400 | N18: =IF(H18="","未揭露",IF(H18>=0_條件與假設!$B$5,"✓","✗")) -> 未揭露 | O18: =IF(I18="","未提供",IF(I18<=0_條件與假設!$B$6,"≤45萬",IF(I18<=0_條件與假設!$B$7,"45～55萬","超過55萬"))) -> 45～55萬 | P18: 南京復興 | Q18: 綠 | R18: 175 | S18: 3 | T18: =IF(S18="","未確認",IF(S18<=0_條件與假設!$B$8,"✓",IF(S18<=16,"△ 11～16分","✗"))) -> ✓ | U18: 廁所無照片：591 21423260 共 15 張為現況辦公室（目前有人使用：開放式天花、玻璃會議室、茶水間、哺乳室），沒有拍廁所；刊登設備寫「公共衛生間」。 | V18: 3年 | W18: 面議 | X18: 10/12：591 21423260 刊登中，501,984（含稅）／209.16坪（權狀） | Y18: 權狀僅209坪；管理費未提供 | Z18: 尚揚 陳先生 0906-118-677 | AA18: 開啟 | AB18: 開啟地圖 | AC18: 不符：權狀僅209.16坪（實坪必低於220）
A19: N29 | B19: 健康路 3F（台北小巨蛋站） | C19: 不符合 | D19: 松山 | E19: 健康路 | F19: 3F/12F | G19: 221 | I19: 508300 | J19: 508,300（591 20903777，稅別未寫） | L19: =IF(OR(I19="",K19=""),"管理費缺",I19+K19) -> 管理費缺 | M19: =IF(OR(I19="",G19=""),"",I19/G19) -> 2300 | N19: =IF(H19="","未揭露",IF(H19>=0_條件與假設!$B$5,"✓","✗")) -> 未揭露 | O19: =IF(I19="","未提供",IF(I19<=0_條件與假設!$B$6,"≤45萬",IF(I19<=0_條件與假設!$B$7,"45～55萬","超過55萬"))) -> 45～55萬 | P19: 台北小巨蛋 | Q19: 綠 | R19: 94 | S19: 2 | T19: =IF(S19="","未確認",IF(S19<=0_條件與假設!$B$8,"✓",IF(S19<=16,"△ 11～16分","✗"))) -> ✓ | U19: 廁所無照片：591 20903777 共 4 張為空室（新木紋地板、新天花燈具），沒有拍廁所；刊登設備寫「獨立衛生間」。 | V19: 兩年 | W19: 面議 | X19: 10/12：591 20903777 刊登中，508,300／221坪（權狀） | Y19: 權狀僅221坪；實坪未揭露；租金稅別未寫；管理費未提供 | Z19: 591 刊登人（專案經理）0977-222-827 | AA19: 開啟 | AB19: 開啟地圖 | AC19: 不符：權狀221坪，公設比需≤0.5%才達220（實坪未揭露）
A20: N33 | B20: 菸廠路 8F（國父紀念館站・松菸旁） | C20: 不符合 | D20: 信義 | E20: 菸廠路 | F20: 8F/14F | G20: 196 | I20: 578621 | J20: 551,068 未稅（591 22162790 內文「此租金未含加值型營業稅5%」）→ 含稅 578,621 | L20: =IF(OR(I20="",K20=""),"管理費缺",I20+K20) -> 管理費缺 | M20: =IF(OR(I20="",G20=""),"",I20/G20) -> 2952.148 | N20: =IF(H20="","未揭露",IF(H20>=0_條件與假設!$B$5,"✓","✗")) -> 未揭露 | O20: =IF(I20="","未提供",IF(I20<=0_條件與假設!$B$6,"≤45萬",IF(I20<=0_條件與假設!$B$7,"45～55萬","超過55萬"))) -> 超過55萬 | P20: 國父紀念館 | Q20: 藍 | R20: 274 | S20: 5 | T20: =IF(S20="","未確認",IF(S20<=0_條件與假設!$B$8,"✓",IF(S20<=16,"△ 11～16分","✗"))) -> ✓ | U20: 廁所無照片：591 22162790 共 7 張為空室（地毯舊、有磨損，面松菸／大巨蛋），沒有拍廁所。 | V20: 一年 | W20: 面議 | X20: 10/12：591 22162790 刊登中，551,068（未稅）／196坪 | Y20: 刊登僅196坪；含稅超過55萬；管理費未提供 | Z20: 東家國際 蔡泳翰 0912-816-677 | AA20: 開啟 | AB20: 開啟地圖 | AC20: 不符：權狀僅196坪（實坪必低於220）；月租578,621超過55萬
A21: J17 | B21: 市民大道3段近復興南路 8F 257坪 | C21: 不符合 | D21: 大安 | E21: 市民大道3段近復興南路 | F21: 8F | G21: 257 | I21: 588000 | J21: 588,000（未稅×1.05） | L21: =IF(OR(I21="",K21=""),"管理費缺",I21+K21) -> 管理費缺 | M21: =IF(OR(I21="",G21=""),"",I21/G21) -> 2287.9377 | N21: =IF(H21="","未揭露",IF(H21>=0_條件與假設!$B$5,"✓","✗")) -> 未揭露 | O21: =IF(I21="","未提供",IF(I21<=0_條件與假設!$B$6,"≤45萬",IF(I21<=0_條件與假設!$B$7,"45～55萬","超過55萬"))) -> 超過55萬 | P21: 忠孝復興 | Q21: 藍 | R21: 370 | S21: 7 | T21: =IF(S21="","未確認",IF(S21<=0_條件與假設!$B$8,"✓",IF(S21<=16,"△ 11～16分","✗"))) -> ✓ | U21: 廁所無照片：591 22061936 共 3 張（接待櫃台、會客區、會議室，高檔裝潢），沒有拍廁所。 | V21: — | W21: 3個月 | X21: 10/12：591 22061936 刊登中，533,333（稅別未寫）／257坪（權狀） | Y21: 591 533,333 稅別未寫（若含稅則≤55萬，需確認）；同棟仲介口述使用約171坪 | Z21: 傑森愛華 張先生 0931-330823 | AA21: 開啟 | AB21: 開啟地圖 | AC21: 不符：月租588,000超過55萬
A22: N28 | B22: 民生東路三段 8F（中山國中站） | C22: 不符合 | D22: 中山 | E22: 民生東路三段 | F22: 8F/16F | G22: 254.53 | I22: 614678 | J22: 585,408 未稅（591 22129776 內文「租金為未稅金額」）→ 含稅 614,678 | L22: =IF(OR(I22="",K22=""),"管理費缺",I22+K22) -> 管理費缺 | M22: =IF(OR(I22="",G22=""),"",I22/G22) -> 2414.9531 | N22: =IF(H22="","未揭露",IF(H22>=0_條件與假設!$B$5,"✓","✗")) -> 未揭露 | O22: =IF(I22="","未提供",IF(I22<=0_條件與假設!$B$6,"≤45萬",IF(I22<=0_條件與假設!$B$7,"45～55萬","超過55萬"))) -> 超過55萬 | P22: 南京復興 | Q22: 綠 | R22: 1070 | S22: 18 | T22: =IF(S22="","未確認",IF(S22<=0_條件與假設!$B$8,"✓",IF(S22<=16,"△ 11～16分","✗"))) -> ✗ | U22: 廁所無照片：591 22129776 共 12 張皆為辦公區（現成新式裝潢、目前有人使用：會議室、茶水吧、置物櫃），沒有拍廁所。 | V22: 一年 | W22: 面議 | X22: 10/12：591 22129776 刊登中，585,408（未稅）／254.53坪 | Y22: 含稅超過55萬；實坪未揭露；管理費未提供；綠紅藍捷運步行約18分（概略） | Z22: 同陽商仲 房先生 0978-751-212 | AA22: 開啟 | AB22: 開啟地圖 | AC22: 不符：月租614,678超過55萬；捷運南京復興(綠) 18分太遠

Sheet A_總表
A1: 分級 | B1: 排序 | C1: 案號 | D1: 案名 | E1: 行政區 | F1: 地址 | G1: 樓層 | H1: 權狀坪 | I1: 實坪 (主+附) | J1: 實坪來源 | K1: 月租(含稅) | L1: 租金原文／稅別 | M1: 管理費(月) | N1: 月總成本(公式) 管理費缺＝只含租金 | O1: 每實坪月成本 (公式) | P1: 實坪≥門檻 (公式) | Q1: 租金級距 (公式) | R1: 最近綠紅藍站 | S1: 路線 | T1: 距離(m) | U1: 步行(分) | V1: 捷運判定 (公式) | W1: 判定說明 | X1: 缺漏／待確認 | Y1: 屋況／廁所（照片判讀） | Z1: 屋齡 | AA1: 車位 | AB1: 來源 | AC1: 聯絡人 | AD1: 連結 | AE1: 地圖定位依據 | AF1: Google 地圖
A2: 第一優先 | B2: 1 | C2: S05 | D2: 建國北路二段 10F（大辦公室＋大倉儲） | E2: 中山 | F2: 建國北路二段 | G2: 10F/12F | H2: 278.04 | I2: 262.5 | J2: 信義房屋物件頁：主建物246.00＋附屬16.50（共有15.54） | K2: 388500 | L2: 388,500（信義房屋刊登） | M2: 37500 | N2: =IF(K2="","",K2+N(M2)) -> 426000 | O2: =IF(OR(I2="",N2=""),"",N2/I2) -> 1622.8571 | P2: =IF(I2="","未揭露",IF(I2>=0_條件與假設!$B$5,"✓","✗")) -> ✓ | Q2: =IF(K2="","未提供",IF(K2<=0_條件與假設!$B$6,"≤45萬",IF(K2<=0_條件與假設!$B$7,"45～55萬","超過55萬"))) -> ≤45萬 | R2: 松江南京 | S2: 綠 | T2: 530 | U2: 9 | V2: =IF(U2="","未確認",IF(U2<=0_條件與假設!$B$8,"✓",IF(U2<=16,"△ 11～16分","✗"))) -> ✓ | W2: 四項全符合：實坪262.5 · 月租38.9萬 · 松江南京(綠) 9分 | X2: 租金稅別未寫；廁所老舊需整修 | Y2: 廁所老舊：廁所為舊式裝修（信義房屋物件照片 M、N）：立柱式洗手台、舊式隔間、天花板老式排風扇與日光燈格柵；辦公區地毯有污漬、部分天花板板材已拆（照片 C、D、G）；電梯廳已翻新（照片 K、L）；茶水間小（照片 I、J）。建議把廁所整修列入議價，或要求房東交屋前整修。 | Z2: 屋齡41.7年 | AA2: 無；平面車位可另租5,000 | AB2: 信義房屋 C905199（2026/07/28更新） | AC2: 張聰仁 信義房屋投資二部 0939-738-856 | AD2: 信義全球物件頁（16張照片） | AE2: 物件頁座標：信義全球物件座標（25.055616, 121.536479） | AF2: 開啟地圖
A3: 第二優先 | B3: 2 | C3: N04 | D3: 信義大樓 10F | E3: 信義 | F3: 松仁路（信義大樓） | G3: 10F/23F | H3: 330.22 | I3: 300.43 | J3: 同一戶信義房屋 C904200：主254.24＋附46.19（591 刊登「300坪」與此相符） | K3: 480000 | L3: 480,000（591 21537848，稅別未寫）；同戶信義房屋刊登577,885 | M3: 49533 | N3: =IF(K3="","",K3+N(M3)) -> 529533 | O3: =IF(OR(I3="",N3=""),"",N3/I3) -> 1762.5836 | P3: =IF(I3="","未揭露",IF(I3>=0_條件與假設!$B$5,"✓","✗")) -> ✓ | Q3: =IF(K3="","未提供",IF(K3<=0_條件與假設!$B$6,"≤45萬",IF(K3<=0_條件與假設!$B$7,"45～55萬","超過55萬"))) -> 45～55萬 | R3: 象山 | S3: 紅 | T3: 950 | U3: 16 | V3: =IF(U3="","未確認",IF(U3<=0_條件與假設!$B$8,"✓",IF(U3<=16,"△ 11～16分","✗"))) -> △ 11～16分 | W3: 坪數符合；實坪300.43 · 月租48.0萬（45～55萬） · 捷運象山(紅) 16分（>10分） | X3: 591 48萬刊登已下架（9/30），現存刊登為信義 577,885（超過55萬）；租金稅別未寫；兩方報價不同 | Y3: 廁所新：廁所為新裝修（信義房屋 C904200 照片 C：檯面式洗手台、木紋隔間）；辦公區天花為開放式未封板。 | Z3: 屋齡約29年 | AA3: 591：平面式 | AB3: 591 21537848（傑森愛華 張先生）；信義房屋 C904200 | AC3: 傑森愛華 張先生 0931-330-823 | AD3: 信義全球 10F（面積分項） | AE3: 物件頁座標：同信義大樓座標（25.024307, 121.569847） | AF3: 開啟地圖
A4: 第二優先 | B4: 3 | C4: C | D4: 旭寶大樓 5F | E4: 松山 | F4: 敦化南路一段25號 | G4: 5F/12F(B2) | H4: 282.06 | I4: 255.38 | J4: 尚揚物調表：實用坪255.38 | K4: 472500 | L4: 472,500 含稅（尚揚物調表）；591 21530071 刊登450,000（=未稅，×1.05即472,500） | M4: 33847 | N4: =IF(K4="","",K4+N(M4)) -> 506347 | O4: =IF(OR(I4="",N4=""),"",N4/I4) -> 1982.7199 | P4: =IF(I4="","未揭露",IF(I4>=0_條件與假設!$B$5,"✓","✗")) -> ✓ | Q4: =IF(K4="","未提供",IF(K4<=0_條件與假設!$B$6,"≤45萬",IF(K4<=0_條件與假設!$B$7,"45～55萬","超過55萬"))) -> 45～55萬 | R4: 忠孝敦化 | S4: 藍 | T4: 570 | U4: 10 | V4: =IF(U4="","未確認",IF(U4<=0_條件與假設!$B$8,"✓",IF(U4<=16,"△ 11～16分","✗"))) -> ✓ | W4: 坪數符合；實坪255.38 · 月租47.2萬（45～55萬） · 忠孝敦化(藍) 10分 | X4: 只能租4年（之後都更）；廁所老舊需整修 | Y4: 廁所老舊：廁所為舊式裝修（591 21530071 照片 9、10）：藍色磁磚地坪、藍色立柱式洗手台、舊式小便斗與隔間、舊天花板；茶水間為木紋新作（照片 11）。建議把廁所整修列入議價。 | Z4: 屋齡約43年（1983/12竣工，好房網） | AA4: 機械車位×6（租金內含） | AB4: 尚揚國際物調表；591 21530071（房仲提供）；591 21524253「敦南綠景」5F 250.97坪 45萬含6車位（21530071 標題同稱「敦南綠景」→ 同戶） | AC4: 尚揚 王智平 0917-154-083；591 呂育瑄 0919-219-331 | AD4: 大樓照片（好房網19張） | AE4: 門牌定位：Google地圖：敦化南路一段25號（25.0464096, 121.5494252） | AF4: 開啟地圖
A5: 第二優先 | B5: 4 | C5: N02 | D5: 廣成大廈 4F | E5: 中正 | F5: 延平南路189號4樓～之5 | G5: 4F/7F(B2) | H5: 326.85 | I5: 253.54 | J5: 尚揚物調表：主建物＋附屬建物253.54 | K5: 491000 | L5: 491,000（尚揚物調表標示「含稅」；傑森愛華清單同價但標「未稅」；591 21779044 標491,000含管理費；591 20971276 標491,000、管理費另計31,053） | M5: 31053 | N5: =IF(K5="","",K5+N(M5)) -> 522053 | O5: =IF(OR(I5="",N5=""),"",N5/I5) -> 2059.0558 | P5: =IF(I5="","未揭露",IF(I5>=0_條件與假設!$B$5,"✓","✗")) -> ✓ | Q5: =IF(K5="","未提供",IF(K5<=0_條件與假設!$B$6,"≤45萬",IF(K5<=0_條件與假設!$B$7,"45～55萬","超過55萬"))) -> 45～55萬 | R5: 小南門 | S5: 綠 | T5: 380 | U5: 7 | V5: =IF(U5="","未確認",IF(U5<=0_條件與假設!$B$8,"✓",IF(U5<=16,"△ 11～16分","✗"))) -> ✓ | W5: 坪數符合；實坪253.54 · 月租49.1萬（45～55萬） · 小南門(綠) 7分 | X5: 租金是否含稅、是否含管理費：物調表／傑森愛華／591 三方說法不同，需書面確認；廁所需現勘 | Y5: 廁所無照片：尚揚照片、591 21779044（3 張：大廳、空室）、傑森愛華清單照片都沒有拍廁所；辦公區為開放空間、水泥地坪需整理。需現勘。 | Z5: 民國70/1/5竣工（屋齡約45年） | AA5: 固定車位7,000(含稅)／非固定5,000(含稅) | AB5: 尚揚物調表（陳威翰）；591 21779044、20971276（葛林威 林小姐，326.87坪 4F/7F 491,000＋管理費31,053）、22009979；傑森愛華 2026/9/23清單第3頁 | AC5: 尚揚 陳威翰 0906-118-677；591 楊小姐 02-27415343#36；591 葛林威 林小姐 0984-002-297 | AD5: 591 物件頁 | AE5: 門牌定位：Google地圖：延平南路189號（25.0337995, 121.5075571） | AF5: 開啟地圖
A6: 第二優先 | B6: 5 | C6: S12 | D6: 全球人壽信義大樓 21F | E6: 信義 | F6: 松仁路277號21樓 | G6: 21F/23F(B4) | H6: 265.82 | I6: 241.8 | J6: 尚揚物調表：主建物＋附屬241.8；信義房屋 C904707：主204.94＋附36.86＝241.80 | K6: 502400 | L6: 502,400 含稅（尚揚物調表）；信義房屋刊登544,931 | M6: 39873 | N6: =IF(K6="","",K6+N(M6)) -> 542273 | O6: =IF(OR(I6="",N6=""),"",N6/I6) -> 2242.651 | P6: =IF(I6="","未揭露",IF(I6>=0_條件與假設!$B$5,"✓","✗")) -> ✓ | Q6: =IF(K6="","未提供",IF(K6<=0_條件與假設!$B$6,"≤45萬",IF(K6<=0_條件與假設!$B$7,"45～55萬","超過55萬"))) -> 45～55萬 | R6: 象山 | S6: 紅 | T6: 950 | U6: 16 | V6: =IF(U6="","未確認",IF(U6<=0_條件與假設!$B$8,"✓",IF(U6<=16,"△ 11～16分","✗"))) -> △ 11～16分 | W6: 坪數符合；實坪241.8 · 月租50.2萬（45～55萬） · 捷運象山(紅) 16分（>10分） | Y6: 廁所新：廁所、茶水間為新裝修（尚揚照片：石材牆面、木紋隔間、檯面式洗手台）；地毯、天花完整。 | Z6: 民國86/5/25竣工（屋齡約29年） | AA6: 物調表未載；信義頁：無 | AB6: 尚揚物調表（劉于上）；信義房屋 C904707 | AC6: 尚揚 劉于上 0938-259-324；信義 許雅傑 0966-513-725 | AD6: 信義全球物件頁 | AE6: 物件頁座標：信義全球物件座標（25.024307, 121.569847） | AF6: 開啟地圖
A7: 第二優先 | B7: 6 | C7: N01 | D7: 南海開發大樓 5F | E7: 中正 | F7: 南海路20號5樓 | G7: 5F/10F(B1) | H7: 260.98 | I7: 228.34 | J7: 尚揚物調表：主建物＋附屬建物228.34 | K7: 465849 | L7: 465,849 含稅（尚揚物調表）；591 22010357 刊登443,666（×1.05=465,849，即未稅價）；傑森愛華清單 443,000 未稅 | N7: =IF(K7="","",K7+N(M7)) -> 465849 | O7: =IF(OR(I7="",N7=""),"",N7/I7) -> 2040.155 | P7: =IF(I7="","未揭露",IF(I7>=0_條件與假設!$B$5,"✓","✗")) -> ✓ | Q7: =IF(K7="","未提供",IF(K7<=0_條件與假設!$B$6,"≤45萬",IF(K7<=0_條件與假設!$B$7,"45～55萬","超過55萬"))) -> 45～55萬 | R7: 中正紀念堂 | S7: 紅綠 | T7: 150 | U7: 3 | V7: =IF(U7="","未確認",IF(U7<=0_條件與假設!$B$8,"✓",IF(U7<=16,"△ 11～16分","✗"))) -> ✓ | W7: 坪數符合；實坪228.34 · 月租46.6萬（45～55萬） · 中正紀念堂(紅綠) 3分 | X7: 管理費只有區間（2.5萬～3萬），無確切金額；廁所需現勘 | Y7: 廁所無照片：尚揚照片與 591 22010357（僅 1 張外觀）都沒有拍廁所；辦公區為亮面地坪、天花完整。需現勘。 | Z7: 民國77/9/22竣工（屋齡約38年） | AA7: 附坡平車位2個（591：含車位） | AB7: 尚揚物調表（陳威翰）；591 22010357、21589109；傑森愛華 2026/9/23清單第1頁 | AC7: 尚揚 陳威翰 0906-118-677；兆淇 鄭先生 0960-539-161；傑森愛華 張先生 0931-330823 | AD7: 591 物件頁 | AE7: 門牌定位：Google地圖：南海路20號（25.0324406, 121.5169915） | AF7: 開啟地圖
A8: 待確認實坪 | B8: 7 | C8: N05 | D8: 信義大樓 8F | E8: 信義 | F8: 松仁路（信義區） | G8: 8F | H8: 331 | J8: 8F 本身未揭露；同棟5F/9F 實坪300.54／300.44（信義房屋） | K8: 538703 | L8: 513,050 未稅（@1,550）→ 含稅 538,703 | N8: =IF(K8="","",K8+N(M8)) -> 538703 | O8: =IF(OR(I8="",N8=""),"",N8/I8) | P8: =IF(I8="","未揭露",IF(I8>=0_條件與假設!$B$5,"✓","✗")) -> 未揭露 | Q8: =IF(K8="","未提供",IF(K8<=0_條件與假設!$B$6,"≤45萬",IF(K8<=0_條件與假設!$B$7,"45～55萬","超過55萬"))) -> 45～55萬 | R8: 象山 | S8: 紅 | T8: 950 | U8: 16 | V8: =IF(U8="","未確認",IF(U8<=0_條件與假設!$B$8,"✓",IF(U8<=16,"△ 11～16分","✗"))) -> △ 11～16分 | W8: 待確認：實坪未揭露（權狀331坪） · 捷運象山(紅) 16分（>10分）；已符合：月租53.9萬（45～55萬） | X8: 實坪未揭露；管理費未提供；廁所需現勘 | Y8: 8F未拍廁所：8F 本身沒有室內照片（傑森愛華 3 張皆外觀）；同棟 10F、21F 廁所為新裝修，8F 需現勘確認。 | Z8: 屋齡約29年 | AA8: 未提供 | AB8: 傑森愛華 2026/9/23清單第3頁 | AC8: 傑森愛華 張先生 0931-330823 | AD8: 傑森愛華清單 第3頁 | AE8: 物件頁座標：同信義大樓座標（25.024307, 121.569847） | AF8: 開啟地圖
A9: 待確認實坪 | B9: 8 | C9: N08 | D9: 松江路 3F（松江南京站） | E9: 中山 | F9: 松江路 | G9: 3F/12F | H9: 302 | J9: 591 原文「刊登坪數、權狀面積依地政機關登記為準」 | K9: 540837 | L9: 515,083 未含營業稅（591 21635155）→ 含稅 540,837 | N9: =IF(K9="","",K9+N(M9)) -> 540837 | O9: =IF(OR(I9="",N9=""),"",N9/I9) | P9: =IF(I9="","未揭露",IF(I9>=0_條件與假設!$B$5,"✓","✗")) -> 未揭露 | Q9: =IF(K9="","未提供",IF(K9<=0_條件與假設!$B$6,"≤45萬",IF(K9<=0_條件與假設!$B$7,"45～55萬","超過55萬"))) -> 45～55萬 | R9: 松江南京 | S9: 綠 | T9: 156 | U9: 3 | V9: =IF(U9="","未確認",IF(U9<=0_條件與假設!$B$8,"✓",IF(U9<=16,"△ 11～16分","✗"))) -> ✓ | W9: 待確認：實坪未揭露（權狀302坪）；已符合：月租54.1萬（45～55萬） · 松江南京(綠) 3分 | X9: 實坪未揭露；管理費未提供；廁所需現勘 | Y9: 廁所無照片：591 只有 1 張照片（捷運出口），室內與廁所都沒有拍。需現勘。 | Z9: 未提供 | AA9: 未提供 | AB9: 591 21635155（東家）、22017413（兆淇 鄭先生，302.99坪、515,083、1,700元/坪）、21888124、21548435 | AC9: 東家國際 蔡泳翰 0912-816-677；兆淇 鄭先生 0960-539-161 | AD9: 591 物件頁 | AE9: 概略位置：591 21635155 物件頁地圖座標（門牌未揭露，591 標點可能為概略位置）（25.0533328, 121.5334926） | AF9: 開啟地圖
A10: 待確認實坪 | B10: 9 | C10: S11 | D10: 八德大樓 5F（出租285.67坪） | E10: 中山 | F10: 八德路二段 | G10: 5F/12F | H10: 285.67 | J10: 信義 CZ05585：整筆權狀577.14、主322.97＋附38.67（整筆），出租285.67坪部分的實坪未寫 | K10: 428505 | L10: 428,505（信義刊登）；591 21804249 285坪 427,500（1,500/坪） | M10: 47136 | N10: =IF(K10="","",K10+N(M10)) -> 475641 | O10: =IF(OR(I10="",N10=""),"",N10/I10) | P10: =IF(I10="","未揭露",IF(I10>=0_條件與假設!$B$5,"✓","✗")) -> 未揭露 | Q10: =IF(K10="","未提供",IF(K10<=0_條件與假設!$B$6,"≤45萬",IF(K10<=0_條件與假設!$B$7,"45～55萬","超過55萬"))) -> ≤45萬 | R10: 忠孝復興 | S10: 藍 | T10: 620 | U10: 11 | V10: =IF(U10="","未確認",IF(U10<=0_條件與假設!$B$8,"✓",IF(U10<=16,"△ 11～16分","✗"))) -> △ 11～16分 | W10: 待確認：實坪未揭露（權狀285.67坪） · 捷運忠孝復興(藍) 11分（>10分）；已符合：月租42.9萬 | X10: 出租部分實坪未揭露；稅別未寫 | Y10: 廁所新：廁所新裝修（信義 CZ05585 照片 D、G：石材檯面、新式小便斗、木紋隔間）；茶水間新（照片 J）；電梯廳石材。 | Z10: 屋齡30.1年 | AA10: 無 | AB10: 信義房屋 CZ05585；591 20991086、21804249 | AC10: 信義 林嘉君 0912-313-517 | AD10: 信義全球物件頁 | AE10: 物件頁座標：信義全球物件座標（25.046292, 121.540346） | AF10: 開啟地圖
A11: 待確認實坪 | B11: 10 | C11: N10 | D11: 光復北路11巷 2F（南京三民站） | E11: 松山 | F11: 光復北路11巷 | G11: 2F/14F | H11: 283 | J11: 591 原文「廣告坪數為權狀坪數」 | K11: 534870 | L11: 509,400 未稅（591 22062249、傑森愛華清單第2頁）→ 含稅 534,870 | N11: =IF(K11="","",K11+N(M11)) -> 534870 | O11: =IF(OR(I11="",N11=""),"",N11/I11) | P11: =IF(I11="","未揭露",IF(I11>=0_條件與假設!$B$5,"✓","✗")) -> 未揭露 | Q11: =IF(K11="","未提供",IF(K11<=0_條件與假設!$B$6,"≤45萬",IF(K11<=0_條件與假設!$B$7,"45～55萬","超過55萬"))) -> 45～55萬 | R11: 南京三民 | S11: 綠 | T11: 88 | U11: 2 | V11: =IF(U11="","未確認",IF(U11<=0_條件與假設!$B$8,"✓",IF(U11<=16,"△ 11～16分","✗"))) -> ✓ | W11: 待確認：實坪未揭露（權狀283坪）；已符合：月租53.5萬（45～55萬） · 南京三民(綠) 2分 | X11: 實坪未揭露；大樓名稱為推定；管理費未提供；廁所需現勘 | Y11: 廁所無照片：591 只有 2 張（空室、捷運站），沒有拍廁所。需現勘。 | Z11: 未提供 | AA11: 未提供（傑森愛華：停車方便） | AB11: 591 22062249（易信 王先生）；傑森愛華 2026/9/23清單第2頁 | AC11: 易信國際 王先生 0955-866-400；傑森愛華 張先生 0931-330823 | AD11: 591 物件頁 | AE11: 概略位置：591 22062249 物件頁地圖座標（門牌未揭露，591 標點可能為概略位置）（25.0508017, 121.5633299） | AF11: 開啟地圖
A12: 待確認實坪 | B12: 11 | C12: N11 | D12: 旭寶大樓 4F | E12: 松山 | F12: 敦化南路一段25號 | G12: 4F/12F | H12: 282.06 | J12: 591 原文「廣告顯示使用面積為含公設面積」；同棟5F 實用255.38（尚揚） | K12: 532980 | L12: 507,600 未稅（傑森愛華清單第2頁）；591 21788157 507,708 未含稅 → 含稅約533,000 | N12: =IF(K12="","",K12+N(M12)) -> 532980 | O12: =IF(OR(I12="",N12=""),"",N12/I12) | P12: =IF(I12="","未揭露",IF(I12>=0_條件與假設!$B$5,"✓","✗")) -> 未揭露 | Q12: =IF(K12="","未提供",IF(K12<=0_條件與假設!$B$6,"≤45萬",IF(K12<=0_條件與假設!$B$7,"45～55萬","超過55萬"))) -> 45～55萬 | R12: 忠孝敦化 | S12: 藍 | T12: 570 | U12: 10 | V12: =IF(U12="","未確認",IF(U12<=0_條件與假設!$B$8,"✓",IF(U12<=16,"△ 11～16分","✗"))) -> ✓ | W12: 待確認：實坪未揭露（權狀282.06坪）；已符合：月租53.3萬（45～55萬） · 忠孝敦化(藍) 10分 | X12: 實坪未揭露；管理費未提供；廁所需現勘 | Y12: 廁所無照片：591 21788157 共 10 張皆為辦公區（地毯磨損、有接待櫃台），沒有拍廁所；同棟 5F 廁所老舊，4F 很可能相同，需現勘。 | Z12: 屋齡約43年 | AA12: 未提供 | AB12: 傑森愛華 2026/9/23清單第2頁；591 21788157（松華 李鴻鈞）、21429025、21908353 | AC12: 傑森愛華 張先生 0931-330823；松華 李鴻鈞 0939-060-379 | AD12: 591 物件頁 | AE12: 門牌定位：同旭寶大樓座標（25.0464096, 121.5494252） | AF12: 開啟地圖
A13: 待確認實坪 | B13: 12 | C13: J18 | D13: 忠孝東路四段×延吉街 4F | E13: 大安 | F13: 忠孝東路4段VS延吉街 | G13: 4F | H13: 276 | J13: 清單只有坪數276（未說明權狀或實坪） | K13: 504000 | L13: 480,000 未稅（@1,739）→ 含稅 504,000（傑森愛華 9/22 與 9/23 兩份清單同價） | N13: =IF(K13="","",K13+N(M13)) -> 504000 | O13: =IF(OR(I13="",N13=""),"",N13/I13) | P13: =IF(I13="","未揭露",IF(I13>=0_條件與假設!$B$5,"✓","✗")) -> 未揭露 | Q13: =IF(K13="","未提供",IF(K13<=0_條件與假設!$B$6,"≤45萬",IF(K13<=0_條件與假設!$B$7,"45～55萬","超過55萬"))) -> 45～55萬 | R13: 國父紀念館 | S13: 藍 | T13: 300 | U13: 5 | V13: =IF(U13="","未確認",IF(U13<=0_條件與假設!$B$8,"✓",IF(U13<=16,"△ 11～16分","✗"))) -> ✓ | W13: 待確認：實坪未揭露（權狀276坪）；已符合：月租50.4萬（45～55萬） · 國父紀念館(藍) 5分 | X13: 實坪未揭露；門牌與大樓名稱為推定；管理費未提供；廁所需現勘 | Y13: 廁所無照片：傑森愛華清單 3 張（外觀、毛胚室內、窗景），沒有拍廁所。需現勘。 | Z13: 推定大樓1982/08竣工（好房網） | AA13: 未提供 | AB13: 傑森愛華 9/22清單（J18）、9/23清單第1頁 | AC13: 傑森愛華 張先生 0931-330823 | AD13: 傑森愛華清單 第1頁 | AE13: 概略位置：忠孝東路四段×延吉街口（清單未給門牌）（25.0413459, 121.5545064） | AF13: 開啟地圖
A14: 待確認實坪 | B14: 13 | C14: N07 | D14: 忠孝東路一段 11F（台北車站） | E14: 中正 | F14: 忠孝東路一段 | G14: 11F/12F | H14: 266.78 | J14: 591 原文「權狀約266.78坪、低公設比」 | K14: 533500 | L14: 533,500 含稅（591 19506910） | N14: =IF(K14="","",K14+N(M14)) -> 533500 | O14: =IF(OR(I14="",N14=""),"",N14/I14) | P14: =IF(I14="","未揭露",IF(I14>=0_條件與假設!$B$5,"✓","✗")) -> 未揭露 | Q14: =IF(K14="","未提供",IF(K14<=0_條件與假設!$B$6,"≤45萬",IF(K14<=0_條件與假設!$B$7,"45～55萬","超過55萬"))) -> 45～55萬 | R14: 台北車站 | S14: 紅藍 | T14: 171 | U14: 3 | V14: =IF(U14="","未確認",IF(U14<=0_條件與假設!$B$8,"✓",IF(U14<=16,"△ 11～16分","✗"))) -> ✓ | W14: 待確認：實坪未揭露（權狀266.78坪）；已符合：月租53.4萬（45～55萬） · 台北車站(紅藍) 3分 | X14: 591 刊登已下架（9/24 查），需確認是否仍可租；實坪未揭露；管理費未提供；廁所需現勘 | Y14: 廁所無照片：591 19506910 共 10 張皆為空辦公區（部分天花板板材缺、地面有污漬），沒有拍廁所。需現勘。 | Z14: 未提供 | AA14: 未提供 | AB14: 591 19506910（尚揚 陳先生） | AC14: 尚揚 陳先生 0906-118-677 | AD14: 591 物件頁 | AE14: 無法定位：沒有門牌也沒有座標 | AF14: —
A15: 待確認實坪 | B15: 14 | C15: N14 | D15: 中山北路三段 6F（民權西路站） | E15: 中山 | F15: 中山北路三段 | G15: 6F/14F | H15: 265.93 | J15: 591 只寫「使用坪數265.93」，無分項 | K15: 385599 | L15: 385,599（591 22010409，含車位、含管理費，稅別未寫） | M15: 0 | N15: =IF(K15="","",K15+N(M15)) -> 385599 | O15: =IF(OR(I15="",N15=""),"",N15/I15) | P15: =IF(I15="","未揭露",IF(I15>=0_條件與假設!$B$5,"✓","✗")) -> 未揭露 | Q15: =IF(K15="","未提供",IF(K15<=0_條件與假設!$B$6,"≤45萬",IF(K15<=0_條件與假設!$B$7,"45～55萬","超過55萬"))) -> ≤45萬 | R15: 民權西路 | S15: 紅 | T15: 170 | U15: 3 | V15: =IF(U15="","未確認",IF(U15<=0_條件與假設!$B$8,"✓",IF(U15<=16,"△ 11～16分","✗"))) -> ✓ | W15: 待確認：實坪未揭露（權狀265.93坪）；已符合：月租38.6萬 · 民權西路(紅) 3分 | X15: 實坪未揭露；稅別未寫；大樓名稱未揭露；廁所需現勘 | Y15: 廁所無照片：591 只有 1 張照片（捷運站），室內與廁所都沒有拍。需現勘。 | Z15: 未提供 | AA15: 含車位 | AB15: 591 22010409（兆淇 鄭先生） | AC15: 兆淇 鄭先生 0960-539-161 | AD15: 591 物件頁 | AE15: 概略位置：591 22010409 物件頁地圖座標（門牌未揭露，591 標點可能為概略位置）（25.063996, 121.5208493） | AF15: 開啟地圖
A16: 待確認實坪 | B16: 15 | C16: N06 | D16: 忠孝東路一段 2F（善導寺站） | E16: 中正 | F16: 忠孝東路一段 | G16: 2F/21F | H16: 261.4 | J16: 591 原文「權狀約261.4坪（室內實際使用坪數以現場丈量或地政謄本為準）」 | K16: 421872 | L16: 421,872（591 20214332 等7筆同價，稅別未寫）；另有 480,000（住商南門 21553405／21867832） | N16: =IF(K16="","",K16+N(M16)) -> 421872 | O16: =IF(OR(I16="",N16=""),"",N16/I16) | P16: =IF(I16="","未揭露",IF(I16>=0_條件與假設!$B$5,"✓","✗")) -> 未揭露 | Q16: =IF(K16="","未提供",IF(K16<=0_條件與假設!$B$6,"≤45萬",IF(K16<=0_條件與假設!$B$7,"45～55萬","超過55萬"))) -> ≤45萬 | R16: 善導寺 | S16: 藍 | T16: 119 | U16: 2 | V16: =IF(U16="","未確認",IF(U16<=0_條件與假設!$B$8,"✓",IF(U16<=16,"△ 11～16分","✗"))) -> ✓ | W16: 待確認：實坪未揭露（權狀261.4坪）；已符合：月租42.2萬 · 善導寺(藍) 2分 | X16: 實坪未揭露；租金稅別未寫；兩種報價（42.2萬／48萬）；廁所需現勘 | Y16: 廁所無照片：591 20214332 共 14 張：辦公區、吧檯茶水區、戶外露台，沒有拍廁所。需現勘。 | Z16: 未提供 | AA16: 平面式 | AB16: 591 20214332（尚揚 陳先生）、21980734、21234693、21588975、21788512、22020729、22019214、21939596；21553405、21804380、21867832 | AC16: 尚揚 陳先生 0906-118-677 | AD16: 591 物件頁 | AE16: 概略位置：591 20214332 物件頁地圖座標（門牌未揭露，591 標點可能為概略位置）（25.0452963, 121.5244289） | AF16: 開啟地圖
A17: 待確認實坪 | B17: 16 | C17: N15 | D17: 民生東路二段 6F（仲介稱使用約226坪） | E17: 中山 | F17: 民生東路二段 | G17: 6F/12F | H17: 255.18 | J17: 591 21985150 標題「使用約226坪」（仲介口述，無謄本分項）；21595066 寫255.18坪 | K17: 507565 | L17: 483,395 未含稅（591 21595066）→ 含稅 507,565 | N17: =IF(K17="","",K17+N(M17)) -> 507565 | O17: =IF(OR(I17="",N17=""),"",N17/I17) | P17: =IF(I17="","未揭露",IF(I17>=0_條件與假設!$B$5,"✓","✗")) -> 未揭露 | Q17: =IF(K17="","未提供",IF(K17<=0_條件與假設!$B$6,"≤45萬",IF(K17<=0_條件與假設!$B$7,"45～55萬","超過55萬"))) -> 45～55萬 | R17: 行天宮(橘) 188m | V17: =IF(U17="","未確認",IF(U17<=0_條件與假設!$B$8,"✓",IF(U17<=16,"△ 11～16分","✗"))) -> 未確認 | W17: 待確認：實坪未揭露（權狀255.18坪） · 綠紅藍捷運距離未確認（最近 行天宮(橘) 188m）；已符合：月租50.8萬（45～55萬） | X17: 實坪只有仲介口述；綠紅藍捷運距離未確認（概略座標推算松江南京約780m）；稅別依據（591 21595066「未含稅」）已下架，現存刊登未寫稅別 | Y17: 廁所新：廁所為新裝修（591 21985150 照片 8、9：深色石材牆面、檯面式洗手台、新式小便斗）；辦公區天花有部分線材外露待整理；同戶 591 21812612 內文寫「廁所設於室內」。 | Z17: 未提供 | AA17: 平面式 | AB17: 591 21985150（弘浥 張先生）、21595066（兆淇 童先生）、21812612、21635522；591 21812612（易信 王先生 0955-866-400，255坪權狀、483,395、3年） | AC17: 弘浥 張先生 0920-323-930；易信國際 王先生 0955-866-400 | AD17: 591 物件頁 | AE17: 概略位置：591 21985150 物件頁地圖座標（門牌未揭露，591 標點可能為概略位置）（25.0588777, 121.531561） | AF17: 開啟地圖
A18: 待確認實坪 | B18: 17 | C18: S06 | D18: 八德大樓 7F（出租254.06坪） | E18: 中山 | F18: 八德路二段 | G18: 7F/12F | H18: 254.06 | J18: 信義 CZ05587：整筆權狀786.72、主322.97＋附12.15（整筆，數字異常），出租部分實坪未寫 | K18: 381090 | L18: 381,090（信義刊登）；591 22053377 254坪 381,000 | M18: 41920 | N18: =IF(K18="","",K18+N(M18)) -> 423010 | O18: =IF(OR(I18="",N18=""),"",N18/I18) | P18: =IF(I18="","未揭露",IF(I18>=0_條件與假設!$B$5,"✓","✗")) -> 未揭露 | Q18: =IF(K18="","未提供",IF(K18<=0_條件與假設!$B$6,"≤45萬",IF(K18<=0_條件與假設!$B$7,"45～55萬","超過55萬"))) -> ≤45萬 | R18: 忠孝復興 | S18: 藍 | T18: 620 | U18: 11 | V18: =IF(U18="","未確認",IF(U18<=0_條件與假設!$B$8,"✓",IF(U18<=16,"△ 11～16分","✗"))) -> △ 11～16分 | W18: 待確認：實坪未揭露（權狀254.06坪） · 捷運忠孝復興(藍) 11分（>10分）；已符合：月租38.1萬 | X18: 出租部分實坪未揭露；稅別未寫 | Y18: 廁所新：與 S11 同棟同規格：廁所新裝修（信義 CZ05587 照片 H）、茶水間新（照片 G）。 | Z18: 屋齡30.1年 | AA18: 無 | AB18: 信義房屋 CZ05587；591 20991786、22053377、21808787、21595262 | AC18: 信義 林嘉君 0912-313-517 | AD18: 信義全球物件頁 | AE18: 物件頁座標：信義全球物件座標（25.046277, 121.540437） | AF18: 開啟地圖
A19: 待確認實坪 | B19: 18 | C19: N09 | D19: 長春路 8F（松江南京站） | E19: 中山 | F19: 長春路 | G19: 8F/12F | H19: 253 | J19: 591 只寫「使用坪數253坪」，無分項 | K19: 480035 | L19: 480,035（591 22061922，稅別未寫） | N19: =IF(K19="","",K19+N(M19)) -> 480035 | O19: =IF(OR(I19="",N19=""),"",N19/I19) | P19: =IF(I19="","未揭露",IF(I19>=0_條件與假設!$B$5,"✓","✗")) -> 未揭露 | Q19: =IF(K19="","未提供",IF(K19<=0_條件與假設!$B$6,"≤45萬",IF(K19<=0_條件與假設!$B$7,"45～55萬","超過55萬"))) -> 45～55萬 | R19: 松江南京 | S19: 綠 | T19: 310 | U19: 6 | V19: =IF(U19="","未確認",IF(U19<=0_條件與假設!$B$8,"✓",IF(U19<=16,"△ 11～16分","✗"))) -> ✓ | W19: 待確認：實坪未揭露（權狀253坪）；已符合：月租48.0萬（45～55萬） · 松江南京(綠) 6分 | X19: 實坪未揭露；租金稅別未寫；管理費未提供；廁所需現勘 | Y19: 廁所無照片：591 共 4 張皆為辦公區（開放式天花、地毯），沒有拍廁所。需現勘。 | Z19: 未提供 | AA19: 未提供 | AB19: 591 22061922（易信 王先生） | AC19: 易信國際 王先生 0955-866-400 | AD19: 591 物件頁 | AE19: 概略位置：591 22061922 物件頁地圖座標（門牌未揭露，591 標點可能為概略位置）（25.0545594, 121.5342379） | AF19: 開啟地圖
A20: 待確認實坪 | B20: 19 | C20: N27 | D20: 南京東路五段 3F（南京三民站） | E20: 松山 | F20: 南京東路五段 | G20: 3F/16F | H20: 243 | J20: 591 原文「廣告坪數為權狀坪數」；公設比需≤9.5%才可能達220 | K20: 534754 | L20: 534,754（591 22061968，稅別未寫；若為未稅，含稅561,492將超過上限） | N20: =IF(K20="","",K20+N(M20)) -> 534754 | O20: =IF(OR(I20="",N20=""),"",N20/I20) | P20: =IF(I20="","未揭露",IF(I20>=0_條件與假設!$B$5,"✓","✗")) -> 未揭露 | Q20: =IF(K20="","未提供",IF(K20<=0_條件與假設!$B$6,"≤45萬",IF(K20<=0_條件與假設!$B$7,"45～55萬","超過55萬"))) -> 45～55萬 | R20: 南京三民 | S20: 綠 | T20: 48 | U20: 1 | V20: =IF(U20="","未確認",IF(U20<=0_條件與假設!$B$8,"✓",IF(U20<=16,"△ 11～16分","✗"))) -> ✓ | W20: 待確認：實坪未揭露（權狀243坪）；已符合：月租53.5萬（45～55萬） · 南京三民(綠) 1分 | X20: 實坪未揭露；稅別未寫（未稅則超過55萬）；廁所需現勘 | Y20: 廁所無照片：591 共 4 張（辦公區、外觀），沒有拍廁所。需現勘。 | Z20: 未提供 | AA20: 未提供 | AB20: 591 22061968（易信 王先生） | AC20: 易信國際 王先生 0955-866-400 | AD20: 591 物件頁 | AE20: 概略位置：591 22061968 物件頁地圖座標（門牌未揭露，591 標點可能為概略位置）（25.0510453, 121.5640687） | AF20: 開啟地圖
A21: 不符合 | B21: 20 | C21: N19 | D21: 信義大樓 5F | E21: 信義 | F21: 松仁路 | G21: 5F/23F | H21: 330.42 | I21: 300.54 | J21: 信義 C905082：主264.78＋附35.76 | K21: 561714 | L21: 561,714（信義刊登） | M21: 49563 | N21: =IF(K21="","",K21+N(M21)) -> 611277 | O21: =IF(OR(I21="",N21=""),"",N21/I21) -> 2033.9289 | P21: =IF(I21="","未揭露",IF(I21>=0_條件與假設!$B$5,"✓","✗")) -> ✓ | Q21: =IF(K21="","未提供",IF(K21<=0_條件與假設!$B$6,"≤45萬",IF(K21<=0_條件與假設!$B$7,"45～55萬","超過55萬"))) -> 超過55萬 | R21: 象山 | S21: 紅 | T21: 950 | U21: 16 | V21: =IF(U21="","未確認",IF(U21<=0_條件與假設!$B$8,"✓",IF(U21<=16,"△ 11～16分","✗"))) -> △ 11～16分 | W21: 不符：月租561,714超過55萬 | X21: 稅別未寫 | Y21: 同棟廁所新：同棟 10F、21F 廁所為新裝修；本層未另拍。 | Z21: 屋齡29.2年 | AA21: 無 | AB21: 信義房屋 C905082 | AC21: 信義 許雅傑 0966-513-725 | AD21: 信義全球物件頁 | AE21: 物件頁座標：同信義大樓座標（25.024307, 121.569847） | AF21: 開啟地圖
A22: 不符合 | B22: 21 | C22: N20 | D22: 信義大樓 9F | E22: 信義 | F22: 松仁路 | G22: 9F/23F | H22: 330.22 | I22: 300.44 | J22: 信義 C904199：主249.55＋附50.89 | K22: 577885 | L22: 577,885（信義刊登） | M22: 49533 | N22: =IF(K22="","",K22+N(M22)) -> 627418 | O22: =IF(OR(I22="",N22=""),"",N22/I22) -> 2088.3304 | P22: =IF(I22="","未揭露",IF(I22>=0_條件與假設!$B$5,"✓","✗")) -> ✓ | Q22: =IF(K22="","未提供",IF(K22<=0_條件與假設!$B$6,"≤45萬",IF(K22<=0_條件與假設!$B$7,"45～55萬","超過55萬"))) -> 超過55萬 | R22: 象山 | S22: 紅 | T22: 950 | U22: 16 | V22: =IF(U22="","未確認",IF(U22<=0_條件與假設!$B$8,"✓",IF(U22<=16,"△ 11～16分","✗"))) -> △ 11～16分 | W22: 不符：月租577,885超過55萬 | X22: 稅別未寫 | Y22: 同棟廁所新：同棟 10F、21F 廁所為新裝修；本層未另拍。 | Z22: 屋齡28.2年 | AA22: 無 | AB22: 信義房屋 C904199 | AC22: 信義 許雅傑 0966-513-725 | AD22: 信義全球物件頁 | AE22: 物件頁座標：同信義大樓座標（25.024307, 121.569847） | AF22: 開啟地圖
A23: 不符合 | B23: 22 | C23: S14 | D23: 復興南路稀有大空間地下室 B1 | E23: 大安 | F23: 復興南路一段 | G23: B1/7F | H23: 277.81 | I23: 256.87 | J23: 上一版資料：實用坪256.87 | K23: 300000 | L23: 300,000（含稅） | N23: =IF(K23="","",K23+N(M23)) -> 300000 | O23: =IF(OR(I23="",N23=""),"",N23/I23) -> 1167.9059 | P23: =IF(I23="","未揭露",IF(I23>=0_條件與假設!$B$5,"✓","✗")) -> ✓ | Q23: =IF(K23="","未提供",IF(K23<=0_條件與假設!$B$6,"≤45萬",IF(K23<=0_條件與假設!$B$7,"45～55萬","超過55萬"))) -> ≤45萬 | R23: 忠孝復興 | S23: 藍 | T23: 290 | U23: 5 | V23: =IF(U23="","未確認",IF(U23<=0_條件與假設!$B$8,"✓",IF(U23<=16,"△ 11～16分","✗"))) -> ✓ | W23: 不符：地下室／1樓 | Y23: 未檢視：本案不符合條件，本輪未逐張檢視廁所照片；如需要可補看。 | Z23: 46年 | AA23: 無 | AB23: 信義房屋 | AC23: 信義房屋 和平店 傅椿淵 0988-100-122 | AD23: 信義 本戶·5張照片（C348029） | AE23: 物件頁座標：信義全球物件座標（25.0436965, 121.5455521） | AF23: 開啟地圖
A24: 不符合 | B24: 23 | C24: N18 | D24: 新設工大樓 6C（中山北路三段） | E24: 中山 | F24: 中山北路三段22號之1 | G24: 6F/14F | H24: 353.16 | I24: 234.22 | J24: 591 原文「權狀面積353.16坪，淨面積234.22坪」 | K24: 574768 | L24: 547,398 未稅（1,550/坪）→ 含稅 574,768 | M24: 35316 | N24: =IF(K24="","",K24+N(M24)) -> 610084 | O24: =IF(OR(I24="",N24=""),"",N24/I24) -> 2604.7477 | P24: =IF(I24="","未揭露",IF(I24>=0_條件與假設!$B$5,"✓","✗")) -> ✓ | Q24: =IF(K24="","未提供",IF(K24<=0_條件與假設!$B$6,"≤45萬",IF(K24<=0_條件與假設!$B$7,"45～55萬","超過55萬"))) -> 超過55萬 | R24: 民權西路 | S24: 紅 | T24: 66 | U24: 2 | V24: =IF(U24="","未確認",IF(U24<=0_條件與假設!$B$8,"✓",IF(U24<=16,"△ 11～16分","✗"))) -> ✓ | W24: 不符：月租574,768超過55萬 | Y24: 未檢視：本案不符合條件，本輪未逐張檢視廁所照片；如需要可補看。 | Z24: 未提供 | AA24: 不含 | AB24: 591 21672889（大同開發 林副理） | AC24: 大同開發 林副理 02-25925252#2781／0911-033-078 | AD24: 591 物件頁 | AE24: 無座標；依門牌搜尋 | AF24: 開啟地圖
A25: 不符合 | B25: 24 | C25: N21 | D25: 信義大樓 22F | E25: 信義 | F25: 松仁路 | G25: 22F/23F | H25: 243.03 | I25: 221.05 | J25: 信義 C904442：主152.65＋附68.40 | K25: 595424 | L25: 595,424（信義刊登） | M25: 36455 | N25: =IF(K25="","",K25+N(M25)) -> 631879 | O25: =IF(OR(I25="",N25=""),"",N25/I25) -> 2858.5343 | P25: =IF(I25="","未揭露",IF(I25>=0_條件與假設!$B$5,"✓","✗")) -> ✓ | Q25: =IF(K25="","未提供",IF(K25<=0_條件與假設!$B$6,"≤45萬",IF(K25<=0_條件與假設!$B$7,"45～55萬","超過55萬"))) -> 超過55萬 | R25: 象山 | S25: 紅 | T25: 950 | U25: 16 | V25: =IF(U25="","未確認",IF(U25<=0_條件與假設!$B$8,"✓",IF(U25<=16,"△ 11～16分","✗"))) -> △ 11～16分 | W25: 不符：月租595,424超過55萬 | X25: 稅別未寫 | Y25: 同棟廁所新：同棟 10F、21F 廁所為新裝修；本層未另拍。 | Z25: 屋齡28.2年 | AA25: 無 | AB25: 信義房屋 C904442 | AC25: 信義 許雅傑 0966-513-725 | AD25: 信義全球物件頁 | AE25: 物件頁座標：同信義大樓座標（25.024307, 121.569847） | AF25: 開啟地圖
A26: 不符合 | B26: 25 | C26: S04 | D26: 光復南路大坪數辦公 6F | E26: 松山 | F26: 光復南路 | G26: 6F/11F | H26: 211.38 | I26: 211.38 | J26: 尚揚物調表：主建物＋附屬211.38（分割戶） | K26: 401622 | L26: 401,622 含稅（尚揚物調表）；信義 388,500 | M26: 18000 | N26: =IF(K26="","",K26+N(M26)) -> 419622 | O26: =IF(OR(I26="",N26=""),"",N26/I26) -> 1985.1547 | P26: =IF(I26="","未揭露",IF(I26>=0_條件與假設!$B$5,"✓","✗")) -> ✗ | Q26: =IF(K26="","未提供",IF(K26<=0_條件與假設!$B$6,"≤45萬",IF(K26<=0_條件與假設!$B$7,"45～55萬","超過55萬"))) -> ≤45萬 | R26: 國父紀念館 | S26: 藍 | T26: 580 | U26: 10 | V26: =IF(U26="","未確認",IF(U26<=0_條件與假設!$B$8,"✓",IF(U26<=16,"△ 11～16分","✗"))) -> ✓ | W26: 不符：實坪211.38（差8.6坪） | Y26: 廁所無照片：尚揚照片為毛胚（天花未封、水泥地），沒有拍廁所。 | Z26: 51年 | AA26: 可另租(年租2.4萬≈2,000/月) | AB26: 尚揚物調表（光復大樓6F分割，光復南路35號）；信義 C328671 | AC26: 信義房屋 松江南京店 汪智凱 0921-427-889 | AD26: 信義 本戶·19張照片（C328671） | AE26: 物件頁座標：信義全球物件座標（25.0465695, 121.5579704） | AF26: 開啟地圖
A27: 不符合 | B27: 26 | C27: D | D27: 敦化財經大樓 4F之1 | E27: 松山 | F27: 敦化北路214號 | G27: 4F/11F(B2) | H27: 220.07 | I27: 207.21 | J27: 尚揚物調表：主建物207.21 | K27: 440140 | L27: 440,140 含稅（尚揚物調表）；591 同戶 386,839 稅別未寫 | M27: 48415 | N27: =IF(K27="","",K27+N(M27)) -> 488555 | O27: =IF(OR(I27="",N27=""),"",N27/I27) -> 2357.7771 | P27: =IF(I27="","未揭露",IF(I27>=0_條件與假設!$B$5,"✓","✗")) -> ✗ | Q27: =IF(K27="","未提供",IF(K27<=0_條件與假設!$B$6,"≤45萬",IF(K27<=0_條件與假設!$B$7,"45～55萬","超過55萬"))) -> ≤45萬 | R27: 中山國中(棕) 404m（591寫明） | V27: =IF(U27="","未確認",IF(U27<=0_條件與假設!$B$8,"✓",IF(U27<=16,"△ 11～16分","✗"))) -> 未確認 | W27: 不符：實坪207.21（差12.8坪） | X27: 591 與物調表租金／管理費不同（446,480 vs 440,140；47,840 vs 48,415） | Y27: 廁所在外：物調表註明「廁所在外」（公共廁所，非本戶專用）；尚揚照片大多為毛胚（天花拆除、管線外露），沒有拍廁所；591 21711753 共 11 張為大樓外觀、大廳（石材）與周邊，也沒有室內與廁所照片。 | Z27: 35年* | AA27: 坡平另租8,000 | AB27: 尚揚物調表（張正修）；591 20880830、20380770、21711753、21643233（標題「使用約207坪」） | AC27: 尚揚國際 張正修 0937-519-365 | AD27: 591 疑同戶4F 220坪·星辰地產 | AE27: 概略位置：591 21711753 物件頁地圖座標（門牌未揭露，591 標點可能為概略位置）（25.0587943, 121.5464862） | AF27: 開啟地圖
A28: 不符合 | B28: 27 | C28: S15 | D28: 永春地下大空間店商辦 B1 | E28: 信義 | F28: 松德路 | G28: B1/12F | H28: 213.56 | I28: 204.08 | J28: 上一版資料：實用坪204.08 | K28: 218000 | L28: 218,000（含稅） | M28: 18980 | N28: =IF(K28="","",K28+N(M28)) -> 236980 | O28: =IF(OR(I28="",N28=""),"",N28/I28) -> 1161.2113 | P28: =IF(I28="","未揭露",IF(I28>=0_條件與假設!$B$5,"✓","✗")) -> ✗ | Q28: =IF(K28="","未提供",IF(K28<=0_條件與假設!$B$6,"≤45萬",IF(K28<=0_條件與假設!$B$7,"45～55萬","超過55萬"))) -> ≤45萬 | R28: 永春 | S28: 藍 | T28: 190 | U28: 4 | V28: =IF(U28="","未確認",IF(U28<=0_條件與假設!$B$8,"✓",IF(U28<=16,"△ 11～16分","✗"))) -> ✓ | W28: 不符：地下室／1樓；實坪204.08（差15.9坪） | Y28: 未檢視：本案不符合條件，本輪未逐張檢視廁所照片；如需要可補看。 | Z28: 36年 | AA28: 2個升降機械 | AB28: 信義房屋 | AC28: 信義房屋 忠孝永春店 張超鈞 0905-809-808 | AD28: 信義 本戶·18張照片（C360351） | AE28: 物件頁座標：信義全球物件座標（25.039575, 121.57748） | AF28: 開啟地圖
A29: 不符合 | B29: 28 | C29: E | D29: 國泰世華銀行大樓 6F | E29: 大安 | F29: 仁愛路四段85號 | G29: 6F/14F(B2) | H29: 265.72 | I29: 203.79 | J29: 上一版資料：實用坪203.79 | K29: 502211 | L29: 502,211（含稅） | N29: =IF(K29="","",K29+N(M29)) -> 502211 | O29: =IF(OR(I29="",N29=""),"",N29/I29) -> 2464.3555 | P29: =IF(I29="","未揭露",IF(I29>=0_條件與假設!$B$5,"✓","✗")) -> ✗ | Q29: =IF(K29="","未提供",IF(K29<=0_條件與假設!$B$6,"≤45萬",IF(K29<=0_條件與假設!$B$7,"45～55萬","超過55萬"))) -> 45～55萬 | R29: 忠孝敦化 | S29: 藍 | T29: 440 | U29: 8 | V29: =IF(U29="","未確認",IF(U29<=0_條件與假設!$B$8,"✓",IF(U29<=16,"△ 11～16分","✗"))) -> ✓ | W29: 不符：實坪203.79（差16.2坪） | Y29: 未檢視：本案不符合條件，本輪未逐張檢視廁所照片；如需要可補看。 | Z29: 43年 | AA29: 租金內含2坡平+2機車位 | AB29: 物調表 | AC29: 尚揚國際 葉建成 0973-894168 | AD29: 591 物件頁（同戶） | AE29: 門牌定位：Google地圖：仁愛路四段85號（25.0382915, 121.5477716） | AF29: 開啟地圖
A30: 不符合 | B30: 29 | C30: S03 | D30: 敦北長城大樓 3F | E30: 松山 | F30: 八德路三段(長城大樓) | G30: 3F/16F | H30: 225.83 | I30: 201.29 | J30: 尚揚物調表／信義 CZ05326：主189.31＋附11.98 | K30: 474500 | L30: 信義 474,500；尚揚物調表 513,892 含稅（個人稅別） | M30: 27100 | N30: =IF(K30="","",K30+N(M30)) -> 501600 | O30: =IF(OR(I30="",N30=""),"",N30/I30) -> 2491.9271 | P30: =IF(I30="","未揭露",IF(I30>=0_條件與假設!$B$5,"✓","✗")) -> ✗ | Q30: =IF(K30="","未提供",IF(K30<=0_條件與假設!$B$6,"≤45萬",IF(K30<=0_條件與假設!$B$7,"45～55萬","超過55萬"))) -> 45～55萬 | R30: 台北小巨蛋 | S30: 綠 | T30: 400 | U30: 7 | V30: =IF(U30="","未確認",IF(U30<=0_條件與假設!$B$8,"✓",IF(U30<=16,"△ 11～16分","✗"))) -> ✓ | W30: 不符：實坪201.29（差18.7坪） | Y30: 廁所無照片：尚揚照片為現況裝潢（會議室、輕鋼架天花），沒有拍廁所；信義頁面寫「男女分廁」。 | Z30: 34年 | AA30: 無 | AB30: 信義房屋 | AC30: 信義房屋 商仲一部 陳霆瑋 0938-893-639 | AD30: 信義 本戶·21張照片（CZ05326） | AE30: 物件頁座標：信義全球物件座標（25.048055, 121.551782） | AF30: 開啟地圖
A31: 不符合 | B31: 30 | C31: N17 | D31: 松哖大樓 2F | E31: 中山 | F31: 民生東路二段161號＋163號2樓 | G31: 2F/12F(B1) | H31: 227.15 | I31: 198.26 | J31: 尚揚物調表：主建物＋附屬198.26 | K31: 500000 | L31: 500,000 含稅（尚揚物調表）；591 同樓層 439,450～500,000 多筆 | M31: 40000 | N31: =IF(K31="","",K31+N(M31)) -> 540000 | O31: =IF(OR(I31="",N31=""),"",N31/I31) -> 2723.6962 | P31: =IF(I31="","未揭露",IF(I31>=0_條件與假設!$B$5,"✓","✗")) -> ✗ | Q31: =IF(K31="","未提供",IF(K31<=0_條件與假設!$B$6,"≤45萬",IF(K31<=0_條件與假設!$B$7,"45～55萬","超過55萬"))) -> 45～55萬 | R31: 行天宮(橘) 約185～299m | V31: =IF(U31="","未確認",IF(U31<=0_條件與假設!$B$8,"✓",IF(U31<=16,"△ 11～16分","✗"))) -> 未確認 | W31: 不符：實坪198.26（差21.7坪） | Y31: 廁所無照片：尚揚照片為辦公區（水泥地坪、部分天花拆），沒有拍廁所；591 20941554 共 10 張也都是空室（天花部分拆除），沒有廁所。 | Z31: 使照77/03/07（屋齡約38年） | AA31: 坡平另租7,000～8,000 | AB31: 尚揚物調表（劉品汯）；591 21593366、21555597、21985155（標題「使用約180坪」）、22044758、20941554、20864693 | AC31: 尚揚 劉品汯 0901-407-026 | AD31: 591 物件頁 | AE31: 概略位置：591 20941554 物件頁地圖座標（門牌未揭露，591 標點可能為概略位置）（25.0572705, 121.5327198） | AF31: 開啟地圖
A32: 不符合 | B32: 31 | C32: N26 | D32: 安和路一段 11F | E32: 大安 | F32: 安和路一段 | G32: 11F/18F | H32: 224.31 | I32: 192.04 | J32: 住商 WR81767：主173.05＋附18.99 | K32: 486000 | L32: 48.6萬（住商） | M32: 30860 | N32: =IF(K32="","",K32+N(M32)) -> 516860 | O32: =IF(OR(I32="",N32=""),"",N32/I32) -> 2691.4185 | P32: =IF(I32="","未揭露",IF(I32>=0_條件與假設!$B$5,"✓","✗")) -> ✗ | Q32: =IF(K32="","未提供",IF(K32<=0_條件與假設!$B$6,"≤45萬",IF(K32<=0_條件與假設!$B$7,"45～55萬","超過55萬"))) -> 45～55萬 | R32: 忠孝敦化 | S32: 藍 | T32: 255 | U32: 5 | V32: =IF(U32="","未確認",IF(U32<=0_條件與假設!$B$8,"✓",IF(U32<=16,"△ 11～16分","✗"))) -> ✓ | W32: 不符：實坪192.04（差28.0坪） | X32: 稅別未寫 | Y32: 未檢視：本案不符合條件，本輪未逐張檢視廁所照片；如需要可補看。 | Z32: 屋齡38.5年 | AA32: 可租，坡道平面 | AB32: 住商不動產 WR81767 | AC32: 住商仁愛光復 關文乾 02-27764000 | AD32: 住商物件頁 | AE32: 無法定位：沒有門牌也沒有座標 | AF32: —
A33: 不符合 | B33: 32 | C33: F | D33: 友聯大樓 5F | E33: 松山 | F33: 南京東路五段89號 | G33: 5F/15F(B3) | H33: 203.26 | I33: 189.91 | J33: 上一版資料：實用坪189.91 | K33: 405504 | L33: 405,504（含稅） | N33: =IF(K33="","",K33+N(M33)) -> 405504 | O33: =IF(OR(I33="",N33=""),"",N33/I33) -> 2135.243 | P33: =IF(I33="","未揭露",IF(I33>=0_條件與假設!$B$5,"✓","✗")) -> ✗ | Q33: =IF(K33="","未提供",IF(K33<=0_條件與假設!$B$6,"≤45萬",IF(K33<=0_條件與假設!$B$7,"45～55萬","超過55萬"))) -> ≤45萬 | R33: 南京三民 | S33: 綠 | T33: 380 | U33: 7 | V33: =IF(U33="","未確認",IF(U33<=0_條件與假設!$B$8,"✓",IF(U33<=16,"△ 11～16分","✗"))) -> ✓ | W33: 不符：實坪189.91（差30.1坪） | Y33: 未檢視：本案不符合條件，本輪未逐張檢視廁所照片；如需要可補看。 | Z33: 36年 | AA33: 坡平另租7,000~8,000 | AB33: 物調表 | AC33: 尚揚國際 劉品汯 0901-407-026 | AD33: 大樓頁（好房網） | AE33: 門牌定位：Google地圖：南京東路五段89號（25.0517198, 121.5601141） | AF33: 開啟地圖
A34: 不符合 | B34: 33 | C34: A | D34: 安敦國際大樓 7F | E34: 大安 | F34: 安和路一段29號 | G34: 7F/18F(B4) | H34: 220.81 | I34: 189.32 | J34: 上一版資料：實用坪189.32 | K34: 420000 | L34: 420,000（含稅） | M34: 30913 | N34: =IF(K34="","",K34+N(M34)) -> 450913 | O34: =IF(OR(I34="",N34=""),"",N34/I34) -> 2381.7505 | P34: =IF(I34="","未揭露",IF(I34>=0_條件與假設!$B$5,"✓","✗")) -> ✗ | Q34: =IF(K34="","未提供",IF(K34<=0_條件與假設!$B$6,"≤45萬",IF(K34<=0_條件與假設!$B$7,"45～55萬","超過55萬"))) -> ≤45萬 | R34: 忠孝敦化 | S34: 藍 | T34: 185 | U34: 4 | V34: =IF(U34="","未確認",IF(U34<=0_條件與假設!$B$8,"✓",IF(U34<=16,"△ 11～16分","✗"))) -> ✓ | W34: 不符：實坪189.32（差30.7坪） | Y34: 未檢視：本案不符合條件，本輪未逐張檢視廁所照片；如需要可補看。 | Z34: 38年 | AA34: 租金內含2個坡平車位 | AB34: 物調表 | AC34: 尚揚國際 劉品汯 0901-407-026 | AD34: 591 本戶7F·14張照片 | AE34: 無座標；依門牌搜尋 | AF34: 開啟地圖
A35: 不符合 | B35: 34 | C35: B | D35: 中鼎大樓 15F之1 | E35: 大安 | F35: 敦化南路二段77號 | G35: 15F/22F(B2) | H35: 232.22 | I35: 183.22 | J35: 上一版資料：實用坪183.22 | K35: 451087 | L35: 451,087（含稅） | M35: 32511 | N35: =IF(K35="","",K35+N(M35)) -> 483598 | O35: =IF(OR(I35="",N35=""),"",N35/I35) -> 2639.4389 | P35: =IF(I35="","未揭露",IF(I35>=0_條件與假設!$B$5,"✓","✗")) -> ✗ | Q35: =IF(K35="","未提供",IF(K35<=0_條件與假設!$B$6,"≤45萬",IF(K35<=0_條件與假設!$B$7,"45～55萬","超過55萬"))) -> 45～55萬 | R35: 信義安和 | S35: 紅 | T35: 510 | U35: 9 | V35: =IF(U35="","未確認",IF(U35<=0_條件與假設!$B$8,"✓",IF(U35<=16,"△ 11～16分","✗"))) -> ✓ | W35: 不符：實坪183.22（差36.8坪） | Y35: 未檢視：本案不符合條件，本輪未逐張檢視廁所照片；如需要可補看。 | Z35: 42年 | AA35: 坡平另租10,000未稅 | AB35: 物調表 | AC35: 尚揚國際 王智平 0917-154-083 | AD35: 信義 本戶15F·15張照片（CZ05572） | AE35: 物件頁座標：信義全球物件座標(中鼎大樓)（25.030026, 121.549429） | AF35: 開啟地圖
A36: 不符合 | B36: 35 | C36: J15 | D36: 敦化南路2段(中鼎大樓 77號22樓) 22F 230坪 | E36: 大安 | F36: 敦化南路2段(中鼎大樓 77號22樓) | G36: 22F | H36: 230 | I36: 179 | J36: 上一版資料：實用坪179 | K36: 478170 | L36: 478,170（未稅×1.05） | M36: 36800 | N36: =IF(K36="","",K36+N(M36)) -> 514970 | O36: =IF(OR(I36="",N36=""),"",N36/I36) -> 2876.9274 | P36: =IF(I36="","未揭露",IF(I36>=0_條件與假設!$B$5,"✓","✗")) -> ✗ | Q36: =IF(K36="","未提供",IF(K36<=0_條件與假設!$B$6,"≤45萬",IF(K36<=0_條件與假設!$B$7,"45～55萬","超過55萬"))) -> 45～55萬 | R36: 信義安和 | S36: 紅 | T36: 510 | U36: 9 | V36: =IF(U36="","未確認",IF(U36<=0_條件與假設!$B$8,"✓",IF(U36<=16,"△ 11～16分","✗"))) -> ✓ | W36: 不符：實坪179（差41.0坪） | Y36: 未檢視：本案不符合條件，本輪未逐張檢視廁所照片；如需要可補看。 | Z36: 42年 | AA36: 1個12,000/月 | AB36: 傑森愛華 | AC36: 傑森愛華 張先生 0931-330823 | AD36: 傑森愛華單筆報表PDF（中鼎22F·3頁，含照片） | AE36: 物件頁座標：同中鼎大樓(信義全球座標)（25.030026, 121.549429） | AF36: 開啟地圖
A37: 不符合 | B37: 36 | C37: J12 | D37: 敦化南路2段 (中鼎大樓 77號2樓) 2F 222坪 | E37: 大安 | F37: 敦化南路2段 (中鼎大樓 77號2樓) | G37: 2F | H37: 222 | I37: 173 | J37: 上一版資料：實用坪173 | K37: 420000 | L37: 420,000（未稅×1.05） | M37: 33300 | N37: =IF(K37="","",K37+N(M37)) -> 453300 | O37: =IF(OR(I37="",N37=""),"",N37/I37) -> 2620.2312 | P37: =IF(I37="","未揭露",IF(I37>=0_條件與假設!$B$5,"✓","✗")) -> ✗ | Q37: =IF(K37="","未提供",IF(K37<=0_條件與假設!$B$6,"≤45萬",IF(K37<=0_條件與假設!$B$7,"45～55萬","超過55萬"))) -> ≤45萬 | R37: 信義安和 | S37: 紅 | T37: 510 | U37: 9 | V37: =IF(U37="","未確認",IF(U37<=0_條件與假設!$B$8,"✓",IF(U37<=16,"△ 11～16分","✗"))) -> ✓ | W37: 不符：實坪173（差47.0坪） | Y37: 未檢視：本案不符合條件，本輪未逐張檢視廁所照片；如需要可補看。 | Z37: 42年 | AA37: 2個各10,000/月 | AB37: 傑森愛華 | AC37: 傑森愛華 張先生 0931-330823 | AD37: 傑森愛華單筆報表PDF（中鼎2F·2頁，含照片） | AE37: 物件頁座標：同中鼎大樓(信義全球座標)（25.030026, 121.549429） | AF37: 開啟地圖
A38: 不符合 | B38: 37 | C38: S07 | D38: 明水路營業用商辦 4F | E38: 中山 | F38: 明水路(大直) | G38: 4F/10F | H38: 253.16 | I38: 166.77 | J38: 上一版資料：實用坪166.77 | K38: 350000 | L38: 350,000（含稅） | M38: 36676 | N38: =IF(K38="","",K38+N(M38)) -> 386676 | O38: =IF(OR(I38="",N38=""),"",N38/I38) -> 2318.6185 | P38: =IF(I38="","未揭露",IF(I38>=0_條件與假設!$B$5,"✓","✗")) -> ✗ | Q38: =IF(K38="","未提供",IF(K38<=0_條件與假設!$B$6,"≤45萬",IF(K38<=0_條件與假設!$B$7,"45～55萬","超過55萬"))) -> ≤45萬 | R38: 台北小巨蛋 | S38: 綠 | T38: 3310 | U38: 54 | V38: =IF(U38="","未確認",IF(U38<=0_條件與假設!$B$8,"✓",IF(U38<=16,"△ 11～16分","✗"))) -> ✗ | W38: 不符：實坪166.77（差53.2坪）；捷運台北小巨蛋(綠) 54分太遠；大直（依指示不列優先） | Y38: 未檢視：本案不符合條件，本輪未逐張檢視廁所照片；如需要可補看。 | Z38: 25年 | AA38: 5個坡道平面(含) | AB38: 信義房屋 | AC38: 信義房屋 商仲二部 陳泰利 0952-228-883 | AD38: 信義 本戶·12張照片（CZ03701） | AE38: 物件頁座標：信義全球物件座標（25.081444, 121.551799） | AF38: 開啟地圖
A39: 不符合 | B39: 38 | C39: Y2 | D39: 家美金融大樓 15F | E39: 信義 | F39: 忠孝東路五段(家美金融) | G39: 15F/28F | H39: 208.96 | I39: 164.05 | J39: 上一版資料：實用坪164.05 | K39: 398000 | L39: 398,000（含稅） | M39: 36435 | N39: =IF(K39="","",K39+N(M39)) -> 434435 | O39: =IF(OR(I39="",N39=""),"",N39/I39) -> 2648.1865 | P39: =IF(I39="","未揭露",IF(I39>=0_條件與假設!$B$5,"✓","✗")) -> ✗ | Q39: =IF(K39="","未提供",IF(K39<=0_條件與假設!$B$6,"≤45萬",IF(K39<=0_條件與假設!$B$7,"45～55萬","超過55萬"))) -> ≤45萬 | R39: 永春 | S39: 藍 | T39: 200 | U39: 4 | V39: =IF(U39="","未確認",IF(U39<=0_條件與假設!$B$8,"✓",IF(U39<=16,"△ 11～16分","✗"))) -> ✓ | W39: 不符：實坪164.05（差55.9坪） | Y39: 未檢視：本案不符合條件，本輪未逐張檢視廁所照片；如需要可補看。 | Z39: 33年 | AA39: 3個坡道+平面(信義頁;永慶未標) | AB39: 永慶房屋 | AC39: 永慶 南京光復直營店／信義 商仲二部 簡伊涵 0916-263-633／簡文章 0918-520-184 | AD39: 永慶 本戶15F·14張照片 | AE39: 物件頁座標：信義全球物件座標(家美金融)（25.040833, 121.578638） | AF39: 開啟地圖
A40: 不符合 | B40: 39 | C40: G | D40: 白宮企業大樓 5F | E40: 松山 | F40: 南京東路三段346號 | G40: 5F/12F(B1) | H40: 207.04 | I40: 156.93 | J40: 上一版資料：實用坪156.93 | K40: 360150 | L40: 360,150（含稅） | M40: 28984 | N40: =IF(K40="","",K40+N(M40)) -> 389134 | O40: =IF(OR(I40="",N40=""),"",N40/I40) -> 2479.6661 | P40: =IF(I40="","未揭露",IF(I40>=0_條件與假設!$B$5,"✓","✗")) -> ✗ | Q40: =IF(K40="","未提供",IF(K40<=0_條件與假設!$B$6,"≤45萬",IF(K40<=0_條件與假設!$B$7,"45～55萬","超過55萬"))) -> ≤45萬 | R40: 台北小巨蛋 | S40: 綠 | T40: 390 | U40: 7 | V40: =IF(U40="","未確認",IF(U40<=0_條件與假設!$B$8,"✓",IF(U40<=16,"△ 11～16分","✗"))) -> ✓ | W40: 不符：實坪156.93（差63.1坪） | Y40: 未檢視：本案不符合條件，本輪未逐張檢視廁所照片；如需要可補看。 | Z40: 48年 | AA40: 無車位 | AB40: 物調表 | AC40: 尚揚國際 張正修 0937-519-365 | AD40: 好房網大樓頁·10張照片（本戶207坪整層無公開頁） | AE40: 門牌定位：Google地圖：南京東路三段346號白宮企業大樓（25.0513632, 121.5480628） | AF40: 開啟地圖
A41: 不符合 | B41: 40 | C41: J07 | D41: 仁愛路4段近復興南路 (鴻霖大樓 25號10樓之2) 10F 210坪 | E41: 大安 | F41: 仁愛路4段近復興南路 (鴻霖大樓 25號10樓之2) | G41: 10F | H41: 210 | I41: 153 | J41: 上一版資料：實用坪153 | K41: 367500 | L41: 367,500（未稅×1.05） | M41: 39900 | N41: =IF(K41="","",K41+N(M41)) -> 407400 | O41: =IF(OR(I41="",N41=""),"",N41/I41) -> 2662.7451 | P41: =IF(I41="","未揭露",IF(I41>=0_條件與假設!$B$5,"✓","✗")) -> ✗ | Q41: =IF(K41="","未提供",IF(K41<=0_條件與假設!$B$6,"≤45萬",IF(K41<=0_條件與假設!$B$7,"45～55萬","超過55萬"))) -> ≤45萬 | R41: 忠孝復興 | S41: 藍 | T41: 370 | U41: 6 | V41: =IF(U41="","未確認",IF(U41<=0_條件與假設!$B$8,"✓",IF(U41<=16,"△ 11～16分","✗"))) -> ✓ | W41: 不符：實坪153（差67.0坪） | Y41: 未檢視：本案不符合條件，本輪未逐張檢視廁所照片；如需要可補看。 | Z41: 55年 | AA41: 另租(費用未提供) | AB41: 傑森愛華 | AC41: 傑森愛華 張先生 0931-330823 | AD41: 傑森愛華單筆報表PDF（鴻霖10F之2·3頁，含照片） | AE41: 門牌定位：Google地圖：仁愛路四段25號鴻霖大廈（25.0385627, 121.5451228） | AF41: 開啟地圖
A42: 不符合 | B42: 41 | C42: J16 | D42: 八德路近復興北路 (中影八德大樓 八德路二段260號2樓全層) 2F 200坪 | E42: 中山 | F42: 八德路二段260號2樓全層(中影八德大樓) | G42: 2F/11F(B3) | H42: 200 | I42: 150 | J42: 上一版資料：實用坪150 | K42: 308700 | L42: 308,700（未稅×1.05） | M42: 30000 | N42: =IF(K42="","",K42+N(M42)) -> 338700 | O42: =IF(OR(I42="",N42=""),"",N42/I42) -> 2258 | P42: =IF(I42="","未揭露",IF(I42>=0_條件與假設!$B$5,"✓","✗")) -> ✗ | Q42: =IF(K42="","未提供",IF(K42<=0_條件與假設!$B$6,"≤45萬",IF(K42<=0_條件與假設!$B$7,"45～55萬","超過55萬"))) -> ≤45萬 | R42: 忠孝復興 | S42: 藍 | T42: 630 | U42: 11 | V42: =IF(U42="","未確認",IF(U42<=0_條件與假設!$B$8,"✓",IF(U42<=16,"△ 11～16分","✗"))) -> △ 11～16分 | W42: 不符：實坪150（差70.0坪） | Y42: 未檢視：本案不符合條件，本輪未逐張檢視廁所照片；如需要可補看。 | Z42: 40年 | AA42: 1個 7,000/月(未稅) | AB42: 傑森愛華 | AC42: 傑森愛華 張先生 0931-330823 | AD42: 傑森愛華單筆報表PDF（中影八德2F·11頁，含照片/使照） | AE42: 門牌定位：Google地圖：八德路二段256～260號中影八德大樓（25.0466545, 121.5409442） | AF42: 開啟地圖
A43: 不符合 | B43: 42 | C43: I | D43: 光復北路新大樓 5F | E43: 松山 | F43: 光復北路(門牌未揭露) | G43: 5F/11F | H43: 203.56 | I43: 119.66 | J43: 上一版資料：實用坪119.66 | K43: 305340 | L43: 305,340（含稅） | M43: 32570 | N43: =IF(K43="","",K43+N(M43)) -> 337910 | O43: =IF(OR(I43="",N43=""),"",N43/I43) -> 2823.9178 | P43: =IF(I43="","未揭露",IF(I43>=0_條件與假設!$B$5,"✓","✗")) -> ✗ | Q43: =IF(K43="","未提供",IF(K43<=0_條件與假設!$B$6,"≤45萬",IF(K43<=0_條件與假設!$B$7,"45～55萬","超過55萬"))) -> ≤45萬 | R43: 南京三民 | S43: 綠 | T43: 450 | U43: 8 | V43: =IF(U43="","未確認",IF(U43<=0_條件與假設!$B$8,"✓",IF(U43<=16,"△ 11～16分","✗"))) -> ✓ | W43: 不符：實坪119.66（差100.3坪） | Y43: 未檢視：本案不符合條件，本輪未逐張檢視廁所照片；如需要可補看。 | Z43: 1.1年 | AA43: 無;可另租坡道平面(費用未提供) | AB43: 信義房屋 | AC43: 信義房屋 復興民生店 施雅惠 0955-237827 | AD43: 信義全球 本戶·14張照片（C355686） | AE43: 概略位置：信義全球物件座標（25.050386, 121.559536） | AF43: 開啟地圖
A44: 不符合 | B44: 43 | C44: S08 | D44: 國票大樓 15F C | E44: 中山 | F44: 樂群三路(大直) | G44: 15F/17F | H44: 213.3 | I44: 87.55 | J44: 上一版資料：實用坪87.55 | K44: 467500 | L44: 467,500（含稅） | M44: 33600 | N44: =IF(K44="","",K44+N(M44)) -> 501100 | O44: =IF(OR(I44="",N44=""),"",N44/I44) -> 5723.5865 | P44: =IF(I44="","未揭露",IF(I44>=0_條件與假設!$B$5,"✓","✗")) -> ✗ | Q44: =IF(K44="","未提供",IF(K44<=0_條件與假設!$B$6,"≤45萬",IF(K44<=0_條件與假設!$B$7,"45～55萬","超過55萬"))) -> 45～55萬 | R44: 台北小巨蛋 | S44: 綠 | T44: 3440 | U44: 56 | V44: =IF(U44="","未確認",IF(U44<=0_條件與假設!$B$8,"✓",IF(U44<=16,"△ 11～16分","✗"))) -> ✗ | W44: 不符：實坪87.55（差132.4坪）；捷運台北小巨蛋(綠) 56分太遠；大直（依指示不列優先） | Y44: 未檢視：本案不符合條件，本輪未逐張檢視廁所照片；如需要可補看。 | Z44: 7年 | AA44: 6個坡道平面(含) | AB44: 信義房屋 | AC44: 信義房屋 大直明水店 林彥儒 0988-520-520 | AD44: 信義 本戶·12張照片（C346398） | AE44: 物件頁座標：信義全球物件座標（25.082506, 121.554582） | AF44: 開啟地圖
A45: 不符合 | B45: 44 | C45: W10 | D45: 松山路 7F | E45: 信義 | F45: 松山路 | G45: 7F/10F | H45: 205 | J45: 未揭露 | K45: 300000 | L45: 300,000（刊登價,稅別未標） | N45: =IF(K45="","",K45+N(M45)) -> 300000 | O45: =IF(OR(I45="",N45=""),"",N45/I45) | P45: =IF(I45="","未揭露",IF(I45>=0_條件與假設!$B$5,"✓","✗")) -> 未揭露 | Q45: =IF(K45="","未提供",IF(K45<=0_條件與假設!$B$6,"≤45萬",IF(K45<=0_條件與假設!$B$7,"45～55萬","超過55萬"))) -> ≤45萬 | R45: 未確認 | V45: =IF(U45="","未確認",IF(U45<=0_條件與假設!$B$8,"✓",IF(U45<=16,"△ 11～16分","✗"))) -> 未確認 | W45: 不符：權狀僅205坪（實坪必低於220） | Y45: 未檢視：本案不符合條件，本輪未逐張檢視廁所照片；如需要可補看。 | Z45: 缺 | AA45: 平面式 | AB45: HouseWeb | AC45: 優昇商用 連先生 02-8751-6676 | AD45: HouseWeb·20張 | AE45: 無法定位：沒有門牌也沒有座標 | AF45: —
A46: 不符合 | B46: 45 | C46: W13 | D46: 林森北路 6F | E46: 中山 | F46: 林森北路 | G46: 6F/11F(B2) | H46: 200.79 | J46: 未揭露 | K46: 320000 | L46: 320,000（刊登價,稅別未標） | N46: =IF(K46="","",K46+N(M46)) -> 320000 | O46: =IF(OR(I46="",N46=""),"",N46/I46) | P46: =IF(I46="","未揭露",IF(I46>=0_條件與假設!$B$5,"✓","✗")) -> 未揭露 | Q46: =IF(K46="","未提供",IF(K46<=0_條件與假設!$B$6,"≤45萬",IF(K46<=0_條件與假設!$B$7,"45～55萬","超過55萬"))) -> ≤45萬 | R46: 未確認 | V46: =IF(U46="","未確認",IF(U46<=0_條件與假設!$B$8,"✓",IF(U46<=16,"△ 11～16分","✗"))) -> 未確認 | W46: 不符：權狀僅200.79坪（實坪必低於220） | Y46: 未檢視：本案不符合條件，本輪未逐張檢視廁所照片；如需要可補看。 | Z46: 缺 | AA46: 無車位 | AB46: HouseWeb | AC46: 弗利艾樂 辦公室出租商業網 0913-958-003 | AD46: HouseWeb·27張 | AE46: 無法定位：沒有門牌也沒有座標 | AF46: —
A47: 不符合 | B47: 46 | C47: N24 | D47: 星勢力大樓 4F（大直） | E47: 中山 | F47: 明水路 | G47: 4F/10F | H47: 308.7 | J47: 591 只寫308.7坪 | K47: 350000 | L47: 350,000（591 21803100，含車位） | N47: =IF(K47="","",K47+N(M47)) -> 350000 | O47: =IF(OR(I47="",N47=""),"",N47/I47) | P47: =IF(I47="","未揭露",IF(I47>=0_條件與假設!$B$5,"✓","✗")) -> 未揭露 | Q47: =IF(K47="","未提供",IF(K47<=0_條件與假設!$B$6,"≤45萬",IF(K47<=0_條件與假設!$B$7,"45～55萬","超過55萬"))) -> ≤45萬 | R47: 大直(棕) 428m | V47: =IF(U47="","未確認",IF(U47<=0_條件與假設!$B$8,"✓",IF(U47<=16,"△ 11～16分","✗"))) -> 未確認 | W47: 不符：大直（依指示不列優先） | X47: 實坪未揭露 | Y47: 未檢視：本案不符合條件，本輪未逐張檢視廁所照片；如需要可補看。 | Z47: 未提供 | AA47: 含車位 | AB47: 591 21803100 | AC47: 591 刊登人 | AD47: 591 物件頁 | AE47: 無法定位：沒有門牌也沒有座標 | AF47: —
A48: 不符合 | B48: 47 | C48: W03 | D48: 明水路（大直） 4F | E48: 中山 | F48: 明水路(大直) | G48: 4F/10F | H48: 253 | J48: 未揭露 | K48: 350000 | L48: 350,000（刊登價,稅別未標） | N48: =IF(K48="","",K48+N(M48)) -> 350000 | O48: =IF(OR(I48="",N48=""),"",N48/I48) | P48: =IF(I48="","未揭露",IF(I48>=0_條件與假設!$B$5,"✓","✗")) -> 未揭露 | Q48: =IF(K48="","未提供",IF(K48<=0_條件與假設!$B$6,"≤45萬",IF(K48<=0_條件與假設!$B$7,"45～55萬","超過55萬"))) -> ≤45萬 | R48: 台北小巨蛋 | S48: 綠 | T48: 3310 | U48: 54 | V48: =IF(U48="","未確認",IF(U48<=0_條件與假設!$B$8,"✓",IF(U48<=16,"△ 11～16分","✗"))) -> ✗ | W48: 不符：捷運台北小巨蛋(綠) 54分太遠；大直（依指示不列優先） | Y48: 未檢視：本案不符合條件，本輪未逐張檢視廁所照片；如需要可補看。 | Z48: 缺 | AA48: 未揭露 | AB48: HouseWeb | AC48: 優昇商用 連先生 02-8751-6676 | AD48: HouseWeb·27張 | AE48: 物件頁座標：同 S07 明水路物件（HouseWeb同戶）（25.081444, 121.551799） | AF48: 開啟地圖
A49: 不符合 | B49: 48 | C49: W02 | D49: 八德路四段 9F | E49: 松山 | F49: 八德路四段 | G49: 9F/16F | H49: 206 | J49: 未揭露 | K49: 350900 | L49: 350,900（刊登價,稅別未標） | N49: =IF(K49="","",K49+N(M49)) -> 350900 | O49: =IF(OR(I49="",N49=""),"",N49/I49) | P49: =IF(I49="","未揭露",IF(I49>=0_條件與假設!$B$5,"✓","✗")) -> 未揭露 | Q49: =IF(K49="","未提供",IF(K49<=0_條件與假設!$B$6,"≤45萬",IF(K49<=0_條件與假設!$B$7,"45～55萬","超過55萬"))) -> ≤45萬 | R49: 未確認 | V49: =IF(U49="","未確認",IF(U49<=0_條件與假設!$B$8,"✓",IF(U49<=16,"△ 11～16分","✗"))) -> 未確認 | W49: 不符：權狀僅206坪（實坪必低於220） | Y49: 未檢視：本案不符合條件，本輪未逐張檢視廁所照片；如需要可補看。 | Z49: 缺 | AA49: 平面式 | AB49: HouseWeb | AC49: 優昇商用 連先生 02-8751-6676 / 0939-658-987 | AD49: HouseWeb·38張 | AE49: 無法定位：沒有門牌也沒有座標 | AF49: —
A50: 不符合 | B50: 49 | C50: J11 | D50: 八德路vs龍江路 2F 220坪 | E50: 松山 | F50: 八德路vs龍江路 | G50: 2F | H50: 220 | J50: 未揭露 | K50: 369600 | L50: 369,600（未稅×1.05） | N50: =IF(K50="","",K50+N(M50)) -> 369600 | O50: =IF(OR(I50="",N50=""),"",N50/I50) | P50: =IF(I50="","未揭露",IF(I50>=0_條件與假設!$B$5,"✓","✗")) -> 未揭露 | Q50: =IF(K50="","未提供",IF(K50<=0_條件與假設!$B$6,"≤45萬",IF(K50<=0_條件與假設!$B$7,"45～55萬","超過55萬"))) -> ≤45萬 | R50: 忠孝復興 | S50: 藍 | T50: 660 | U50: 11 | V50: =IF(U50="","未確認",IF(U50<=0_條件與假設!$B$8,"✓",IF(U50<=16,"△ 11～16分","✗"))) -> △ 11～16分 | W50: 不符：權狀220坪，公設比需≤0.0%才達220（實坪未揭露） | Y50: 未檢視：本案不符合條件，本輪未逐張檢視廁所照片；如需要可補看。 | Z50: 缺 | AA50: 缺 | AB50: 傑森愛華 | AC50: 傑森愛華 張先生 0931-330823 | AD50: 傑森愛華原始PDF 第3頁（此列無照片） | AE50: 概略位置：八德路×龍江路口（清單未給門牌）（25.0467545, 121.5404769） | AF50: 開啟地圖
A51: 不符合 | B51: 50 | C51: W06 | D51: 明水路（大直） 4F | E51: 中山 | F51: 明水路(大直) | G51: 4F/10F | H51: 252 | J51: 未揭露 | K51: 380000 | L51: 380,000（刊登價,稅別未標） | N51: =IF(K51="","",K51+N(M51)) -> 380000 | O51: =IF(OR(I51="",N51=""),"",N51/I51) | P51: =IF(I51="","未揭露",IF(I51>=0_條件與假設!$B$5,"✓","✗")) -> 未揭露 | Q51: =IF(K51="","未提供",IF(K51<=0_條件與假設!$B$6,"≤45萬",IF(K51<=0_條件與假設!$B$7,"45～55萬","超過55萬"))) -> ≤45萬 | R51: 台北小巨蛋 | S51: 綠 | T51: 3310 | U51: 54 | V51: =IF(U51="","未確認",IF(U51<=0_條件與假設!$B$8,"✓",IF(U51<=16,"△ 11～16分","✗"))) -> ✗ | W51: 不符：捷運台北小巨蛋(綠) 54分太遠；大直（依指示不列優先） | Y51: 未檢視：本案不符合條件，本輪未逐張檢視廁所照片；如需要可補看。 | Z51: 缺 | AA51: 平面式 | AB51: HouseWeb | AC51: 優昇商用 連先生 02-8751-6676 | AD51: HouseWeb·37張 | AE51: 概略位置：同明水路大樓（推定，HouseWeb未給門牌）（25.081444, 121.551799） | AF51: 開啟地圖
A52: 不符合 | B52: 51 | C52: W11 | D52: 光復南路 7F | E52: 松山 | F52: 光復南路 | G52: 7F/11F(B2) | H52: 211 | J52: 未揭露 | K52: 400000 | L52: 400,000（含稅(591備註)） | N52: =IF(K52="","",K52+N(M52)) -> 400000 | O52: =IF(OR(I52="",N52=""),"",N52/I52) | P52: =IF(I52="","未揭露",IF(I52>=0_條件與假設!$B$5,"✓","✗")) -> 未揭露 | Q52: =IF(K52="","未提供",IF(K52<=0_條件與假設!$B$6,"≤45萬",IF(K52<=0_條件與假設!$B$7,"45～55萬","超過55萬"))) -> ≤45萬 | R52: 南京三民 | S52: 綠 | T52: 659 | U52: 11 | V52: =IF(U52="","未確認",IF(U52<=0_條件與假設!$B$8,"✓",IF(U52<=16,"△ 11～16分","✗"))) -> △ 11～16分 | W52: 不符：權狀僅211坪（實坪必低於220） | Y52: 未檢視：本案不符合條件，本輪未逐張檢視廁所照片；如需要可補看。 | Z52: 缺 | AA52: 可承租 | AB52: HouseWeb | AC52: 弗利艾樂 辦公室出租商業網 0913-958-003 / 02-2547-1511 | AD52: HouseWeb·40張 | AE52: 無法定位：沒有門牌也沒有座標 | AF52: —
A53: 不符合 | B53: 52 | C53: H | D53: 光復南路 7F | E53: 松山 | F53: 光復南路(門牌未揭露) | G53: 7F/11F | H53: 211 | J53: 未揭露 | K53: 400000 | L53: 400,000（含稅） | M53: 17935 | N53: =IF(K53="","",K53+N(M53)) -> 417935 | O53: =IF(OR(I53="",N53=""),"",N53/I53) | P53: =IF(I53="","未揭露",IF(I53>=0_條件與假設!$B$5,"✓","✗")) -> 未揭露 | Q53: =IF(K53="","未提供",IF(K53<=0_條件與假設!$B$6,"≤45萬",IF(K53<=0_條件與假設!$B$7,"45～55萬","超過55萬"))) -> ≤45萬 | R53: 南京三民 | S53: 綠 | T53: 659 | U53: 11 | V53: =IF(U53="","未確認",IF(U53<=0_條件與假設!$B$8,"✓",IF(U53<=16,"△ 11～16分","✗"))) -> △ 11～16分 | W53: 不符：權狀僅211坪（實坪必低於220） | Y53: 未檢視：本案不符合條件，本輪未逐張檢視廁所照片；如需要可補看。 | Z53: 缺 | AA53: 未揭露 | AB53: 591 | AC53: 言成不動產 呂小姐 0955-577-686 | AD53: HouseWeb 本戶·40張照片 | AE53: 無法定位：沒有門牌也沒有座標 | AF53: —
A54: 不符合 | B54: 53 | C54: J01 | D54: 信義路5段(環球) 18F 201坪 | E54: 信義 | F54: 信義路5段(環球) | G54: 18F | H54: 201 | J54: 未揭露 | K54: 401100 | L54: 401,100（未稅×1.05） | N54: =IF(K54="","",K54+N(M54)) -> 401100 | O54: =IF(OR(I54="",N54=""),"",N54/I54) | P54: =IF(I54="","未揭露",IF(I54>=0_條件與假設!$B$5,"✓","✗")) -> 未揭露 | Q54: =IF(K54="","未提供",IF(K54<=0_條件與假設!$B$6,"≤45萬",IF(K54<=0_條件與假設!$B$7,"45～55萬","超過55萬"))) -> ≤45萬 | R54: 象山 | S54: 紅 | T54: 510 | U54: 9 | V54: =IF(U54="","未確認",IF(U54<=0_條件與假設!$B$8,"✓",IF(U54<=16,"△ 11～16分","✗"))) -> ✓ | W54: 不符：權狀僅201坪（實坪必低於220） | Y54: 未檢視：本案不符合條件，本輪未逐張檢視廁所照片；如需要可補看。 | Z54: 缺 | AA54: 缺 | AB54: 傑森愛華 | AC54: 傑森愛華 張先生 0931-330823 | AD54: 傑森愛華原始PDF 第1頁（含照片） | AE54: 概略位置：同環球世貿（S13座標，清單未給門牌）（25.028332, 121.571059） | AF54: 開啟地圖
A55: 不符合 | B55: 54 | C55: J02 | D55: 南京東路5段近三民站 5F 204坪 | E55: 松山 | F55: 南京東路5段近三民站 | G55: 5F | H55: 204 | J55: 未揭露 | K55: 404985 | L55: 404,985（未稅×1.05） | N55: =IF(K55="","",K55+N(M55)) -> 404985 | O55: =IF(OR(I55="",N55=""),"",N55/I55) | P55: =IF(I55="","未揭露",IF(I55>=0_條件與假設!$B$5,"✓","✗")) -> 未揭露 | Q55: =IF(K55="","未提供",IF(K55<=0_條件與假設!$B$6,"≤45萬",IF(K55<=0_條件與假設!$B$7,"45～55萬","超過55萬"))) -> ≤45萬 | R55: 未確認 | V55: =IF(U55="","未確認",IF(U55<=0_條件與假設!$B$8,"✓",IF(U55<=16,"△ 11～16分","✗"))) -> 未確認 | W55: 不符：權狀僅204坪（實坪必低於220） | Y55: 未檢視：本案不符合條件，本輪未逐張檢視廁所照片；如需要可補看。 | Z55: 缺 | AA55: 缺 | AB55: 傑森愛華 | AC55: 傑森愛華 張先生 0931-330823 | AD55: 傑森愛華原始PDF 第1頁（含照片） | AE55: 無法定位：沒有門牌也沒有座標 | AF55: —
A56: 不符合 | B56: 55 | C56: W07 | D56: 明水路（大直） 3F | E56: 中山 | F56: 明水路(大直) | G56: 3F/10F | H56: 276 | J56: 未揭露 | K56: 413800 | L56: 413,800（刊登價,稅別未標） | N56: =IF(K56="","",K56+N(M56)) -> 413800 | O56: =IF(OR(I56="",N56=""),"",N56/I56) | P56: =IF(I56="","未揭露",IF(I56>=0_條件與假設!$B$5,"✓","✗")) -> 未揭露 | Q56: =IF(K56="","未提供",IF(K56<=0_條件與假設!$B$6,"≤45萬",IF(K56<=0_條件與假設!$B$7,"45～55萬","超過55萬"))) -> ≤45萬 | R56: 台北小巨蛋 | S56: 綠 | T56: 3310 | U56: 54 | V56: =IF(U56="","未確認",IF(U56<=0_條件與假設!$B$8,"✓",IF(U56<=16,"△ 11～16分","✗"))) -> ✗ | W56: 不符：捷運台北小巨蛋(綠) 54分太遠；大直（依指示不列優先） | Y56: 未檢視：本案不符合條件，本輪未逐張檢視廁所照片；如需要可補看。 | Z56: 缺 | AA56: 平面式(費用另計) | AB56: HouseWeb | AC56: 優昇商用 連先生 02-8751-6676 | AD56: HouseWeb·27張 | AE56: 概略位置：同明水路大樓（推定，HouseWeb未給門牌）（25.081444, 121.551799） | AF56: 開啟地圖
A57: 不符合 | B57: 56 | C57: N22 | D57: 建國北路三段 2F（合併物件） | E57: 中山 | F57: 建國北路三段 | G57: 2F/11F | H57: 306.62 | J57: 591 原文「刊登權狀坪數306.62坪（此為合併物件）」 | K57: 417900 | L57: 398,000 未稅（591 21200503）→ 含稅 417,900；另一刊登 22058045 寫306坪 415,000 | N57: =IF(K57="","",K57+N(M57)) -> 417900 | O57: =IF(OR(I57="",N57=""),"",N57/I57) | P57: =IF(I57="","未揭露",IF(I57>=0_條件與假設!$B$5,"✓","✗")) -> 未揭露 | Q57: =IF(K57="","未提供",IF(K57<=0_條件與假設!$B$6,"≤45萬",IF(K57<=0_條件與假設!$B$7,"45～55萬","超過55萬"))) -> ≤45萬 | R57: 行天宮(橘) 486m | V57: =IF(U57="","未確認",IF(U57<=0_條件與假設!$B$8,"✓",IF(U57<=16,"△ 11～16分","✗"))) -> 未確認 | W57: 不符：附近無綠紅藍線（僅橘線行天宮486m） | X57: 實坪未揭露 | Y57: 未檢視：本案不符合條件，本輪未逐張檢視廁所照片；如需要可補看。 | Z57: 未提供 | AA57: 未提供 | AB57: 591 21200503（尚揚 陳先生）、22058045 | AC57: 尚揚 陳先生 0906-118-677 | AD57: 591 物件頁 | AE57: 無法定位：沒有門牌也沒有座標 | AF57: —
A58: 不符合 | B58: 57 | C58: J09 | D58: 敦化北路VS民生東路 2F 211坪 | E58: 松山 | F58: 敦化北路VS民生東路 | G58: 2F | H58: 211 | J58: 未揭露 | K58: 436800 | L58: 436,800（未稅×1.05） | N58: =IF(K58="","",K58+N(M58)) -> 436800 | O58: =IF(OR(I58="",N58=""),"",N58/I58) | P58: =IF(I58="","未揭露",IF(I58>=0_條件與假設!$B$5,"✓","✗")) -> 未揭露 | Q58: =IF(K58="","未提供",IF(K58<=0_條件與假設!$B$6,"≤45萬",IF(K58<=0_條件與假設!$B$7,"45～55萬","超過55萬"))) -> ≤45萬 | R58: 台北小巨蛋 | S58: 綠 | T58: 760 | U58: 13 | V58: =IF(U58="","未確認",IF(U58<=0_條件與假設!$B$8,"✓",IF(U58<=16,"△ 11～16分","✗"))) -> △ 11～16分 | W58: 不符：權狀僅211坪（實坪必低於220） | Y58: 未檢視：本案不符合條件，本輪未逐張檢視廁所照片；如需要可補看。 | Z58: 缺 | AA58: 缺 | AB58: 傑森愛華 | AC58: 傑森愛華 張先生 0931-330823 | AD58: 傑森愛華原始PDF 第3頁（含照片） | AE58: 概略位置：敦化北路×民生東路口（清單未給門牌）（25.058038, 121.549018） | AF58: 開啟地圖
A59: 不符合 | B59: 58 | C59: J06 | D59: 中山北路1段近市民大道 9F 209坪 | E59: 中山 | F59: 中山北路1段近市民大道 | G59: 9F | H59: 209 | J59: 未揭露 | K59: 438900 | L59: 438,900（未稅×1.05） | N59: =IF(K59="","",K59+N(M59)) -> 438900 | O59: =IF(OR(I59="",N59=""),"",N59/I59) | P59: =IF(I59="","未揭露",IF(I59>=0_條件與假設!$B$5,"✓","✗")) -> 未揭露 | Q59: =IF(K59="","未提供",IF(K59<=0_條件與假設!$B$6,"≤45萬",IF(K59<=0_條件與假設!$B$7,"45～55萬","超過55萬"))) -> ≤45萬 | R59: 台北車站 | S59: 紅藍 | T59: 390 | U59: 7 | V59: =IF(U59="","未確認",IF(U59<=0_條件與假設!$B$8,"✓",IF(U59<=16,"△ 11～16分","✗"))) -> ✓ | W59: 不符：權狀僅209坪（實坪必低於220） | Y59: 未檢視：本案不符合條件，本輪未逐張檢視廁所照片；如需要可補看。 | Z59: 缺 | AA59: 缺 | AB59: 傑森愛華 | AC59: 傑森愛華 張先生 0931-330823 | AD59: 傑森愛華原始PDF 第2頁（含照片） | AE59: 概略位置：中山北路一段×市民大道口（清單未給門牌）（25.0482394, 121.5206867） | AF59: 開啟地圖
A60: 不符合 | B60: 59 | C60: W04 | D60: 植福路（大直） 9F | E60: 中山 | F60: 植福路(大直) | G60: 9F/10F | H60: 203 | J60: 未揭露 | K60: 446800 | L60: 446,800（刊登價,稅別未標） | N60: =IF(K60="","",K60+N(M60)) -> 446800 | O60: =IF(OR(I60="",N60=""),"",N60/I60) | P60: =IF(I60="","未揭露",IF(I60>=0_條件與假設!$B$5,"✓","✗")) -> 未揭露 | Q60: =IF(K60="","未提供",IF(K60<=0_條件與假設!$B$6,"≤45萬",IF(K60<=0_條件與假設!$B$7,"45～55萬","超過55萬"))) -> ≤45萬 | R60: 未確認 | V60: =IF(U60="","未確認",IF(U60<=0_條件與假設!$B$8,"✓",IF(U60<=16,"△ 11～16分","✗"))) -> 未確認 | W60: 不符：權狀僅203坪（實坪必低於220）；大直（依指示不列優先） | Y60: 未檢視：本案不符合條件，本輪未逐張檢視廁所照片；如需要可補看。 | Z60: 缺 | AA60: 平面式 | AB60: HouseWeb | AC60: 優昇商用 連先生 02-8751-6676 | AD60: HouseWeb·43張 | AE60: 無法定位：沒有門牌也沒有座標 | AF60: —
A61: 不符合 | B61: 60 | C61: Y1 | D61: 安敦國際大樓 14F | E61: 大安 | F61: 安和路一段(安敦國際大樓) | G61: 14F/18F | H61: 224.18 | J61: 未揭露 | K61: 448000 | L61: 448,000（含稅） | M61: 32000 | N61: =IF(K61="","",K61+N(M61)) -> 480000 | O61: =IF(OR(I61="",N61=""),"",N61/I61) | P61: =IF(I61="","未揭露",IF(I61>=0_條件與假設!$B$5,"✓","✗")) -> 未揭露 | Q61: =IF(K61="","未提供",IF(K61<=0_條件與假設!$B$6,"≤45萬",IF(K61<=0_條件與假設!$B$7,"45～55萬","超過55萬"))) -> ≤45萬 | R61: 忠孝敦化 | S61: 藍 | T61: 260 | U61: 5 | V61: =IF(U61="","未確認",IF(U61<=0_條件與假設!$B$8,"✓",IF(U61<=16,"△ 11～16分","✗"))) -> ✓ | W61: 不符：權狀224.18坪，公設比需≤1.9%才達220（實坪未揭露） | Y61: 未檢視：本案不符合條件，本輪未逐張檢視廁所照片；如需要可補看。 | Z61: 37年 | AA61: 租金內含坡道平面車位(數量未標) | AB61: 永慶房屋 | AC61: 永慶房屋 南京光復直營店 簡伊涵 0916-263-633 | AD61: 永慶 本戶14F·15張照片 | AE61: 物件頁座標：同安敦國際大樓(信義全球座標)（25.03901, 121.550592） | AF61: 開啟地圖
A62: 不符合 | B62: 61 | C62: N34 | D62: 民權西路 5F（民權西路站） | E62: 大同 | F62: 民權西路 | G62: 5F/13F | H62: 303 | J62: 591 11580037 刊登303坪，內文「廣告顯示使用面積為含公設面積」 | K62: 450000 | L62: 450,000（591 11580037，稅別未寫） | N62: =IF(K62="","",K62+N(M62)) -> 450000 | O62: =IF(OR(I62="",N62=""),"",N62/I62) | P62: =IF(I62="","未揭露",IF(I62>=0_條件與假設!$B$5,"✓","✗")) -> 未揭露 | Q62: =IF(K62="","未提供",IF(K62<=0_條件與假設!$B$6,"≤45萬",IF(K62<=0_條件與假設!$B$7,"45～55萬","超過55萬"))) -> ≤45萬 | R62: 民權西路 | S62: 紅 | T62: 164 | U62: 3 | V62: =IF(U62="","未確認",IF(U62<=0_條件與假設!$B$8,"✓",IF(U62<=16,"△ 11～16分","✗"))) -> ✓ | W62: 不符：非指定行政區 | X62: 大同區（不在五區內）；實坪未揭露；租金稅別未寫；管理費未提供 | Y62: 廁所無照片：591 11580037 共 12 張為現有裝潢（木紋地板、玻璃隔間會議室、茶水區），沒有拍廁所；照片上傳於 2021/09，現況需現勘。 | Z62: 未提供 | AA62: 未提供 | AB62: 591 11580037（住商不動產安和仁愛加盟店 林玉蘋） | AC62: 住商 林玉蘋 0952-060-901 | AD62: 591 物件頁 | AE62: 概略位置：591 11580037 物件頁地圖座標（門牌未揭露，591 標點可能為概略位置）（25.0641548, 121.5204928） | AF62: 開啟地圖
A63: 不符合 | B63: 62 | C63: W01 | D63: 敦南商圈（路名未揭露） | E63: 大安 | F63: 敦南商圈(路名未揭露) | G63: —/27F(B4) | H63: 204 | J63: 未揭露 | K63: 469000 | L63: 469,000（刊登價,稅別未標） | N63: =IF(K63="","",K63+N(M63)) -> 469000 | O63: =IF(OR(I63="",N63=""),"",N63/I63) | P63: =IF(I63="","未揭露",IF(I63>=0_條件與假設!$B$5,"✓","✗")) -> 未揭露 | Q63: =IF(K63="","未提供",IF(K63<=0_條件與假設!$B$6,"≤45萬",IF(K63<=0_條件與假設!$B$7,"45～55萬","超過55萬"))) -> 45～55萬 | R63: 未確認 | V63: =IF(U63="","未確認",IF(U63<=0_條件與假設!$B$8,"✓",IF(U63<=16,"△ 11～16分","✗"))) -> 未確認 | W63: 不符：權狀僅204坪（實坪必低於220） | Y63: 未檢視：本案不符合條件，本輪未逐張檢視廁所照片；如需要可補看。 | Z63: 33年 | AA63: 可承租 | AB63: HouseWeb | AC63: 滿意房屋 02-2713-5151 | AD63: HouseWeb·26張 | AE63: 無法定位：沒有門牌也沒有座標 | AF63: —
A64: 不符合 | B64: 63 | C64: N30 | D64: 敦化南路二段 15F（信義安和站） | E64: 大安 | F64: 敦化南路二段 | G64: 15F/27F | H64: 204 | J64: 591 22062144 刊登204坪，內文「廣告坪數為權狀坪數」 | K64: 469200 | L64: 469,200（591 22062144，稅別未寫） | N64: =IF(K64="","",K64+N(M64)) -> 469200 | O64: =IF(OR(I64="",N64=""),"",N64/I64) | P64: =IF(I64="","未揭露",IF(I64>=0_條件與假設!$B$5,"✓","✗")) -> 未揭露 | Q64: =IF(K64="","未提供",IF(K64<=0_條件與假設!$B$6,"≤45萬",IF(K64<=0_條件與假設!$B$7,"45～55萬","超過55萬"))) -> 45～55萬 | R64: 信義安和 | S64: 紅 | T64: 760 | U64: 13 | V64: =IF(U64="","未確認",IF(U64<=0_條件與假設!$B$8,"✓",IF(U64<=16,"△ 11～16分","✗"))) -> △ 11～16分 | W64: 不符：權狀僅204坪（實坪必低於220） | X64: 權狀僅204坪；租金稅別未寫；管理費未提供 | Y64: 廁所無照片：591 22062144 共 9 張為空室（木紋地板、開放式天花）＋茶水間（照片 9，新），沒有拍廁所。 | Z64: 未提供 | AA64: 未提供 | AB64: 591 22062144（易信 王先生） | AC64: 易信國際 王先生 0955-866-400 | AD64: 591 物件頁 | AE64: 概略位置：591 物件頁地圖座標（概略）（25.0277004, 121.5485169） | AF64: 開啟地圖
A65: 不符合 | B65: 64 | C65: N31 | D65: 健康路 8F（南京三民／小巨蛋站） | E65: 松山 | F65: 健康路 | G65: 8F/12F | H65: 195 | J65: 591 17979949 刊登「195坪」（未說明權狀或使用坪數；內文「使用坪數超值、超低公設」） | K65: 470925 | L65: 448,500 未稅（591 17979949 內文「此租金為未稅金額」，2,300元/坪）→ 含稅 470,925 | N65: =IF(K65="","",K65+N(M65)) -> 470925 | O65: =IF(OR(I65="",N65=""),"",N65/I65) | P65: =IF(I65="","未揭露",IF(I65>=0_條件與假設!$B$5,"✓","✗")) -> 未揭露 | Q65: =IF(K65="","未提供",IF(K65<=0_條件與假設!$B$6,"≤45萬",IF(K65<=0_條件與假設!$B$7,"45～55萬","超過55萬"))) -> 45～55萬 | R65: 台北小巨蛋 | S65: 綠 | T65: 180 | U65: 3 | V65: =IF(U65="","未確認",IF(U65<=0_條件與假設!$B$8,"✓",IF(U65<=16,"△ 11～16分","✗"))) -> ✓ | W65: 不符：591 刊登195坪（未說明權狀或使用坪數，任一種都低於220） | X65: 刊登195坪；坪數性質未說明；管理費未提供 | Y65: 廁所無照片：591 17979949 共 15 張為空室（高架地板、地毯已拆）＋茶水間（照片 15），沒有拍廁所；刊登設備寫「公共衛生間」；照片上傳於 2024/06。 | Z65: 未提供 | AA65: 平面式 | AB65: 591 17979949（尚揚 陳先生） | AC65: 尚揚 陳先生 0906-118-677 | AD65: 591 物件頁 | AE65: 概略位置：591 17979949 物件頁地圖座標（門牌未揭露，591 標點可能為概略位置）（25.0529935, 121.5528903） | AF65: 開啟地圖
A66: 不符合 | B66: 65 | C66: J13 | D66: 民生東路VS建國北路 2*F 225坪 | E66: 中山 | F66: 民生東路VS建國北路 | G66: 2*F | H66: 225 | J66: 未揭露 | K66: 472500 | L66: 472,500（未稅×1.05） | N66: =IF(K66="","",K66+N(M66)) -> 472500 | O66: =IF(OR(I66="",N66=""),"",N66/I66) | P66: =IF(I66="","未揭露",IF(I66>=0_條件與假設!$B$5,"✓","✗")) -> 未揭露 | Q66: =IF(K66="","未提供",IF(K66<=0_條件與假設!$B$6,"≤45萬",IF(K66<=0_條件與假設!$B$7,"45～55萬","超過55萬"))) -> 45～55萬 | R66: 松江南京 | S66: 綠 | T66: 780 | U66: 13 | V66: =IF(U66="","未確認",IF(U66<=0_條件與假設!$B$8,"✓",IF(U66<=16,"△ 11～16分","✗"))) -> △ 11～16分 | W66: 不符：權狀225坪，公設比需≤2.2%才達220（實坪未揭露） | Y66: 未檢視：本案不符合條件，本輪未逐張檢視廁所照片；如需要可補看。 | Z66: 缺 | AA66: 缺 | AB66: 傑森愛華 | AC66: 傑森愛華 張先生 0931-330823 | AD66: 傑森愛華原始PDF 第4頁（含照片） | AE66: 概略位置：民生東路×建國北路口（清單未給門牌）（25.0576372, 121.5376791） | AF66: 開啟地圖
A67: 不符合 | B67: 66 | C67: J04 | D67: 民生東路3段vs復興北路 11F 205坪 | E67: 松山 | F67: 民生東路3段vs復興北路 | G67: 11F | H67: 205 | J67: 未揭露 | K67: 486465 | L67: 486,465（未稅×1.05） | N67: =IF(K67="","",K67+N(M67)) -> 486465 | O67: =IF(OR(I67="",N67=""),"",N67/I67) | P67: =IF(I67="","未揭露",IF(I67>=0_條件與假設!$B$5,"✓","✗")) -> 未揭露 | Q67: =IF(K67="","未提供",IF(K67<=0_條件與假設!$B$6,"≤45萬",IF(K67<=0_條件與假設!$B$7,"45～55萬","超過55萬"))) -> 45～55萬 | R67: 南京復興 | S67: 綠 | T67: 620 | U67: 11 | V67: =IF(U67="","未確認",IF(U67<=0_條件與假設!$B$8,"✓",IF(U67<=16,"△ 11～16分","✗"))) -> △ 11～16分 | W67: 不符：權狀僅205坪（實坪必低於220） | Y67: 未檢視：本案不符合條件，本輪未逐張檢視廁所照片；如需要可補看。 | Z67: 缺 | AA67: 缺 | AB67: 傑森愛華 | AC67: 傑森愛華 張先生 0931-330823 | AD67: 傑森愛華原始PDF 第2頁（含照片） | AE67: 概略位置：民生東路三段×復興北路口（清單未給門牌）（25.0576954, 121.5440874） | AF67: 開啟地圖
A68: 不符合 | B68: 67 | C68: J05 | D68: 民生東路3段vs復興北路 3F 205坪 | E68: 松山 | F68: 民生東路3段vs復興北路 | G68: 3F | H68: 205 | J68: 未揭露 | K68: 486465 | L68: 486,465（未稅×1.05） | N68: =IF(K68="","",K68+N(M68)) -> 486465 | O68: =IF(OR(I68="",N68=""),"",N68/I68) | P68: =IF(I68="","未揭露",IF(I68>=0_條件與假設!$B$5,"✓","✗")) -> 未揭露 | Q68: =IF(K68="","未提供",IF(K68<=0_條件與假設!$B$6,"≤45萬",IF(K68<=0_條件與假設!$B$7,"45～55萬","超過55萬"))) -> 45～55萬 | R68: 南京復興 | S68: 綠 | T68: 620 | U68: 11 | V68: =IF(U68="","未確認",IF(U68<=0_條件與假設!$B$8,"✓",IF(U68<=16,"△ 11～16分","✗"))) -> △ 11～16分 | W68: 不符：權狀僅205坪（實坪必低於220） | Y68: 未檢視：本案不符合條件，本輪未逐張檢視廁所照片；如需要可補看。 | Z68: 缺 | AA68: 缺 | AB68: 傑森愛華 | AC68: 傑森愛華 張先生 0931-330823 | AD68: 傑森愛華原始PDF 第2頁（含照片） | AE68: 概略位置：民生東路三段×復興北路口（清單未給門牌）（25.0576954, 121.5440874） | AF68: 開啟地圖
A69: 不符合 | B69: 68 | C69: J03 | D69: 中山北路近市民大道 17F 204坪 | E69: 中山 | F69: 中山北路近市民大道 | G69: 17F | H69: 204 | J69: 未揭露 | K69: 490245 | L69: 490,245（未稅×1.05） | M69: 22330 | N69: =IF(K69="","",K69+N(M69)) -> 512575 | O69: =IF(OR(I69="",N69=""),"",N69/I69) | P69: =IF(I69="","未揭露",IF(I69>=0_條件與假設!$B$5,"✓","✗")) -> 未揭露 | Q69: =IF(K69="","未提供",IF(K69<=0_條件與假設!$B$6,"≤45萬",IF(K69<=0_條件與假設!$B$7,"45～55萬","超過55萬"))) -> 45～55萬 | R69: 台北車站 | S69: 紅藍 | T69: 390 | U69: 7 | V69: =IF(U69="","未確認",IF(U69<=0_條件與假設!$B$8,"✓",IF(U69<=16,"△ 11～16分","✗"))) -> ✓ | W69: 不符：權狀僅204坪（實坪必低於220） | Y69: 未檢視：本案不符合條件，本輪未逐張檢視廁所照片；如需要可補看。 | Z69: 29年 | AA69: 缺 | AB69: 傑森愛華 | AC69: 傑森愛華 張先生 0931-330823 | AD69: 傑森愛華原始PDF 第1頁（此列無照片）；同戶照片見W08 HouseWeb | AE69: 概略位置：中山北路一段×市民大道口（清單未給門牌）（25.0482394, 121.5206867） | AF69: 開啟地圖
A70: 不符合 | B70: 69 | C70: W08 | D70: 中山北路一段 17F | E70: 中山 | F70: 中山北路一段 | G70: 17F/18F(B4) | H70: 203 | J70: 未揭露 | K70: 490245 | L70: 490,245（未稅×1.05） | M70: 22330 | N70: =IF(K70="","",K70+N(M70)) -> 512575 | O70: =IF(OR(I70="",N70=""),"",N70/I70) | P70: =IF(I70="","未揭露",IF(I70>=0_條件與假設!$B$5,"✓","✗")) -> 未揭露 | Q70: =IF(K70="","未提供",IF(K70<=0_條件與假設!$B$6,"≤45萬",IF(K70<=0_條件與假設!$B$7,"45～55萬","超過55萬"))) -> 45～55萬 | R70: 台北車站 | S70: 紅藍 | T70: 390 | U70: 7 | V70: =IF(U70="","未確認",IF(U70<=0_條件與假設!$B$8,"✓",IF(U70<=16,"△ 11～16分","✗"))) -> ✓ | W70: 不符：權狀僅203坪（實坪必低於220） | Y70: 未檢視：本案不符合條件，本輪未逐張檢視廁所照片；如需要可補看。 | Z70: 29年 | AA70: 無車位 | AB70: HouseWeb | AC70: 松高房屋 洪小姐 0984-278-218 | AD70: HouseWeb·35張 | AE70: 概略位置：中山北路一段×市民大道口（HouseWeb未給門牌）（25.0482394, 121.5206867） | AF70: 開啟地圖
A71: 不符合 | B71: 70 | C71: J10 | D71: 安和路一段 (即安敦國際大樓17F) 17F 214坪 | E71: 大安 | F71: 安和路一段 (即安敦國際大樓17F) | G71: 17F | H71: 214 | J71: 未揭露 | K71: 494340 | L71: 494,340（未稅×1.05） | N71: =IF(K71="","",K71+N(M71)) -> 494340 | O71: =IF(OR(I71="",N71=""),"",N71/I71) | P71: =IF(I71="","未揭露",IF(I71>=0_條件與假設!$B$5,"✓","✗")) -> 未揭露 | Q71: =IF(K71="","未提供",IF(K71<=0_條件與假設!$B$6,"≤45萬",IF(K71<=0_條件與假設!$B$7,"45～55萬","超過55萬"))) -> 45～55萬 | R71: 忠孝敦化 | S71: 藍 | T71: 260 | U71: 5 | V71: =IF(U71="","未確認",IF(U71<=0_條件與假設!$B$8,"✓",IF(U71<=16,"△ 11～16分","✗"))) -> ✓ | W71: 不符：權狀僅214坪（實坪必低於220） | Y71: 未檢視：本案不符合條件，本輪未逐張檢視廁所照片；如需要可補看。 | Z71: 38年 | AA71: 缺 | AB71: 傑森愛華 | AC71: 傑森愛華 張先生 0931-330823 | AD71: 傑森愛華原始PDF 第3頁（含照片）；同戶另見信義CZ05290 | AE71: 物件頁座標：同安敦國際大樓(信義全球座標)（25.03901, 121.550592） | AF71: 開啟地圖
A72: 不符合 | B72: 71 | C72: N32 | D72: 南京東路三段 9F（南京復興站） | E72: 中山 | F72: 南京東路三段 | G72: 9F/14F | H72: 209.16 | J72: 591 21423260 刊登209.16坪，內文「權狀約209坪」 | K72: 501984 | L72: 501,984 含稅（591 21423260 內文「此租金為含稅金額」，2,400元/坪） | N72: =IF(K72="","",K72+N(M72)) -> 501984 | O72: =IF(OR(I72="",N72=""),"",N72/I72) | P72: =IF(I72="","未揭露",IF(I72>=0_條件與假設!$B$5,"✓","✗")) -> 未揭露 | Q72: =IF(K72="","未提供",IF(K72<=0_條件與假設!$B$6,"≤45萬",IF(K72<=0_條件與假設!$B$7,"45～55萬","超過55萬"))) -> 45～55萬 | R72: 南京復興 | S72: 綠 | T72: 175 | U72: 3 | V72: =IF(U72="","未確認",IF(U72<=0_條件與假設!$B$8,"✓",IF(U72<=16,"△ 11～16分","✗"))) -> ✓ | W72: 不符：權狀僅209.16坪（實坪必低於220） | X72: 權狀僅209坪；管理費未提供 | Y72: 廁所無照片：591 21423260 共 15 張為現況辦公室（目前有人使用：開放式天花、玻璃會議室、茶水間、哺乳室），沒有拍廁所；刊登設備寫「公共衛生間」。 | Z72: 未提供 | AA72: 未提供 | AB72: 591 21423260（尚揚 陳先生） | AC72: 尚揚 陳先生 0906-118-677 | AD72: 591 物件頁 | AE72: 概略位置：591 21423260 物件頁地圖座標（門牌未揭露，591 標點可能為概略位置）（25.0507974, 121.5430008） | AF72: 開啟地圖
A73: 不符合 | B73: 72 | C73: J08 | D73: 南京東路近龍江路 8F 210坪 | E73: 中山 | F73: 南京東路近龍江路 | G73: 8F | H73: 210 | J73: 未揭露 | K73: 507150 | L73: 507,150（未稅×1.05） | N73: =IF(K73="","",K73+N(M73)) -> 507150 | O73: =IF(OR(I73="",N73=""),"",N73/I73) | P73: =IF(I73="","未揭露",IF(I73>=0_條件與假設!$B$5,"✓","✗")) -> 未揭露 | Q73: =IF(K73="","未提供",IF(K73<=0_條件與假設!$B$6,"≤45萬",IF(K73<=0_條件與假設!$B$7,"45～55萬","超過55萬"))) -> 45～55萬 | R73: 南京復興 | S73: 綠 | T73: 320 | U73: 6 | V73: =IF(U73="","未確認",IF(U73<=0_條件與假設!$B$8,"✓",IF(U73<=16,"△ 11～16分","✗"))) -> ✓ | W73: 不符：權狀僅210坪（實坪必低於220） | Y73: 未檢視：本案不符合條件，本輪未逐張檢視廁所照片；如需要可補看。 | Z73: 缺 | AA73: 缺 | AB73: 傑森愛華 | AC73: 傑森愛華 張先生 0931-330823 | AD73: 傑森愛華原始PDF 第3頁（含照片） | AE73: 概略位置：南京東路×龍江路口（清單未給門牌）（25.051929, 121.540853） | AF73: 開啟地圖
A74: 不符合 | B74: 73 | C74: N29 | D74: 健康路 3F（台北小巨蛋站） | E74: 松山 | F74: 健康路 | G74: 3F/12F | H74: 221 | J74: 591 20903777 刊登221坪，內文「此顯示坪數皆為權狀登記坪數；此物件為分割案件」 | K74: 508300 | L74: 508,300（591 20903777，稅別未寫） | N74: =IF(K74="","",K74+N(M74)) -> 508300 | O74: =IF(OR(I74="",N74=""),"",N74/I74) | P74: =IF(I74="","未揭露",IF(I74>=0_條件與假設!$B$5,"✓","✗")) -> 未揭露 | Q74: =IF(K74="","未提供",IF(K74<=0_條件與假設!$B$6,"≤45萬",IF(K74<=0_條件與假設!$B$7,"45～55萬","超過55萬"))) -> 45～55萬 | R74: 台北小巨蛋 | S74: 綠 | T74: 94 | U74: 2 | V74: =IF(U74="","未確認",IF(U74<=0_條件與假設!$B$8,"✓",IF(U74<=16,"△ 11～16分","✗"))) -> ✓ | W74: 不符：權狀221坪，公設比需≤0.5%才達220（實坪未揭露） | X74: 權狀僅221坪；實坪未揭露；租金稅別未寫；管理費未提供 | Y74: 廁所無照片：591 20903777 共 4 張為空室（新木紋地板、新天花燈具），沒有拍廁所；刊登設備寫「獨立衛生間」。 | Z74: 未提供 | AA74: 平面式 | AB74: 591 20903777（經紀人 李炳興） | AC74: 591 刊登人（專案經理）0977-222-827 | AD74: 591 物件頁 | AE74: 概略位置：591 20903777 物件頁地圖座標（門牌未揭露，591 標點可能為概略位置）（25.0512031, 121.5510999） | AF74: 開啟地圖
A75: 不符合 | B75: 74 | C75: N23 | D75: 民權東路三段 9F | E75: 中山 | F75: 民權東路三段 | G75: 9F/16F | H75: 306.48 | J75: 591 只寫使用坪數306.48 | K75: 509100 | L75: 484,857 未稅（591 21587259）→ 含稅 509,100 | N75: =IF(K75="","",K75+N(M75)) -> 509100 | O75: =IF(OR(I75="",N75=""),"",N75/I75) | P75: =IF(I75="","未揭露",IF(I75>=0_條件與假設!$B$5,"✓","✗")) -> 未揭露 | Q75: =IF(K75="","未提供",IF(K75<=0_條件與假設!$B$6,"≤45萬",IF(K75<=0_條件與假設!$B$7,"45～55萬","超過55萬"))) -> 45～55萬 | R75: 中山國中(棕) 138m | V75: =IF(U75="","未確認",IF(U75<=0_條件與假設!$B$8,"✓",IF(U75<=16,"△ 11～16分","✗"))) -> 未確認 | W75: 不符：附近只有棕線（中山國中138m），綠紅藍線未確認 | X75: 實坪未揭露 | Y75: 未檢視：本案不符合條件，本輪未逐張檢視廁所照片；如需要可補看。 | Z75: 未提供 | AA75: 未提供 | AB75: 591 21587259（兆淇 童先生）、21921504、21983146、22062115 | AC75: 兆淇 童先生 0972-080-924 | AD75: 591 物件頁 | AE75: 無法定位：沒有門牌也沒有座標 | AF75: —
A76: 不符合 | B76: 75 | C76: J14 | D76: 民生東路近敦化北路 8F 226坪 | E76: 松山 | F76: 民生東路近敦化北路 | G76: 8F | H76: 226 | J76: 未揭露 | K76: 522375 | L76: 522,375（未稅×1.05） | N76: =IF(K76="","",K76+N(M76)) -> 522375 | O76: =IF(OR(I76="",N76=""),"",N76/I76) | P76: =IF(I76="","未揭露",IF(I76>=0_條件與假設!$B$5,"✓","✗")) -> 未揭露 | Q76: =IF(K76="","未提供",IF(K76<=0_條件與假設!$B$6,"≤45萬",IF(K76<=0_條件與假設!$B$7,"45～55萬","超過55萬"))) -> 45～55萬 | R76: 台北小巨蛋 | S76: 綠 | T76: 760 | U76: 13 | V76: =IF(U76="","未確認",IF(U76<=0_條件與假設!$B$8,"✓",IF(U76<=16,"△ 11～16分","✗"))) -> △ 11～16分 | W76: 不符：權狀226坪，公設比需≤2.7%才達220（實坪未揭露） | Y76: 未檢視：本案不符合條件，本輪未逐張檢視廁所照片；如需要可補看。 | Z76: 缺 | AA76: 缺 | AB76: 傑森愛華 | AC76: 傑森愛華 張先生 0931-330823 | AD76: 傑森愛華原始PDF 第4頁（含照片） | AE76: 概略位置：民生東路×敦化北路口（清單未給門牌）（25.058038, 121.549018） | AF76: 開啟地圖
A77: 不符合 | B77: 76 | C77: N16 | D77: 環亞大樓 11F（南京東路三段） | E77: 松山 | F77: 南京東路（環亞樓上） | G77: 11F | H77: 262 | J77: 清單只有坪數262 | K77: 550200 | L77: 524,000 未稅（@2,000）→ 含稅 550,200 | N77: =IF(K77="","",K77+N(M77)) -> 550200 | O77: =IF(OR(I77="",N77=""),"",N77/I77) | P77: =IF(I77="","未揭露",IF(I77>=0_條件與假設!$B$5,"✓","✗")) -> 未揭露 | Q77: =IF(K77="","未提供",IF(K77<=0_條件與假設!$B$6,"≤45萬",IF(K77<=0_條件與假設!$B$7,"45～55萬","超過55萬"))) -> 超過55萬 | R77: 台北小巨蛋 | S77: 綠 | V77: =IF(U77="","未確認",IF(U77<=0_條件與假設!$B$8,"✓",IF(U77<=16,"△ 11～16分","✗"))) -> 未確認 | W77: 不符：月租550,200超過55萬 | X77: 實坪未揭露；大樓名稱為推定 | Y77: 廁所無照片：傑森愛華清單 3 張（毛胚室內、窗景），沒有拍廁所。 | Z77: 好房網：1983/10竣工 | AA77: 未提供 | AB77: 傑森愛華 2026/9/23清單第1頁 | AC77: 傑森愛華 張先生 0931-330823 | AD77: 傑森愛華清單 第1頁 | AE77: 無法定位：沒有門牌也沒有座標 | AF77: —
A78: 不符合 | B78: 77 | C78: S13 | D78: 環球世貿 10F | E78: 信義 | F78: 信義路五段(環球世貿) | G78: 10F/22F | H78: 266.36 | J78: 未揭露 | K78: 560000 | L78: 560,000（含稅） | N78: =IF(K78="","",K78+N(M78)) -> 560000 | O78: =IF(OR(I78="",N78=""),"",N78/I78) | P78: =IF(I78="","未揭露",IF(I78>=0_條件與假設!$B$5,"✓","✗")) -> 未揭露 | Q78: =IF(K78="","未提供",IF(K78<=0_條件與假設!$B$6,"≤45萬",IF(K78<=0_條件與假設!$B$7,"45～55萬","超過55萬"))) -> 超過55萬 | R78: 象山 | S78: 紅 | T78: 510 | U78: 9 | V78: =IF(U78="","未確認",IF(U78<=0_條件與假設!$B$8,"✓",IF(U78<=16,"△ 11～16分","✗"))) -> ✓ | W78: 不符：月租560,000超過55萬 | Y78: 未檢視：本案不符合條件，本輪未逐張檢視廁所照片；如需要可補看。 | Z78: 缺 | AA78: 未標示 | AB78: 信義房屋 | AC78: 信義房屋 忠孝玉成店 林雍勝 0915-969-937 | AD78: 信義 本戶（C360646） | AE78: 物件頁座標：信義全球物件座標（25.028332, 121.571059） | AF78: 開啟地圖
A79: 不符合 | B79: 78 | C79: N33 | D79: 菸廠路 8F（國父紀念館站・松菸旁） | E79: 信義 | F79: 菸廠路 | G79: 8F/14F | H79: 196 | J79: 591 22162790 刊登196坪（內文「刊登坪數、權狀面積依地政機關登記為準」） | K79: 578621 | L79: 551,068 未稅（591 22162790 內文「此租金未含加值型營業稅5%」）→ 含稅 578,621 | N79: =IF(K79="","",K79+N(M79)) -> 578621 | O79: =IF(OR(I79="",N79=""),"",N79/I79) | P79: =IF(I79="","未揭露",IF(I79>=0_條件與假設!$B$5,"✓","✗")) -> 未揭露 | Q79: =IF(K79="","未提供",IF(K79<=0_條件與假設!$B$6,"≤45萬",IF(K79<=0_條件與假設!$B$7,"45～55萬","超過55萬"))) -> 超過55萬 | R79: 國父紀念館 | S79: 藍 | T79: 274 | U79: 5 | V79: =IF(U79="","未確認",IF(U79<=0_條件與假設!$B$8,"✓",IF(U79<=16,"△ 11～16分","✗"))) -> ✓ | W79: 不符：權狀僅196坪（實坪必低於220）；月租578,621超過55萬 | X79: 刊登僅196坪；含稅超過55萬；管理費未提供 | Y79: 廁所無照片：591 22162790 共 7 張為空室（地毯舊、有磨損，面松菸／大巨蛋），沒有拍廁所。 | Z79: 未提供 | AA79: 未提供 | AB79: 591 22162790（東家國際 蔡泳翰） | AC79: 東家國際 蔡泳翰 0912-816-677 | AD79: 591 物件頁 | AE79: 概略位置：591 22162790 物件頁地圖座標（門牌未揭露，591 標點可能為概略位置）（25.0410109, 121.5602062） | AF79: 開啟地圖
A80: 不符合 | B80: 79 | C80: J17 | D80: 市民大道3段近復興南路 8F 257坪 | E80: 大安 | F80: 市民大道3段近復興南路 | G80: 8F | H80: 257 | J80: 591 21593285 原文「權狀約256.77坪、使用約171坪」（同棟8F，仲介口述） | K80: 588000 | L80: 588,000（未稅×1.05） | N80: =IF(K80="","",K80+N(M80)) -> 588000 | O80: =IF(OR(I80="",N80=""),"",N80/I80) | P80: =IF(I80="","未揭露",IF(I80>=0_條件與假設!$B$5,"✓","✗")) -> 未揭露 | Q80: =IF(K80="","未提供",IF(K80<=0_條件與假設!$B$6,"≤45萬",IF(K80<=0_條件與假設!$B$7,"45～55萬","超過55萬"))) -> 超過55萬 | R80: 忠孝復興 | S80: 藍 | T80: 370 | U80: 7 | V80: =IF(U80="","未確認",IF(U80<=0_條件與假設!$B$8,"✓",IF(U80<=16,"△ 11～16分","✗"))) -> ✓ | W80: 不符：月租588,000超過55萬 | X80: 591 533,333 稅別未寫（若含稅則≤55萬，需確認）；同棟仲介口述使用約171坪 | Y80: 廁所無照片：591 22061936 共 3 張（接待櫃台、會客區、會議室，高檔裝潢），沒有拍廁所。 | Z80: 缺 | AA80: 缺 | AB80: 傑森愛華；591 22061936（易信 王先生 0955-866-400） | AC80: 傑森愛華 張先生 0931-330823 | AD80: 傑森愛華原始PDF 第5頁（此列無照片） | AE80: 概略位置：市民大道三段×復興南路口（清單未給門牌）（25.044961, 121.54338） | AF80: 開啟地圖
A81: 不符合 | B81: 80 | C81: N28 | D81: 民生東路三段 8F（中山國中站） | E81: 中山 | F81: 民生東路三段 | G81: 8F/16F | H81: 254.53 | J81: 591 22129776 刊登「254.53坪」（未說明是否權狀，無主建物／附屬分項；內文「一層二戶低公設、使用坪數大」） | K81: 614678 | L81: 585,408 未稅（591 22129776 內文「租金為未稅金額」）→ 含稅 614,678 | N81: =IF(K81="","",K81+N(M81)) -> 614678 | O81: =IF(OR(I81="",N81=""),"",N81/I81) | P81: =IF(I81="","未揭露",IF(I81>=0_條件與假設!$B$5,"✓","✗")) -> 未揭露 | Q81: =IF(K81="","未提供",IF(K81<=0_條件與假設!$B$6,"≤45萬",IF(K81<=0_條件與假設!$B$7,"45～55萬","超過55萬"))) -> 超過55萬 | R81: 南京復興 | S81: 綠 | T81: 1070 | U81: 18 | V81: =IF(U81="","未確認",IF(U81<=0_條件與假設!$B$8,"✓",IF(U81<=16,"△ 11～16分","✗"))) -> ✗ | W81: 不符：月租614,678超過55萬；捷運南京復興(綠) 18分太遠 | X81: 含稅超過55萬；實坪未揭露；管理費未提供；綠紅藍捷運步行約18分（概略） | Y81: 廁所無照片：591 22129776 共 12 張皆為辦公區（現成新式裝潢、目前有人使用：會議室、茶水吧、置物櫃），沒有拍廁所。 | Z81: 未提供 | AA81: 平面式 | AB81: 591 22129776（同陽商仲 房先生） | AC81: 同陽商仲 房先生 0978-751-212 | AD81: 591 物件頁 | AE81: 概略位置：591 物件頁地圖座標（概略）（25.0616853, 121.5451777） | AF81: 開啟地圖

Sheet B_優先案詳情
A1: 欄位 | B1: S05 | C1: N04 | D1: C | E1: N02 | F1: S12 | G1: N01 | H1: N05 | I1: N08 | J1: S11 | K1: N10 | L1: N11 | M1: J18 | N1: N07 | O1: N14 | P1: N06 | Q1: N15 | R1: S06 | S1: N09 | T1: N27
A2: 分級 | B2: 第一優先 | C2: 第二優先 | D2: 第二優先 | E2: 第二優先 | F2: 第二優先 | G2: 第二優先 | H2: 待確認實坪 | I2: 待確認實坪 | J2: 待確認實坪 | K2: 待確認實坪 | L2: 待確認實坪 | M2: 待確認實坪 | N2: 待確認實坪 | O2: 待確認實坪 | P2: 待確認實坪 | Q2: 待確認實坪 | R2: 待確認實坪 | S2: 待確認實坪 | T2: 待確認實坪
A3: 案號 | B3: S05 | C3: N04 | D3: C | E3: N02 | F3: S12 | G3: N01 | H3: N05 | I3: N08 | J3: S11 | K3: N10 | L3: N11 | M3: J18 | N3: N07 | O3: N14 | P3: N06 | Q3: N15 | R3: S06 | S3: N09 | T3: N27
A4: 案名 | B4: 建國北路二段 10F（大辦公室＋大倉儲） | C4: 信義大樓 10F | D4: 旭寶大樓 5F | E4: 廣成大廈 4F | F4: 全球人壽信義大樓 21F | G4: 南海開發大樓 5F | H4: 信義大樓 8F | I4: 松江路 3F（松江南京站） | J4: 八德大樓 5F（出租285.67坪） | K4: 光復北路11巷 2F（南京三民站） | L4: 旭寶大樓 4F | M4: 忠孝東路四段×延吉街 4F | N4: 忠孝東路一段 11F（台北車站） | O4: 中山北路三段 6F（民權西路站） | P4: 忠孝東路一段 2F（善導寺站） | Q4: 民生東路二段 6F（仲介稱使用約226坪） | R4: 八德大樓 7F（出租254.06坪） | S4: 長春路 8F（松江南京站） | T4: 南京東路五段 3F（南京三民站）
A5: 大樓 | B5: （大樓名未揭露） | C5: 全球人壽信義大樓（信義大樓） | D5: 旭寶大樓 | E5: 廣成大廈 | F5: 全球人壽信義大樓（信義大樓） | G5: 南海開發大樓 | H5: 全球人壽信義大樓（信義大樓）（推定） | I5: （大樓名未揭露） | J5: 八德大樓（591 匯幸稱） | K5: 推定：光復北路11巷35號（台北瓦斯「光復大樓」） | L5: 旭寶大樓 | M5: 推定：太平洋商業大樓（忠孝東路四段285號） | N5: （大樓名未揭露） | O5: （未揭露；同路段 6F/14F 另有「新設工大樓」刊登） | P5: （大樓名未揭露；另一刊登稱「凱撒世貿中心」） | Q5: （大樓名未揭露） | R5: 八德大樓（591 匯幸稱） | S5: （大樓名未揭露） | T5: （大樓名未揭露）
A6: 行政區 | B6: 中山 | C6: 信義 | D6: 松山 | E6: 中正 | F6: 信義 | G6: 中正 | H6: 信義 | I6: 中山 | J6: 中山 | K6: 松山 | L6: 松山 | M6: 大安 | N6: 中正 | O6: 中山 | P6: 中正 | Q6: 中山 | R6: 中山 | S6: 中山 | T6: 松山
A7: 地址 | B7: 建國北路二段 | C7: 松仁路（信義大樓） | D7: 敦化南路一段25號 | E7: 延平南路189號4樓～之5 | F7: 松仁路277號21樓 | G7: 南海路20號5樓 | H7: 松仁路（信義區） | I7: 松江路 | J7: 八德路二段 | K7: 光復北路11巷 | L7: 敦化南路一段25號 | M7: 忠孝東路4段VS延吉街 | N7: 忠孝東路一段 | O7: 中山北路三段 | P7: 忠孝東路一段 | Q7: 民生東路二段 | R7: 八德路二段 | S7: 長春路 | T7: 南京東路五段
A8: 樓層 | B8: 10F/12F | C8: 10F/23F | D8: 5F/12F(B2) | E8: 4F/7F(B2) | F8: 21F/23F(B4) | G8: 5F/10F(B1) | H8: 8F | I8: 3F/12F | J8: 5F/12F | K8: 2F/14F | L8: 4F/12F | M8: 4F | N8: 11F/12F | O8: 6F/14F | P8: 2F/21F | Q8: 6F/12F | R8: 7F/12F | S8: 8F/12F | T8: 3F/16F
A9: 權狀坪 | B9: 278.04 | C9: 330.22 | D9: 282.06 | E9: 326.85 | F9: 265.82 | G9: 260.98 | H9: 331 | I9: 302 | J9: 285.67 | K9: 283 | L9: 282.06 | M9: 276 | N9: 266.78 | O9: 265.93 | P9: 261.4 | Q9: 255.18 | R9: 254.06 | S9: 253 | T9: 243
A10: 實坪(主+附) | B10: 262.5 | C10: 300.43 | D10: 255.38 | E10: 253.54 | F10: 241.8 | G10: 228.34 | H10: 未揭露 | I10: 未揭露 | J10: 未揭露 | K10: 未揭露 | L10: 未揭露 | M10: 未揭露 | N10: 未揭露 | O10: 未揭露 | P10: 未揭露 | Q10: 未揭露 | R10: 未揭露 | S10: 未揭露 | T10: 未揭露
A11: 實坪來源 | B11: 信義房屋物件頁：主建物246.00＋附屬16.50（共有15.54） | C11: 同一戶信義房屋 C904200：主254.24＋附46.19（591 刊登「300坪」與此相符） | D11: 尚揚物調表：實用坪255.38 | E11: 尚揚物調表：主建物＋附屬建物253.54 | F11: 尚揚物調表：主建物＋附屬241.8；信義房屋 C904707：主204.94＋附36.86＝241.80 | G11: 尚揚物調表：主建物＋附屬建物228.34 | H11: 8F 本身未揭露；同棟5F/9F 實坪300.54／300.44（信義房屋） | I11: 591 原文「刊登坪數、權狀面積依地政機關登記為準」 | J11: 信義 CZ05585：整筆權狀577.14、主322.97＋附38.67（整筆），出租285.67坪部分的實坪未寫 | K11: 591 原文「廣告坪數為權狀坪數」 | L11: 591 原文「廣告顯示使用面積為含公設面積」；同棟5F 實用255.38（尚揚） | M11: 清單只有坪數276（未說明權狀或實坪） | N11: 591 原文「權狀約266.78坪、低公設比」 | O11: 591 只寫「使用坪數265.93」，無分項 | P11: 591 原文「權狀約261.4坪（室內實際使用坪數以現場丈量或地政謄本為準）」 | Q11: 591 21985150 標題「使用約226坪」（仲介口述，無謄本分項）；21595066 寫255.18坪 | R11: 信義 CZ05587：整筆權狀786.72、主322.97＋附12.15（整筆，數字異常），出租部分實坪未寫 | S11: 591 只寫「使用坪數253坪」，無分項 | T11: 591 原文「廣告坪數為權狀坪數」；公設比需≤9.5%才可能達220
A12: 公設比 | B12: 5.6% | C12: 9.0% | D12: 9.46% | E12: 22.43% | F12: 9.04% | G12: 12.51% | H12: 未揭露 | I12: 未揭露 | J12: 未揭露 | K12: 未揭露 | L12: 未揭露 | M12: 未揭露 | N12: 未揭露 | O12: 未揭露 | P12: 未揭露 | Q12: 未揭露 | R12: 未揭露 | S12: 未揭露 | T12: 未揭露
A13: 月租(含稅) | B13: 388500 | C13: 480000 | D13: 472500 | E13: 491000 | F13: 502400 | G13: 465849 | H13: 538703 | I13: 540837 | J13: 428505 | K13: 534870 | L13: 532980 | M13: 504000 | N13: 533500 | O13: 385599 | P13: 421872 | Q13: 507565 | R13: 381090 | S13: 480035 | T13: 534754
A14: 租金原文 | B14: 388,500（信義房屋刊登） | C14: 480,000（591 21537848，稅別未寫）；同戶信義房屋刊登577,885 | D14: 472,500 含稅（尚揚物調表）；591 21530071 刊登450,000（=未稅，×1.05即472,500） | E14: 491,000（尚揚物調表標示「含稅」；傑森愛華清單同價但標「未稅」；591 21779044 標491,000含管理費；591 20971276 標491,000、管理費另計31,053） | F14: 502,400 含稅（尚揚物調表）；信義房屋刊登544,931 | G14: 465,849 含稅（尚揚物調表）；591 22010357 刊登443,666（×1.05=465,849，即未稅價）；傑森愛華清單 443,000 未稅 | H14: 513,050 未稅（@1,550）→ 含稅 538,703 | I14: 515,083 未含營業稅（591 21635155）→ 含稅 540,837 | J14: 428,505（信義刊登）；591 21804249 285坪 427,500（1,500/坪） | K14: 509,400 未稅（591 22062249、傑森愛華清單第2頁）→ 含稅 534,870 | L14: 507,600 未稅（傑森愛華清單第2頁）；591 21788157 507,708 未含稅 → 含稅約533,000 | M14: 480,000 未稅（@1,739）→ 含稅 504,000（傑森愛華 9/22 與 9/23 兩份清單同價） | N14: 533,500 含稅（591 19506910） | O14: 385,599（591 22010409，含車位、含管理費，稅別未寫） | P14: 421,872（591 20214332 等7筆同價，稅別未寫）；另有 480,000（住商南門 21553405／21867832） | Q14: 483,395 未含稅（591 21595066）→ 含稅 507,565 | R14: 381,090（信義刊登）；591 22053377 254坪 381,000 | S14: 480,035（591 22061922，稅別未寫） | T14: 534,754（591 22061968，稅別未寫；若為未稅，含稅561,492將超過上限）
A15: 稅別 | B15: 頁面未寫含稅或未稅 | C15: 未寫（若為未稅，含稅為504,000） | D15: 含稅 | E15: 含稅（物調表）— 三個來源不一致 | F15: 含稅 | G15: 含稅 | H15: 未稅×1.05 | I15: 未稅×1.05 | J15: 頁面未寫 | K15: 未稅×1.05 | L15: 未稅×1.05 | M15: 未稅×1.05 | N15: 含稅 | O15: 未寫 | P15: 未寫（若為未稅，含稅為442,966） | Q15: 未稅×1.05 | R15: 頁面未寫 | S15: 未寫（若為未稅，含稅為504,037） | T15: 未寫
A16: 管理費 | B16: 約37,500（不含於租金） | C16: 約49,533（信義頁） | D16: 33,847 | E16: 31,053 | F16: 39,873（150元/坪） | G16: 實支實付（物調表：約2.5萬～3萬） | H16: 未提供（同棟約49,500） | I16: 未提供 | J16: 約47,136 | K16: 未提供 | L16: 未提供 | M16: 未提供 | N16: 未提供 | O16: 591：租金已含管理費 | P16: 未提供 | Q16: 未提供 | R16: 約41,920 | S16: 未提供 | T16: 未提供
A17: 車位 | B17: 無；平面車位可另租5,000 | C17: 591：平面式 | D17: 機械車位×6（租金內含） | E17: 固定車位7,000(含稅)／非固定5,000(含稅) | F17: 物調表未載；信義頁：無 | G17: 附坡平車位2個（591：含車位） | H17: 未提供 | I17: 未提供 | J17: 無 | K17: 未提供（傑森愛華：停車方便） | L17: 未提供 | M17: 未提供 | N17: 未提供 | O17: 含車位 | P17: 平面式 | Q17: 平面式 | R17: 無 | S17: 未提供 | T17: 未提供
A18: 押金 | B18: 2個月 | C18: — | D18: 2個月 | E18: 3個月 | F18: 3個月 | G18: 2個月 | H18: 3個月 | I18: 面議 | J18: — | K18: 3個月 | L18: 3個月 | M18: 3個月 | N18: 面議 | O18: — | P18: — | Q18: 面議 | R18: 3個月 | S18: 面議 | T18: 面議
A19: 租期 | B19: 最短2年 | C19: 591：兩年 | D19: 只能租4年（之後都更；使用者 2026-09-24 告知）；物調表寫3年 | E19: 2年 | F19: 2年（信義頁：1年） | G19: 2年 | H19: 未提供 | I19: 一年 | J19: — | K19: 3年 | L19: 最多3年約（都更） | M19: 未提供 | N19: 兩年 | O19: 兩年 | P19: 兩年 | Q19: 兩年～3年 | R19: 3年 | S19: 兩年 | T19: 兩年
A20: 屋齡／竣工 | B20: 屋齡41.7年 | C20: 屋齡約29年 | D20: 屋齡約43年（1983/12竣工，好房網） | E20: 民國70/1/5竣工（屋齡約45年） | F20: 民國86/5/25竣工（屋齡約29年） | G20: 民國77/9/22竣工（屋齡約38年） | H20: 屋齡約29年 | I20: 未提供 | J20: 屋齡30.1年 | K20: 未提供 | L20: 屋齡約43年 | M20: 推定大樓1982/08竣工（好房網） | N20: 未提供 | O20: 未提供 | P20: 未提供 | Q20: 未提供 | R20: 屋齡30.1年 | S20: 未提供 | T20: 未提供
A21: 最近綠紅藍站 | B21: 松江南京（綠）530m·約9分 | C21: 象山（紅）950m·約16分 | D21: 忠孝敦化（藍）570m·約10分 | E21: 小南門（綠）380m·約7分 | F21: 象山（紅）950m·約16分 | G21: 中正紀念堂（紅綠）150m·約3分 | H21: 象山（紅）950m·約16分 | I21: 松江南京（綠）156m·約3分 | J21: 忠孝復興（藍）620m·約11分 | K21: 南京三民（綠）88m·約2分 | L21: 忠孝敦化（藍）570m·約10分 | M21: 國父紀念館（藍）300m·約5分 | N21: 台北車站（紅藍）171m·約3分 | O21: 民權西路（紅）170m·約3分 | P21: 善導寺（藍）119m·約2分 | Q21: 行天宮(橘) 188m | R21: 忠孝復興（藍）620m·約11分 | S21: 松江南京（綠）310m·約6分 | T21: 南京三民（綠）48m·約1分
A22: 距離依據 | B22: 信義全球物件座標 | C22: 同信義大樓座標 | D22: Google地圖：敦化南路一段25號 | E22: Google地圖：延平南路189號 | F22: 信義全球物件座標 | G22: Google地圖：南海路20號 | H22: 同信義大樓座標 | I22: 591 物件頁寫明 | J22: 信義全球物件座標 | K22: 591 物件頁寫明 | L22: 同旭寶大樓座標 | M22: 忠孝東路四段×延吉街口（清單未給門牌） | N22: 591 物件頁寫明 | O22: 591 物件頁寫明 | P22: 591 物件頁寫明 | Q22: 591 只寫橘線行天宮站153～188m；綠紅藍線最近站距離未確認 | R22: 信義全球物件座標 | S22: 591 物件頁寫明 | T22: 591 物件頁寫明
A23: 判定 | B23: 四項全符合：實坪262.5 · 月租38.9萬 · 松江南京(綠) 9分 | C23: 坪數符合；實坪300.43 · 月租48.0萬（45～55萬） · 捷運象山(紅) 16分（>10分） | D23: 坪數符合；實坪255.38 · 月租47.2萬（45～55萬） · 忠孝敦化(藍) 10分 | E23: 坪數符合；實坪253.54 · 月租49.1萬（45～55萬） · 小南門(綠) 7分 | F23: 坪數符合；實坪241.8 · 月租50.2萬（45～55萬） · 捷運象山(紅) 16分（>10分） | G23: 坪數符合；實坪228.34 · 月租46.6萬（45～55萬） · 中正紀念堂(紅綠) 3分 | H23: 待確認：實坪未揭露（權狀331坪） · 捷運象山(紅) 16分（>10分）；已符合：月租53.9萬（45～55萬） | I23: 待確認：實坪未揭露（權狀302坪）；已符合：月租54.1萬（45～55萬） · 松江南京(綠) 3分 | J23: 待確認：實坪未揭露（權狀285.67坪） · 捷運忠孝復興(藍) 11分（>10分）；已符合：月租42.9萬 | K23: 待確認：實坪未揭露（權狀283坪）；已符合：月租53.5萬（45～55萬） · 南京三民(綠) 2分 | L23: 待確認：實坪未揭露（權狀282.06坪）；已符合：月租53.3萬（45～55萬） · 忠孝敦化(藍) 10分 | M23: 待確認：實坪未揭露（權狀276坪）；已符合：月租50.4萬（45～55萬） · 國父紀念館(藍) 5分 | N23: 待確認：實坪未揭露（權狀266.78坪）；已符合：月租53.4萬（45～55萬） · 台北車站(紅藍) 3分 | O23: 待確認：實坪未揭露（權狀265.93坪）；已符合：月租38.6萬 · 民權西路(紅) 3分 | P23: 待確認：實坪未揭露（權狀261.4坪）；已符合：月租42.2萬 · 善導寺(藍) 2分 | Q23: 待確認：實坪未揭露（權狀255.18坪） · 綠紅藍捷運距離未確認（最近 行天宮(橘) 188m）；已符合：月租50.8萬（45～55萬） | R23: 待確認：實坪未揭露（權狀254.06坪） · 捷運忠孝復興(藍) 11分（>10分）；已符合：月租38.1萬 | S23: 待確認：實坪未揭露（權狀253坪）；已符合：月租48.0萬（45～55萬） · 松江南京(綠) 6分 | T23: 待確認：實坪未揭露（權狀243坪）；已符合：月租53.5萬（45～55萬） · 南京三民(綠) 1分
A24: 缺漏 | B24: 租金稅別未寫；廁所老舊需整修 | C24: 591 48萬刊登已下架（9/30），現存刊登為信義 577,885（超過55萬）；租金稅別未寫；兩方報價不同 | D24: 只能租4年（之後都更）；廁所老舊需整修 | E24: 租金是否含稅、是否含管理費：物調表／傑森愛華／591 三方說法不同，需書面確認；廁所需現勘 | F24: 未揭露 | G24: 管理費只有區間（2.5萬～3萬），無確切金額；廁所需現勘 | H24: 實坪未揭露；管理費未提供；廁所需現勘 | I24: 實坪未揭露；管理費未提供；廁所需現勘 | J24: 出租部分實坪未揭露；稅別未寫 | K24: 實坪未揭露；大樓名稱為推定；管理費未提供；廁所需現勘 | L24: 實坪未揭露；管理費未提供；廁所需現勘 | M24: 實坪未揭露；門牌與大樓名稱為推定；管理費未提供；廁所需現勘 | N24: 591 刊登已下架（9/24 查），需確認是否仍可租；實坪未揭露；管理費未提供；廁所需現勘 | O24: 實坪未揭露；稅別未寫；大樓名稱未揭露；廁所需現勘 | P24: 實坪未揭露；租金稅別未寫；兩種報價（42.2萬／48萬）；廁所需現勘 | Q24: 實坪只有仲介口述；綠紅藍捷運距離未確認（概略座標推算松江南京約780m）；稅別依據（591 21595066「未含稅」）已下架，現存刊登未寫稅別 | R24: 出租部分實坪未揭露；稅別未寫 | S24: 實坪未揭露；租金稅別未寫；管理費未提供；廁所需現勘 | T24: 實坪未揭露；稅別未寫（未稅則超過55萬）；廁所需現勘
A25: 屋況／廁所（照片判讀） | B25: 廁所老舊：廁所為舊式裝修（信義房屋物件照片 M、N）：立柱式洗手台、舊式隔間、天花板老式排風扇與日光燈格柵；辦公區地毯有污漬、部分天花板板材已拆（照片 C、D、G）；電梯廳已翻新（照片 K、L）；茶水間小（照片 I、J）。建議把廁所整修列入議價，或要求房東交屋前整修。 | C25: 廁所新：廁所為新裝修（信義房屋 C904200 照片 C：檯面式洗手台、木紋隔間）；辦公區天花為開放式未封板。 | D25: 廁所老舊：廁所為舊式裝修（591 21530071 照片 9、10）：藍色磁磚地坪、藍色立柱式洗手台、舊式小便斗與隔間、舊天花板；茶水間為木紋新作（照片 11）。建議把廁所整修列入議價。 | E25: 廁所無照片：尚揚照片、591 21779044（3 張：大廳、空室）、傑森愛華清單照片都沒有拍廁所；辦公區為開放空間、水泥地坪需整理。需現勘。 | F25: 廁所新：廁所、茶水間為新裝修（尚揚照片：石材牆面、木紋隔間、檯面式洗手台）；地毯、天花完整。 | G25: 廁所無照片：尚揚照片與 591 22010357（僅 1 張外觀）都沒有拍廁所；辦公區為亮面地坪、天花完整。需現勘。 | H25: 8F未拍廁所：8F 本身沒有室內照片（傑森愛華 3 張皆外觀）；同棟 10F、21F 廁所為新裝修，8F 需現勘確認。 | I25: 廁所無照片：591 只有 1 張照片（捷運出口），室內與廁所都沒有拍。需現勘。 | J25: 廁所新：廁所新裝修（信義 CZ05585 照片 D、G：石材檯面、新式小便斗、木紋隔間）；茶水間新（照片 J）；電梯廳石材。 | K25: 廁所無照片：591 只有 2 張（空室、捷運站），沒有拍廁所。需現勘。 | L25: 廁所無照片：591 21788157 共 10 張皆為辦公區（地毯磨損、有接待櫃台），沒有拍廁所；同棟 5F 廁所老舊，4F 很可能相同，需現勘。 | M25: 廁所無照片：傑森愛華清單 3 張（外觀、毛胚室內、窗景），沒有拍廁所。需現勘。 | N25: 廁所無照片：591 19506910 共 10 張皆為空辦公區（部分天花板板材缺、地面有污漬），沒有拍廁所。需現勘。 | O25: 廁所無照片：591 只有 1 張照片（捷運站），室內與廁所都沒有拍。需現勘。 | P25: 廁所無照片：591 20214332 共 14 張：辦公區、吧檯茶水區、戶外露台，沒有拍廁所。需現勘。 | Q25: 廁所新：廁所為新裝修（591 21985150 照片 8、9：深色石材牆面、檯面式洗手台、新式小便斗）；辦公區天花有部分線材外露待整理；同戶 591 21812612 內文寫「廁所設於室內」。 | R25: 廁所新：與 S11 同棟同規格：廁所新裝修（信義 CZ05587 照片 H）、茶水間新（照片 G）。 | S25: 廁所無照片：591 共 4 張皆為辦公區（開放式天花、地毯），沒有拍廁所。需現勘。 | T25: 廁所無照片：591 共 4 張（辦公區、外觀），沒有拍廁所。需現勘。
... A30: 連結 | B30: 信義全球物件頁（16張照片） | C30: 信義全球 10F（面積分項） | D30: 大樓照片（好房網19張） | E30: 591 物件頁 | F30: 信義全球物件頁 | G30: 591 物件頁 | H30: 傑森愛華清單 第3頁 | I30: 591 物件頁 | J30: 信義全球物件頁 | K30: 591 物件頁 | L30: 591 物件頁 | M30: 傑森愛華清單 第1頁 | N30: 591 物件頁 | O30: 591 物件頁 | P30: 591 物件頁 | Q30: 591 物件頁 | R30: 信義全球物件頁 | S30: 591 物件頁 | T30: 591 物件頁
C31: 591 物件頁（9/30 已下架） | D31: 591 房仲提供案 | E31: 591 同戶（葛林威） | F31: 大樓介紹（findoffice） | G31: 傑森愛華清單 第1頁 | H31: 大樓介紹（findoffice） | I31: 591 同戶（兆淇） | J31: 591 物件頁 | K31: 傑森愛華清單 第2頁 | L31: 傑森愛華清單 第2頁 | M31: 推定大樓照片（好房網31張） | Q31: 591 21812612（易信） | R31: 591 物件頁
E32: 大樓照片（好房網18張） | G32: 591 大樓頁 | L32: 大樓照片（好房網19張）
E33: 傑森愛華清單 第3頁

Sheet C_待確認清單
A1: 分級 | B1: 案號 | C1: 案名 | D1: 缺什麼 | E1: 要問誰 | F1: 建議問題
A2: 第一優先 | B2: S05 | C2: 建國北路二段 10F（大辦公室＋大倉儲） | D2: 租金稅別未寫 | E2: 張聰仁 信義房屋投資二部 0939-738-856 | F2: 租金是含稅還是未稅？
A3: 第一優先 | B3: S05 | C3: 建國北路二段 10F（大辦公室＋大倉儲） | D3: 廁所老舊需整修 | E3: 張聰仁 信義房屋投資二部 0939-738-856 | F3: 廁所整修可否由房東在交屋前完成？若由我方整修，可否以免租期或租金折讓抵？
A4: 第二優先 | B4: N04 | C4: 信義大樓 10F | D4: 591 48萬刊登已下架（9/30），現存刊登為信義 577,885（超過55萬） | E4: 傑森愛華 張先生 0931-330-823 | F4: 請書面確認
A5: 第二優先 | B5: N04 | C5: 信義大樓 10F | D5: 租金稅別未寫 | E5: 傑森愛華 張先生 0931-330-823 | F5: 租金是含稅還是未稅？
A6: 第二優先 | B6: N04 | C6: 信義大樓 10F | D6: 兩方報價不同 | E6: 傑森愛華 張先生 0931-330-823 | F6: 同一層信義房屋報57.8萬、591報48萬，哪個是現行條件？是否同一戶？
A7: 第二優先 | B7: C | C7: 旭寶大樓 5F | D7: 只能租4年（之後都更） | E7: 尚揚 王智平 0917-154-083；591 呂育瑄 0919-219-331 | F7: 都更時程：何時啟動？4年後可否續租或優先承租？提前解約條款與搬遷補償？裝潢攤提以4年計
A8: 第二優先 | B8: C | C8: 旭寶大樓 5F | D8: 廁所老舊需整修 | E8: 尚揚 王智平 0917-154-083；591 呂育瑄 0919-219-331 | F8: 廁所整修可否由房東在交屋前完成？若由我方整修，可否以免租期或租金折讓抵？
A9: 第二優先 | B9: N02 | C9: 廣成大廈 4F | D9: 租金是否含稅、是否含管理費：物調表／傑森愛華／591 三方說法不同，需書面確認 | E9: 尚揚 陳威翰 0906-118-677；591 楊小姐 02-27415343#36；591 葛林威 林小姐 0984-002-297 | F9: 請書面確認
A10: 第二優先 | B10: N02 | C10: 廣成大廈 4F | D10: 廁所需現勘 | E10: 尚揚 陳威翰 0906-118-677；591 楊小姐 02-27415343#36；591 葛林威 林小姐 0984-002-297 | F10: 看屋時請拍廁所與茶水間；確認是否為本層專用、男女分廁、何時整修過
A11: 第二優先 | B11: N01 | C11: 南海開發大樓 5F | D11: 管理費只有區間（2.5萬～3萬），無確切金額 | E11: 尚揚 陳威翰 0906-118-677；兆淇 鄭先生 0960-539-161；傑森愛華 張先生 0931-330823 | F11: 請書面確認
A12: 第二優先 | B12: N01 | C12: 南海開發大樓 5F | D12: 廁所需現勘 | E12: 尚揚 陳威翰 0906-118-677；兆淇 鄭先生 0960-539-161；傑森愛華 張先生 0931-330823 | F12: 看屋時請拍廁所與茶水間；確認是否為本層專用、男女分廁、何時整修過
... A55: 待確認實坪 | B55: N27 | C55: 南京東路五段 3F（南京三民站） | D55: 廁所需現勘 | E55: 易信國際 王先生 0955-866-400 | F55: 看屋時請拍廁所與茶水間；確認是否為本層專用、男女分廁、何時整修過

Sheet D_捷運距離
A1: 案號 | B1: 案名 | C1: 最近綠紅藍站 | D1: 路線 | E1: 距離(m) | F1: 步行(分) | G1: 其他較近站（非綠紅藍） | H1: 依據 | I1: 計算方式
A2: S05 | B2: 建國北路二段 10F（大辦公室＋大倉儲） | C2: 松江南京 | D2: 綠 | E2: 530 | F2: =IF(E2="","",ROUNDUP(E2*1.3/80,0)) -> 9 | H2: 信義全球物件座標 | I2: 座標直線距離（站點座標見下方）
A3: N04 | B3: 信義大樓 10F | C3: 象山 | D3: 紅 | E3: 950 | F3: =IF(E3="","",ROUNDUP(E3*1.3/80,0)) -> 16 | H3: 同信義大樓座標 | I3: 座標直線距離（站點座標見下方）
A4: C | B4: 旭寶大樓 5F | C4: 忠孝敦化 | D4: 藍 | E4: 570 | F4: =IF(E4="","",ROUNDUP(E4*1.3/80,0)) -> 10 | H4: Google地圖：敦化南路一段25號 | I4: 座標直線距離（站點座標見下方）
A5: N02 | B5: 廣成大廈 4F | C5: 小南門 | D5: 綠 | E5: 380 | F5: =IF(E5="","",ROUNDUP(E5*1.3/80,0)) -> 7 | H5: Google地圖：延平南路189號 | I5: 座標直線距離（站點座標見下方）
A6: S12 | B6: 全球人壽信義大樓 21F | C6: 象山 | D6: 紅 | E6: 950 | F6: =IF(E6="","",ROUNDUP(E6*1.3/80,0)) -> 16 | H6: 信義全球物件座標 | I6: 座標直線距離（站點座標見下方）
A7: N01 | B7: 南海開發大樓 5F | C7: 中正紀念堂 | D7: 紅綠 | E7: 150 | F7: =IF(E7="","",ROUNDUP(E7*1.3/80,0)) -> 3 | H7: Google地圖：南海路20號 | I7: 座標直線距離（站點座標見下方）
A8: N05 | B8: 信義大樓 8F | C8: 象山 | D8: 紅 | E8: 950 | F8: =IF(E8="","",ROUNDUP(E8*1.3/80,0)) -> 16 | H8: 同信義大樓座標 | I8: 座標直線距離（站點座標見下方）
A9: N08 | B9: 松江路 3F（松江南京站） | C9: 松江南京 | D9: 綠 | E9: 156 | F9: =IF(E9="","",ROUNDUP(E9*1.3/80,0)) -> 3 | H9: 591 物件頁寫明 | I9: 採物件頁寫明的距離
A10: S11 | B10: 八德大樓 5F（出租285.67坪） | C10: 忠孝復興 | D10: 藍 | E10: 620 | F10: =IF(E10="","",ROUNDUP(E10*1.3/80,0)) -> 11 | H10: 信義全球物件座標 | I10: 座標直線距離（站點座標見下方）
A11: N10 | B11: 光復北路11巷 2F（南京三民站） | C11: 南京三民 | D11: 綠 | E11: 88 | F11: =IF(E11="","",ROUNDUP(E11*1.3/80,0)) -> 2 | H11: 591 物件頁寫明 | I11: 採物件頁寫明的距離
A12: N11 | B12: 旭寶大樓 4F | C12: 忠孝敦化 | D12: 藍 | E12: 570 | F12: =IF(E12="","",ROUNDUP(E12*1.3/80,0)) -> 10 | H12: 同旭寶大樓座標 | I12: 座標直線距離（站點座標見下方）
A13: J18 | B13: 忠孝東路四段×延吉街 4F | C13: 國父紀念館 | D13: 藍 | E13: 300 | F13: =IF(E13="","",ROUNDUP(E13*1.3/80,0)) -> 5 | H13: 忠孝東路四段×延吉街口（清單未給門牌） | I13: 座標直線距離（站點座標見下方）
... A16: N06 | B16: 忠孝東路一段 2F（善導寺站） | C16: 善導寺 | D16: 藍 | E16: 119 | F16: =IF(E16="","",ROUNDUP(E16*1.3/80,0)) -> 2 | H16: 591 物件頁寫明 | I16: 採物件頁寫明的距離
A17: N15 | B17: 民生東路二段 6F（仲介稱使用約226坪） | C17: 未確認 | F17: =IF(E17="","",ROUNDUP(E17*1.3/80,0)) | G17: 行天宮(橘) 188m | H17: 591 只寫橘線行天宮站153～188m；綠紅藍線最近站距離未確認 | I17: 無法計算
A18: S06 | B18: 八德大樓 7F（出租254.06坪） | C18: 忠孝復興 | D18: 藍 | E18: 620 | F18: =IF(E18="","",ROUNDUP(E18*1.3/80,0)) -> 11 | H18: 信義全球物件座標 | I18: 座標直線距離（站點座標見下方）
A19: N09 | B19: 長春路 8F（松江南京站） | C19: 松江南京 | D19: 綠 | E19: 310 | F19: =IF(E19="","",ROUNDUP(E19*1.3/80,0)) -> 6 | H19: 591 物件頁寫明 | I19: 採物件頁寫明的距離
A20: N27 | B20: 南京東路五段 3F（南京三民站） | C20: 南京三民 | D20: 綠 | E20: 48 | F20: =IF(E20="","",ROUNDUP(E20*1.3/80,0)) -> 1 | H20: 591 物件頁寫明 | I20: 採物件頁寫明的距離
A21: N19 | B21: 信義大樓 5F | C21: 象山 | D21: 紅 | E21: 950 | F21: =IF(E21="","",ROUNDUP(E21*1.3/80,0)) -> 16 | H21: 同信義大樓座標 | I21: 座標直線距離（站點座標見下方）
A22: N20 | B22: 信義大樓 9F | C22: 象山 | D22: 紅 | E22: 950 | F22: =IF(E22="","",ROUNDUP(E22*1.3/80,0)) -> 16 | H22: 同信義大樓座標 | I22: 座標直線距離（站點座標見下方）
A23: S14 | B23: 復興南路稀有大空間地下室 B1 | C23: 忠孝復興 | D23: 藍 | E23: 290 | F23: =IF(E23="","",ROUNDUP(E23*1.3/80,0)) -> 5 | H23: 信義全球物件座標 | I23: 座標直線距離（站點座標見下方）
A24: N18 | B24: 新設工大樓 6C（中山北路三段） | C24: 民權西路 | D24: 紅 | E24: 66 | F24: =IF(E24="","",ROUNDUP(E24*1.3/80,0)) -> 2 | H24: 591 物件頁寫明 | I24: 採物件頁寫明的距離
A25: N21 | B25: 信義大樓 22F | C25: 象山 | D25: 紅 | E25: 950 | F25: =IF(E25="","",ROUNDUP(E25*1.3/80,0)) -> 16 | H25: 同信義大樓座標 | I25: 座標直線距離（站點座標見下方）
A26: S04 | B26: 光復南路大坪數辦公 6F | C26: 國父紀念館 | D26: 藍 | E26: 580 | F26: =IF(E26="","",ROUNDUP(E26*1.3/80,0)) -> 10 | H26: 信義全球物件座標 | I26: 座標直線距離（站點座標見下方）
A27: D | B27: 敦化財經大樓 4F之1 | C27: 未確認 | F27: =IF(E27="","",ROUNDUP(E27*1.3/80,0)) | G27: 中山國中(棕) 404m（591寫明） | H27: 綠紅藍線距離未確認 | I27: 無法計算
A28: S15 | B28: 永春地下大空間店商辦 B1 | C28: 永春 | D28: 藍 | E28: 190 | F28: =IF(E28="","",ROUNDUP(E28*1.3/80,0)) -> 4 | H28: 信義全球物件座標 | I28: 座標直線距離（站點座標見下方）
A29: E | B29: 國泰世華銀行大樓 6F | C29: 忠孝敦化 | D29: 藍 | E29: 440 | F29: =IF(E29="","",ROUNDUP(E29*1.3/80,0)) -> 8 | H29: Google地圖：仁愛路四段85號 | I29: 座標直線距離（站點座標見下方）
A30: S03 | B30: 敦北長城大樓 3F | C30: 台北小巨蛋 | D30: 綠 | E30: 400 | F30: =IF(E30="","",ROUNDUP(E30*1.3/80,0)) -> 7 | H30: 信義全球物件座標 | I30: 座標直線距離（站點座標見下方）
A31: N17 | B31: 松哖大樓 2F | C31: 未確認 | F31: =IF(E31="","",ROUNDUP(E31*1.3/80,0)) | G31: 行天宮(橘) 約185～299m | H31: 物調表「捷運站：小巨蛋站(1)」疑為範本未改；591 寫行天宮(橘)185～299m | I31: 無法計算
A32: N26 | B32: 安和路一段 11F | C32: 忠孝敦化 | D32: 藍 | E32: 255 | F32: =IF(E32="","",ROUNDUP(E32*1.3/80,0)) -> 5 | H32: 住商物件頁寫明 | I32: 採物件頁寫明的距離
A33: F | B33: 友聯大樓 5F | C33: 南京三民 | D33: 綠 | E33: 380 | F33: =IF(E33="","",ROUNDUP(E33*1.3/80,0)) -> 7 | H33: Google地圖：南京東路五段89號 | I33: 座標直線距離（站點座標見下方）
A34: A | B34: 安敦國際大樓 7F | C34: 忠孝敦化 | D34: 藍 | E34: 185 | F34: =IF(E34="","",ROUNDUP(E34*1.3/80,0)) -> 4 | H34: 591物件頁寫明 | I34: 採物件頁寫明的距離
A35: B | B35: 中鼎大樓 15F之1 | C35: 信義安和 | D35: 紅 | E35: 510 | F35: =IF(E35="","",ROUNDUP(E35*1.3/80,0)) -> 9 | H35: 信義全球物件座標(中鼎大樓) | I35: 座標直線距離（站點座標見下方）
A36: J15 | B36: 敦化南路2段(中鼎大樓 77號22樓) 22F 230坪 | C36: 信義安和 | D36: 紅 | E36: 510 | F36: =IF(E36="","",ROUNDUP(E36*1.3/80,0)) -> 9 | H36: 同中鼎大樓(信義全球座標) | I36: 座標直線距離（站點座標見下方）
A37: J12 | B37: 敦化南路2段 (中鼎大樓 77號2樓) 2F 222坪 | C37: 信義安和 | D37: 紅 | E37: 510 | F37: =IF(E37="","",ROUNDUP(E37*1.3/80,0)) -> 9 | H37: 同中鼎大樓(信義全球座標) | I37: 座標直線距離（站點座標見下方）
A38: S07 | B38: 明水路營業用商辦 4F | C38: 台北小巨蛋 | D38: 綠 | E38: 3310 | F38: =IF(E38="","",ROUNDUP(E38*1.3/80,0)) -> 54 | G38: 大直(棕) 500m | H38: 信義全球物件座標 | I38: 座標直線距離（站點座標見下方）
A39: Y2 | B39: 家美金融大樓 15F | C39: 永春 | D39: 藍 | E39: 200 | F39: =IF(E39="","",ROUNDUP(E39*1.3/80,0)) -> 4 | H39: 信義全球物件座標(家美金融) | I39: 座標直線距離（站點座標見下方）
A40: G | B40: 白宮企業大樓 5F | C40: 台北小巨蛋 | D40: 綠 | E40: 390 | F40: =IF(E40="","",ROUNDUP(E40*1.3/80,0)) -> 7 | H40: Google地圖：南京東路三段346號白宮企業大樓 | I40: 座標直線距離（站點座標見下方）
A41: J07 | B41: 仁愛路4段近復興南路 (鴻霖大樓 25號10樓之2) 10F 210坪 | C41: 忠孝復興 | D41: 藍 | E41: 370 | F41: =IF(E41="","",ROUNDUP(E41*1.3/80,0)) -> 7 | H41: Google地圖：仁愛路四段25號鴻霖大廈 | I41: 座標直線距離（站點座標見下方）
A42: J16 | B42: 八德路近復興北路 (中影八德大樓 八德路二段260號2樓全層) 2F 200坪 | C42: 忠孝復興 | D42: 藍 | E42: 630 | F42: =IF(E42="","",ROUNDUP(E42*1.3/80,0)) -> 11 | H42: Google地圖：八德路二段256～260號中影八德大樓 | I42: 座標直線距離（站點座標見下方）
A43: I | B43: 光復北路新大樓 5F | C43: 南京三民 | D43: 綠 | E43: 450 | F43: =IF(E43="","",ROUNDUP(E43*1.3/80,0)) -> 8 | H43: 信義全球物件座標 | I43: 座標直線距離（站點座標見下方）
A44: S08 | B44: 國票大樓 15F C | C44: 台北小巨蛋 | D44: 綠 | E44: 3440 | F44: =IF(E44="","",ROUNDUP(E44*1.3/80,0)) -> 56 | G44: 劍南路(棕) 250m | H44: 信義全球物件座標 | I44: 座標直線距離（站點座標見下方）
A45: W10 | B45: 松山路 7F | C45: 未確認 | F45: =IF(E45="","",ROUNDUP(E45*1.3/80,0)) | H45: 門牌未揭露，無法計算 | I45: 無法計算
A46: W13 | B46: 林森北路 6F | C46: 未確認 | F46: =IF(E46="","",ROUNDUP(E46*1.3/80,0)) | H46: 門牌未揭露，無法計算 | I46: 無法計算
A47: N24 | B47: 星勢力大樓 4F（大直） | C47: 未確認 | F47: =IF(E47="","",ROUNDUP(E47*1.3/80,0)) | G47: 大直(棕) 428m | H47: 591 寫棕線大直428m | I47: 無法計算
A48: W03 | B48: 明水路（大直） 4F | C48: 台北小巨蛋 | D48: 綠 | E48: 3310 | F48: =IF(E48="","",ROUNDUP(E48*1.3/80,0)) -> 54 | G48: 大直(棕) 500m | H48: 同 S07 明水路物件（HouseWeb同戶） | I48: 座標直線距離（站點座標見下方）
A49: W02 | B49: 八德路四段 9F | C49: 未確認 | F49: =IF(E49="","",ROUNDUP(E49*1.3/80,0)) | H49: 門牌未揭露，無法計算 | I49: 無法計算
A50: J11 | B50: 八德路vs龍江路 2F 220坪 | C50: 忠孝復興 | D50: 藍 | E50: 660 | F50: =IF(E50="","",ROUNDUP(E50*1.3/80,0)) -> 11 | H50: 八德路×龍江路口（清單未給門牌） | I50: 座標直線距離（站點座標見下方）
A51: W06 | B51: 明水路（大直） 4F | C51: 台北小巨蛋 | D51: 綠 | E51: 3310 | F51: =IF(E51="","",ROUNDUP(E51*1.3/80,0)) -> 54 | G51: 大直(棕) 500m | H51: 同明水路大樓（推定，HouseWeb未給門牌） | I51: 座標直線距離（站點座標見下方）
A52: W11 | B52: 光復南路 7F | C52: 南京三民 | D52: 綠 | E52: 659 | F52: =IF(E52="","",ROUNDUP(E52*1.3/80,0)) -> 11 | H52: 591/HouseWeb同戶 | I52: 採物件頁寫明的距離
A53: H | B53: 光復南路 7F | C53: 南京三民 | D53: 綠 | E53: 659 | F53: =IF(E53="","",ROUNDUP(E53*1.3/80,0)) -> 11 | H53: 591物件頁寫明 | I53: 採物件頁寫明的距離
A54: J01 | B54: 信義路5段(環球) 18F 201坪 | C54: 象山 | D54: 紅 | E54: 510 | F54: =IF(E54="","",ROUNDUP(E54*1.3/80,0)) -> 9 | H54: 同環球世貿（S13座標，清單未給門牌） | I54: 座標直線距離（站點座標見下方）
A55: J02 | B55: 南京東路5段近三民站 5F 204坪 | C55: 未確認 | F55: =IF(E55="","",ROUNDUP(E55*1.3/80,0)) | H55: 門牌未揭露，無法計算 | I55: 無法計算
A56: W07 | B56: 明水路（大直） 3F | C56: 台北小巨蛋 | D56: 綠 | E56: 3310 | F56: =IF(E56="","",ROUNDUP(E56*1.3/80,0)) -> 54 | G56: 大直(棕) 500m | H56: 同明水路大樓（推定，HouseWeb未給門牌） | I56: 座標直線距離（站點座標見下方）
A57: N22 | B57: 建國北路三段 2F（合併物件） | C57: 未確認 | F57: =IF(E57="","",ROUNDUP(E57*1.3/80,0)) | G57: 行天宮(橘) 486m | H57: 591 只寫橘線行天宮486m；綠紅藍線不在步行範圍（未確認距離） | I57: 無法計算
A58: J09 | B58: 敦化北路VS民生東路 2F 211坪 | C58: 台北小巨蛋 | D58: 綠 | E58: 760 | F58: =IF(E58="","",ROUNDUP(E58*1.3/80,0)) -> 13 | G58: 中山國中(棕) 570m | H58: 敦化北路×民生東路口（清單未給門牌） | I58: 座標直線距離（站點座標見下方）
A59: J06 | B59: 中山北路1段近市民大道 9F 209坪 | C59: 台北車站 | D59: 紅藍 | E59: 390 | F59: =IF(E59="","",ROUNDUP(E59*1.3/80,0)) -> 7 | H59: 中山北路一段×市民大道口（清單未給門牌） | I59: 座標直線距離（站點座標見下方）
A60: W04 | B60: 植福路（大直） 9F | C60: 未確認 | F60: =IF(E60="","",ROUNDUP(E60*1.3/80,0)) | H60: 門牌未揭露，無法計算 | I60: 無法計算
A61: Y1 | B61: 安敦國際大樓 14F | C61: 忠孝敦化 | D61: 藍 | E61: 260 | F61: =IF(E61="","",ROUNDUP(E61*1.3/80,0)) -> 5 | H61: 同安敦國際大樓(信義全球座標) | I61: 座標直線距離（站點座標見下方）
A62: N34 | B62: 民權西路 5F（民權西路站） | C62: 民權西路 | D62: 紅 | E62: 164 | F62: =IF(E62="","",ROUNDUP(E62*1.3/80,0)) -> 3 | H62: 591 物件頁寫明 | I62: 採物件頁寫明的距離
A63: W01 | B63: 敦南商圈（路名未揭露） | C63: 未確認 | F63: =IF(E63="","",ROUNDUP(E63*1.3/80,0)) | H63: 門牌未揭露，無法計算 | I63: 無法計算
A64: N30 | B64: 敦化南路二段 15F（信義安和站） | C64: 信義安和 | D64: 紅 | E64: 760 | F64: =IF(E64="","",ROUNDUP(E64*1.3/80,0)) -> 13 | G64: 科技大樓(棕) 540m | H64: 591 物件頁地圖座標（概略） | I64: 座標直線距離（站點座標見下方）
A65: N31 | B65: 健康路 8F（南京三民／小巨蛋站） | C65: 台北小巨蛋 | D65: 綠 | E65: 180 | F65: =IF(E65="","",ROUNDUP(E65*1.3/80,0)) -> 3 | H65: 591 物件頁寫明 | I65: 採物件頁寫明的距離
A66: J13 | B66: 民生東路VS建國北路 2*F 225坪 | C66: 松江南京 | D66: 綠 | E66: 780 | F66: =IF(E66="","",ROUNDUP(E66*1.3/80,0)) -> 13 | G66: 行天宮(橘) 510m | H66: 民生東路×建國北路口（清單未給門牌） | I66: 座標直線距離（站點座標見下方）
A67: J04 | B67: 民生東路3段vs復興北路 11F 205坪 | C67: 南京復興 | D67: 綠 | E67: 620 | F67: =IF(E67="","",ROUNDUP(E67*1.3/80,0)) -> 11 | G67: 中山國中(棕) 340m | H67: 民生東路三段×復興北路口（清單未給門牌） | I67: 座標直線距離（站點座標見下方）
A68: J05 | B68: 民生東路3段vs復興北路 3F 205坪 | C68: 南京復興 | D68: 綠 | E68: 620 | F68: =IF(E68="","",ROUNDUP(E68*1.3/80,0)) -> 11 | G68: 中山國中(棕) 340m | H68: 民生東路三段×復興北路口（清單未給門牌） | I68: 座標直線距離（站點座標見下方）
A69: J03 | B69: 中山北路近市民大道 17F 204坪 | C69: 台北車站 | D69: 紅藍 | E69: 390 | F69: =IF(E69="","",ROUNDUP(E69*1.3/80,0)) -> 7 | H69: 中山北路一段×市民大道口（清單未給門牌） | I69: 座標直線距離（站點座標見下方）
A70: W08 | B70: 中山北路一段 17F | C70: 台北車站 | D70: 紅藍 | E70: 390 | F70: =IF(E70="","",ROUNDUP(E70*1.3/80,0)) -> 7 | H70: 中山北路一段×市民大道口（HouseWeb未給門牌） | I70: 座標直線距離（站點座標見下方）
A71: J10 | B71: 安和路一段 (即安敦國際大樓17F) 17F 214坪 | C71: 忠孝敦化 | D71: 藍 | E71: 260 | F71: =IF(E71="","",ROUNDUP(E71*1.3/80,0)) -> 5 | H71: 同安敦國際大樓(信義全球座標) | I71: 座標直線距離（站點座標見下方）
A72: N32 | B72: 南京東路三段 9F（南京復興站） | C72: 南京復興 | D72: 綠 | E72: 175 | F72: =IF(E72="","",ROUNDUP(E72*1.3/80,0)) -> 3 | H72: 591 物件頁寫明 | I72: 採物件頁寫明的距離
A73: J08 | B73: 南京東路近龍江路 8F 210坪 | C73: 南京復興 | D73: 綠 | E73: 320 | F73: =IF(E73="","",ROUNDUP(E73*1.3/80,0)) -> 6 | H73: 南京東路×龍江路口（清單未給門牌） | I73: 座標直線距離（站點座標見下方）
A74: N29 | B74: 健康路 3F（台北小巨蛋站） | C74: 台北小巨蛋 | D74: 綠 | E74: 94 | F74: =IF(E74="","",ROUNDUP(E74*1.3/80,0)) -> 2 | H74: 591 物件頁寫明 | I74: 採物件頁寫明的距離
A75: N23 | B75: 民權東路三段 9F | C75: 未確認 | F75: =IF(E75="","",ROUNDUP(E75*1.3/80,0)) | G75: 中山國中(棕) 138m | H75: 591 寫棕線中山國中138m；綠紅藍線距離未確認 | I75: 無法計算
A76: J14 | B76: 民生東路近敦化北路 8F 226坪 | C76: 台北小巨蛋 | D76: 綠 | E76: 760 | F76: =IF(E76="","",ROUNDUP(E76*1.3/80,0)) -> 13 | G76: 中山國中(棕) 570m | H76: 民生東路×敦化北路口（清單未給門牌） | I76: 座標直線距離（站點座標見下方）
A77: N16 | B77: 環亞大樓 11F（南京東路三段） | C77: 台北小巨蛋 | D77: 綠 | F77: =IF(E77="","",ROUNDUP(E77*1.3/80,0)) | H77: 好房網寫步行可達，距離未給 | I77: 無法計算
A78: S13 | B78: 環球世貿 10F | C78: 象山 | D78: 紅 | E78: 510 | F78: =IF(E78="","",ROUNDUP(E78*1.3/80,0)) -> 9 | H78: 信義全球物件座標 | I78: 座標直線距離（站點座標見下方）
A79: N33 | B79: 菸廠路 8F（國父紀念館站・松菸旁） | C79: 國父紀念館 | D79: 藍 | E79: 274 | F79: =IF(E79="","",ROUNDUP(E79*1.3/80,0)) -> 5 | H79: 591 物件頁寫明 | I79: 採物件頁寫明的距離
A80: J17 | B80: 市民大道3段近復興南路 8F 257坪 | C80: 忠孝復興 | D80: 藍 | E80: 370 | F80: =IF(E80="","",ROUNDUP(E80*1.3/80,0)) -> 7 | H80: 市民大道三段×復興南路口（清單未給門牌） | I80: 座標直線距離（站點座標見下方）
A81: N28 | B81: 民生東路三段 8F（中山國中站） | C81: 南京復興 | D81: 綠 | E81: 1070 | F81: =IF(E81="","",ROUNDUP(E81*1.3/80,0)) -> 18 | G81: 中山國中(棕) 140m | H81: 591 物件頁地圖座標（概略） | I81: 座標直線距離（站點座標見下方）
A84: 站點座標（綠紅藍＋其他）
A85: 站名 | B85: 緯度 | C85: 經度 | D85: 路線
A86: 南京復興 | B86: 25.052079 | C86: 121.54401 | D86: 綠／棕
A87: 忠孝復興 | B87: 25.041622 | C87: 121.54378 | D87: 藍／棕
A88: 松江南京 | B88: 25.051982 | C88: 121.53308 | D88: 綠／橘
A89: 忠孝新生 | B89: 25.04236 | C89: 121.5329 | D89: 藍／橘
A90: 國父紀念館 | B90: 25.041378 | C90: 121.55752 | D90: 藍
A91: 信義安和 | B91: 25.033271 | C91: 121.55296 | D91: 紅
A92: 大安 | B92: 25.0332 | C92: 121.54353 | D92: 紅／棕
A93: 南京三民 | B93: 25.051429 | C93: 121.56386 | D93: 綠
A94: 台北小巨蛋 | B94: 25.051668 | C94: 121.55188 | D94: 綠
A95: 中山國中 | B95: 25.06078 | C95: 121.54421 | D95: 棕
A96: 行天宮 | B96: 25.05972 | C96: 121.53318 | D96: 橘
A97: 市政府 | B97: 25.041237 | C97: 121.56656 | D97: 藍
... A115: 民權西路 | B115: 25.062179 | C115: 121.51969 | D115: 紅／橘

Sheet E_591篩選紀錄
A1: 591 商辦出租：台北市 中正／中山／松山／大安／信義，坪數≥220、月租20～55萬；列表共116筆（2026-09-24），逐筆對應如下。591「坪數」多為權狀（多筆物件頁註明「廣告坪數為權狀坪數」）。
A2: 591編號 | B2: 坪數(591) | C2: 樓層 | D2: 區-路段 | E2: 捷運(591原文) | F2: 租金(591原文) | G2: 對應案號／處理 | H2: 分級 | I2: 連結
A3: 21263746 | B3: 220.8 | C3: 7F/18F | D3: 大安-安和路一段 | E3: 忠孝敦化345m | F3: 400,000 | G3: A | H3: 不符合 | I3: 開啟
A4: 21553763 | B4: 220.8 | C4: 7F/18F | D4: 大安-安和路一段 | E4: 忠孝敦化320m | F4: 400,000含車位 | G4: A | H4: 不符合 | I4: 開啟
A5: 21596085 | B5: 220.8 | C5: 7F/18F | D5: 大安-安和路一段 | E5: 忠孝敦化185m | F5: 400,000 | G5: A | H5: 不符合 | I5: 開啟
A6: 21686336 | B6: 221 | C6: 7F/18F | D6: 大安-安和路一段 | E6: 忠孝敦化164m | F6: 400,000 | G6: A | H6: 不符合 | I6: 開啟
A7: 22034644 | B7: 220.8 | C7: 7F/18F | D7: 大安-安和路一段 | E7: 忠孝敦化185m | F7: 380,952含車位 | G7: A | H7: 不符合 | I7: 開啟
A8: 21112784 | B8: 282 | C8: 5F/12F | D8: 松山-敦化南路一段 | E8: 忠孝敦化126m | F8: 450,000 | G8: C | H8: 第二優先 | I8: 開啟
A9: 21546970 | B9: 282.1 | C9: 5F/12F | D9: 松山-敦化南路一段 | E9: 忠孝敦化129m | F9: 450,000 | G9: C | H9: 第二優先 | I9: 開啟
A10: 21588465 | B10: 282.1 | C10: 5F/12F | D10: 松山-敦化南路一段 | E10: 忠孝敦化123m | F10: 450,000 | G10: C | H10: 第二優先 | I10: 開啟
A11: 21524253 | B11: 251 | C11: 5F/12F | D11: 松山-敦化南路一段（敦南綠景） | E11: 忠孝敦化72m | F11: 450,000含6車位 | G11: C（同戶：21530071標題同為敦南綠景） | H11: 第二優先 | I11: 開啟
A12: 21530071 | B12: 282.1 | C12: 5F/12F | D12: 松山-敦化南路一段（旭寶大樓） | E12: 台北小巨蛋517m | F12: 450,000含車位 | G12: C（房仲提供） | H12: 第二優先 | I12: 開啟
A13: 20380770 | B13: 220.1 | C13: 4F/11F | D13: 松山-敦化北路 | E13: 中山國中321m | F13: 386,839 | G13: D | H13: 不符合 | I13: 開啟
A14: 20880830 | B14: 220.1 | C14: 4F/11F | D14: 松山-敦化北路 | E14: 民生敦化路口36m | F14: 386,839 | G14: D | H14: 不符合 | I14: 開啟
... A118: 21994974 | B118: 224.2 | C118: 14F/18F | D118: 大安-安和路一段 | E118: 忠孝敦化340m | F118: 490,000 | G118: Y1 | H118: 不符合 | I118: 開啟
A119: 合計 | B119: =COUNTA(A3:A118) -> 116

Sheet F_尚揚物調表
A1: 尚揚國際不動產提供（使用者資料夾「辦公室 尚揚國際不動產提供」）7 份物調表原文數字
A2: 案號 | B2: 大樓 | C2: 地址 | D2: 樓層 | E2: 建物登記／權狀 | F2: 主建物+附屬 | G2: 公設比 | H2: 月租(含稅) | I2: 管理費 | J2: 押金/最短租期 | K2: 竣工／使照 | L2: 使用分區 | M2: 空調 | N2: 其他原文 | O2: 承辦人 | P2: 備註
A3: N01 | B3: 南海開發大樓 | C3: 中正區南海路20號5樓 | D3: 5F/10F(B1) | E3: 260.98 | F3: 228.34 | G3: 12.51% | H3: 465849 | I3: 實支實付(約2.5萬~3萬) | J3: 2個月/2年 | K3: 77/9/22 | L3: 第參種商業區 | M3: 獨立空調 | N3: 附坡平車位二個；中正紀念堂站約2分鐘 | O3: 陳威翰 0906-118-677 | P3: 資料夾名稱寫「南港開發大樓5樓」
A4: N02 | B4: 廣成大廈 | C4: 中正區延平南路189號4樓~之5 | D4: 4F/7F(B2) | E4: 326.85 | F4: 253.54 | G4: 22.43% | H4: 491000 | I4: 31,053 | J4: 3個月/2年 | K4: 70/1/5 | L4: 第參種住宅區 | M4: 中央空調(08-22)，可自加獨立空調 | N4: 固定車位7,000/非固定5,000(含稅)；小南門站約7分鐘 | O4: 陳威翰 0906-118677
A5: S12 | B5: 全球人壽信義大樓 | C5: 松仁路277號21樓 | D5: 21F/23F(B4) | E5: 265.82 | F5: 241.8 | G5: 9.04 | H5: 502400 | I5: 39,873 (150/坪) | J5: 3個月/2年 | K5: 86/5/25 | L5: 第三種住宅區 | M5: 中央空調(8-18加班再議) | N5: 交通只寫公車；精裝修 | O5: 劉于上 0938-254-324（原文）
A6: D | B6: 敦化財經大樓 | C6: 松山區敦化北路214號4F之1 | D6: 4F/11F(B2) | E6: 220.07 | F6: 207.21 | G6: 5.84% | H6: 440140 | I6: 48,415 | J6: 3個月/2年 | K6: 80/7/31 | L6: 敦化南北路特定區 | M6: 中央空調(08-18)＋可加獨冷 | N6: 坡道平面「8,0000」另租（原文）；南京復興、中山國中10分鐘 | O6: 張正修 0937-519-365
A7: S03 | B7: 敦北長城大樓 | C7: 松山區八德路三段32號3樓 | D7: 3F/16F(B4) | E7: 225.83 | F7: 201.29 | G7: 10.87% | H7: 513892 | I7: 27,100 | J7: 2個月/2年 | K7: 使執81/02/17 | L7: 第參種商業區 | M7: 中央空調(07-19) | N7: 稅別：個人；坡平另租6,000+500；小巨蛋站 | O7: 劉于上 0938-259-324
A8: N17 | B8: 松哖大樓 | C8: 中山區民生東路二段161號+163號2樓 | D8: 2F/12F(B1) | E8: 227.15 | F8: 198.26 | G8: 12.72% | H8: 500000 | I8: 40,000 | J8: 3個月/2年 | K8: 使執77/03/07 | L8: 第參種商業區 | M8: 中央空調(08-18，加班200/H) | N8: 稅別：個人；坡平另租7,000-8,000；表內「捷運站：小巨蛋站(1)」疑誤植 | O8: 劉品汯 0901-407-026
A9: S04 | B9: 光復大樓（分割） | C9: 松山區光復南路35號6樓(分割) | D9: 6F/11F(B1) | E9: 原文「21.38坪」（疑漏字） | F9: 211.38 | G9: 0% | H9: 401622 | I9: 18,000 | J9: 「32個月」/2年（原文，疑為2個月） | K9: 66/8/2 | L9: 第三種商業區 | M9: 獨立空調 | N9: 國父紀念館站9分鐘；現有隔間裝潢 | O9: 劉于上 0938-259-324 | P9: 原文數字有誤植，需確認

Sheet G_傑森愛華0923清單
A1: 傑森愛華國際物業顧問行（張先生 0931-330823）2026/9/23 出租物件清單報表，全部為未稅價；含稅＝×1.05（公式）
A2: 頁 | B2: 地點 | C2: 樓層 | D2: 坪數 | E2: 租金(未稅) | F2: 單價 | G2: 含稅(公式) | H2: 附註（原文） | I2: 對應案號 | J2: 連結
A3: 1 | B3: 南海路近羅斯福路 | C3: 5 | D3: 261 | E3: 443000 | F3: 1700 | G3: =E3*(1+0_條件與假設!$B$9) -> 465150 | H3: 純辦、正方、一層一戶、近捷運、適百業 | I3: N01 | J3: 第1頁
A4: 1 | B4: 南京東路(環亞樓上) | C4: 11 | D4: 262 | E4: 524000 | F4: 2000 | G4: =E4*(1+0_條件與假設!$B$9) -> 550200 | H4: A級純辦，知名地標大樓，獨立空調，近雙捷運，open，視野佳 | I4: N16 | J4: 第1頁
A5: 1 | B5: 忠孝東路4段VS延吉街 | C5: 4 | D5: 276 | E5: 480000 | F5: 1739 | G5: =E5*(1+0_條件與假設!$B$9) -> 504000 | H5: 地標帷幕純辦、OPEN、毛丕，捷運旁、商業區、適百業、多門牌（可分割） | I5: J18 | J5: 第1頁
A6: 2 | B6: 南京東路5段 | C6: 14 | D6: 280 | E6: 655500 | F6: 2341 | G6: =E6*(1+0_條件與假設!$B$9) -> 688275 | H6: 帷幕純辦 正方 挑高 獨立空調，不租醫美 補習班 直銷 | I6: 不符：超過55萬 | J6: 第2頁
A7: 2 | B7: 敦化南路近市民大道 | C7: 4 | D7: 282 | E7: 507600 | F7: 1800 | G7: =E7*(1+0_條件與假設!$B$9) -> 532980 | H7: 純辦 稀有低公設 可至捷運 外商區 全層使用 屋況佳 開發票 最多3年約都更 | I7: N11 | J7: 第2頁
A8: 2 | B8: 光復北路11巷 | C8: 2 | D8: 283 | E8: 509400 | F8: 1800 | G8: =E8*(1+0_條件與假設!$B$9) -> 534870 | H8: A級純辦 漂亮入口 外觀佳 正方 停車方便 | I8: N10 | J8: 第2頁
A9: 2 | B9: 南京東路3段近復興北路 | C9: 5 | D9: 290 | E9: 600000 | F9: 2069 | G9: =E9*(1+0_條件與假設!$B$9) -> 630000 | H9: 地標純辦、OPEN、一層一戶、正方、捷運旁、商業區、適百業 | I9: 不符：超過55萬 | J9: 第2頁
A10: 2 | B10: 信義路5段(環球) | C10: 10 | D10: 296 | E10: 651200 | F10: 2200 | G10: =E10*(1+0_條件與假設!$B$9) -> 683760 | H10: 氣派A級純辦 宏偉大廳 正方 挑高 視野佳 | I10: 不符：超過55萬 | J10: 第2頁
A11: 2 | B11: 光復北路(台北瓦斯) | C11: 6 | D11: 324 | E11: 567000 | F11: 1750 | G11: =E11*(1+0_條件與假設!$B$9) -> 595350 | H11: A級純辦 漂亮入口 外觀佳 正方 停車方便 | I11: 不符：超過55萬 | J11: 第2頁
A12: 3 | B12: 延平南路 | C12: 4 | D12: 327 | E12: 491000 | F12: 1500 | G12: =E12*(1+0_條件與假設!$B$9) -> 515550 | H12: 一層一户，稀有辦公，近捷運，24小時保全 | I12: N02 | J12: 第3頁
A13: 3 | B13: 松仁路(信義區) | C13: 8 | D13: 331 | E13: 513050 | F13: 1550 | G13: =E13*(1+0_條件與假設!$B$9) -> 538702.5 | H13: 純辦、三邊臨馬路，地標大樓，公設低，大理石外牆 | I13: N05 | J13: 第3頁
A14: 3 | B14: 重慶北路2段 | C14: 11 | D14: 334 | E14: 551100 | F14: 1650 | G14: =E14*(1+0_條件與假設!$B$9) -> 578655 | H14: 帷幕純辦，入口佳，正方 挑高 有隔間 | I14: 不符：大同區（非指定五區）且超過55萬 | J14: 第3頁
A15: 3 | B15: 泉州街 | C15: 3 | D15: 371 | E15: 686350 | F15: 1850 | G15: =E15*(1+0_條件與假設!$B$9) -> 720667.5 | H15: 純辦、格局方正、採光佳 低公設，交通便利 | I15: 不符：超過55萬 | J15: 第3頁

Sheet H_搜尋範圍與來源
A1: 網站 | B1: 搜尋條件／方式 | C1: 結果筆數 | D1: 涵蓋情形 | E1: 備註
A2: 591 商用（business.591.com.tw） | B2: 辦公出租；台北市 中正/中山/松山/大安/信義；坪數≥220；租金20～55萬（list?kind=6&section=1,3,4,5,7&acreage=220_&price=200000_550000） | C2: 116 | D2: 全部對應（見E頁） | E2: 591 分頁排序會變動，已多次翻頁取聯集；逐一開啟候選物件頁讀原文
A3: 信義房屋（sinyi.com.tw） | B3: rent/list/Taipei-city/100-104-105-106-110-zip/office-use/150-up-area（另查200-up） | C3: 150坪以上 78 筆 | D3: 全部看過 | E3: 主建物／附屬／共有分項完整；物件連結改用 sinyiglobal.com（使用者網路打不開 sinyi.com.tw）
A4: 永慶房屋（rent.yungching.com.tw） | B4: 辦公用途；台北市 五區 | C4: 172 | D4: 全部看過（Chrome） | E4: ≥200坪僅安敦14F、家美15F、B1／1樓店辦，無新增符合案
A5: 住商不動產（hbhousing.com.tw） | B5: 五區逐頁：中正50、中山103、松山66、大安142、信義74 | C5: 435 | D5: 逐頁看過 | E5: 含大家房屋（g開頭）物件；無新增符合案（安和11F 實坪192.04）
A6: 大家房屋（great-home.com.tw） | B6: 列表需 JS；物件頁可開 | C6: — | D6: 透過住商列表間接涵蓋 | E6: 使用者提供網址 great-home.com.tw 為大家房屋
A7: 安家地產（mysweethome.com.tw） | B7: 列表需 JS，篩選器無法以程式套用；台北出租 791 筆（含住家） | C7: 791（未篩） | D7: 未完成篩選 | E7: 使用者提供網址 mysweethome.com.tw 為安家地產；台灣房屋官網 twhg.com.tw 對本工具回 403
A8: 尚揚國際（使用者資料夾） | B8: 7 份物調表＋照片 | C8: 7 | D8: 全部讀取 | E8: 見F頁；照片已放入儀表板
A9: 傑森愛華（使用者上傳 PDF） | B9: 2026/9/23 出租物件清單報表 | C9: 13 | D9: 全部讀取 | E9: 見G頁；並上網查大樓名稱與照片
A10: 房仲提供 591 21530071 | B10: 旭寶大樓 5F | C10: 1 | D10: 已納入（C） | E10: 使用坪數282.06；物調表實用255.38，以物調表為準
